Workbook

Sheet Cover
B2: Finance Operations Automation Project
B3: Reconciliation · AP · AR · Compliance · Risk · Procurement · Forecasting · Reporting Automation
B4: Data coverage: Jan 2025 – Jul 2026 | Built for Excel (legacy, non-365 compatible — no XLOOKUP / Power Query)
B6: How this workbook is organized
B8: Cover / Assumptions | C8: This sheet + editable As-Of date and risk thresholds (yellow cells).
B9: Raw Data (9 grey tabs) | C9: Untouched source tables: Vendor/Customer Master, POs, GRNs, AP Invoices, AP Payments, Bank Statement, AR Invoices, AR Receipts.
B10: 3Way_Match | C10: Reconciliation Module 1: PO ↔ GRN ↔ Invoice matching, flags amount mismatches & goods invoiced but not received.
B11: Bank_Reconciliation | C11: Reconciliation Module 2: AP payments ↔ bank statement matching, flags unmatched items and timing/amount differences.
B12: AP_Aging | C12: Outstanding AP invoices bucketed 0-30/31-60/61-90/90+ days.
B13: Duplicate_Payments | C13: Flags invoices paid more than once.
B14: DPO_Summary | C14: Days Payable Outstanding — headline metric + monthly trend.
B15: AR_Aging | C15: Outstanding AR invoices bucketed 0-30/31-60/61-90/90+ days.
B16: AR_Partial_Unpaid | C16: Flags short-paid and fully overdue customer invoices.
B17: DSO_Summary | C17: Days Sales Outstanding — headline metric + monthly trend.
B18: SoD_Check | C18: Segregation-of-Duties: flags POs where requester = approver.
B19: RCM | C19: Risk & Control Matrix — internal-audit style pass/fail summary, auto-updating from the modules above.
... B25: KPI_Dashboard | C25: One-page summary with headline KPIs and charts.
B27: See the separate Project Documentation (Word) and How-To-Run Guide for full methodology and the VBA automation setup.

Sheet Assumptions
A1: Assumptions & Editable Inputs
A2: Yellow cells are inputs — change them and every module recalculates.
A4: Assumption | B4: Value | C4: Notes
A5: Reporting As-Of Date | B5: 2026-07-31 | C5: Used by every Aging / DPO / DSO / Forecast module as 'today'. Data runs through Jul-2026 in the source file.
A6: Match Tolerance ($) | B6: 1 | C6: Dollar variance allowed before a 3-way-match / bank line is flagged as a mismatch.
A7: Large Transaction Threshold ($) | B7: 10000 | C7: Risk scoring: amount at/above this adds high points.
A8: Elevated Transaction Threshold ($) | B8: 5000 | C8: Risk scoring: amount at/above this (but below Large) adds medium points.
A9: New Vendor Window (days) | B9: 180 | C9: Vendor is 'new' if onboarded within this many days of the transaction/report date.
A10: Higher-Risk Countries | B10: India, UAE, Singapore | C10: Illustrative geography flag for the AML-style score — replace with your AML policy's actual list.
A11: AP Aging Buckets (days) | B11: 0-30 / 31-60 / 61-90 / 90+ | C11: Standard 4-bucket aging, matches AR for consistency.

Sheet Vendor_Master
A1: Vendor_ID | B1: Vendor_Name | C1: Category | D1: Country | E1: Onboarding_Date | F1: Bank_Account_Last4 | G1: Payment_Terms_Days
A2: V1001 | B2: Figueroa and Sons | C2: Travel & Logistics | D2: USA | E2: 45572 | F2: 1409 | G2: 45
A3: V1002 | B3: Garcia, Yang and Gardner | C3: Office Supplies | D3: UK | E3: 44914 | F3: 3286 | G3: 15
A4: V1003 | B4: Johnson and Sons | C4: Travel & Logistics | D4: UAE | E4: 45495 | F4: 9935 | G4: 15
A5: V1004 | B5: Johnson, Gonzalez and Santos | C5: Marketing | D5: Germany | E5: 44929 | F5: 1520 | G5: 15
A6: V1005 | B6: Cole LLC | C6: IT Services | D6: UK | E6: 45423 | F6: 4811 | G6: 15
A7: V1006 | B7: Blake and Sons | C7: Marketing | D7: UK | E7: 45841 | F7: 9928 | G7: 60
A8: V1007 | B8: Ramirez-Lewis | C8: Office Supplies | D8: Germany | E8: 45665 | F8: 5557 | G8: 15
A9: V1008 | B9: Davis Inc | C9: Software Licensing | D9: Canada | E9: 45769 | F9: 3615 | G9: 60
A10: V1009 | B10: Munoz-Roman | C10: Professional Services | D10: India | E10: 45129 | F10: 3547 | G10: 30
A11: V1010 | B11: Martinez, Nielsen and Miller | C11: Software Licensing | D11: India | E11: 45715 | F11: 2674 | G11: 15
A12: V1011 | B12: Montgomery, Hensley and Ray | C12: Facilities | D12: USA | E12: 45025 | F12: 6881 | G12: 45
A13: V1012 | B13: Stanley LLC | C13: Marketing | D13: India | E13: 45675 | F13: 1711 | G13: 60
... A41: V1040 | B41: Santos, Kim and Holmes | C41: Office Supplies | D41: India | E41: 45192 | F41: 3646 | G41: 15

Sheet Customer_Master
A1: Customer_ID | B1: Customer_Name | C1: Country | D1: Credit_Terms_Days | E1: Industry
A2: C2001 | B2: Wright Inc | C2: Singapore | D2: 45 | E2: Technology
A3: C2002 | B3: Smith-Spencer | C3: USA | D3: 15 | E3: Healthcare
A4: C2003 | B4: Robinson, Jones and Welch | C4: Canada | D4: 45 | E4: Manufacturing
A5: C2004 | B5: Jones Inc | C5: USA | D5: 30 | E5: Financial Services
A6: C2005 | B6: Jones-Young | C6: USA | D6: 15 | E6: Technology
A7: C2006 | B7: Washington, Ryan and Cummings | C7: Canada | D7: 15 | E7: Financial Services
A8: C2007 | B8: Johnston, Sanchez and Kennedy | C8: Canada | D8: 30 | E8: Manufacturing
A9: C2008 | B9: Lee-Davis | C9: UAE | D9: 60 | E9: Financial Services
A10: C2009 | B10: Gomez-Jenkins | C10: UK | D10: 45 | E10: Financial Services
A11: C2010 | B11: Brown, Valdez and Lucas | C11: Canada | D11: 60 | E11: Manufacturing
A12: C2011 | B12: Powell LLC | C12: Singapore | D12: 30 | E12: Healthcare
A13: C2012 | B13: Wright and Sons | C13: Germany | D13: 45 | E13: Technology
... A31: C2030 | B31: Sanchez, Wheeler and Harvey | C31: Canada | D31: 15 | E31: Manufacturing

Sheet Purchase_Orders
A1: PO_ID | B1: Vendor_ID | C1: PO_Date | D1: PO_Amount | E1: Category | F1: Requested_By | G1: Approved_By
A2: PO10001 | B2: V1020 | C2: 46091 | D2: 1309.32 | E2: Travel & Logistics | F2: Shirley Suarez | G2: Evelyn Galvan
A3: PO10002 | B3: V1034 | C3: 45782 | D3: 1749.66 | E3: Marketing | F3: Jimmy Murillo | G3: Shannon Walker
A4: PO10003 | B4: V1014 | C4: 45670 | D4: 2691.35 | E4: Marketing | F4: John Whitehead | G4: Evelyn Galvan
A5: PO10004 | B5: V1040 | C5: 45763 | D5: 889.24 | E5: Office Supplies | F5: James Powers | G5: Julia Torres
A6: PO10005 | B6: V1022 | C6: 45836 | D6: 3058.04 | E6: Facilities | F6: Deborah Figueroa | G6: Sharon Cherry
A7: PO10006 | B7: V1040 | C7: 46129 | D7: 1359.77 | E7: Office Supplies | F7: Deborah Figueroa | G7: Marc Moore
A8: PO10007 | B8: V1040 | C8: 46184 | D8: 3708.39 | E8: Office Supplies | F8: Richard Henson | G8: Evelyn Galvan
A9: PO10008 | B9: V1015 | C9: 45810 | D9: 6081.19 | E9: Travel & Logistics | F9: Anna Henderson | G9: Julia Torres
A10: PO10009 | B10: V1018 | C10: 46007 | D10: 6038.81 | E10: Facilities | F10: Denise Jacobs | G10: Marc Moore
A11: PO10010 | B11: V1005 | C11: 45875 | D11: 1250.19 | E11: IT Services | F11: Kevin Mills | G11: Shannon Walker
A12: PO10011 | B12: V1024 | C12: 46192 | D12: 760.24 | E12: Software Licensing | F12: John Whitehead | G12: Sharon Cochran
A13: PO10012 | B13: V1035 | C13: 45950 | D13: 15002.72 | E13: Marketing | F13: Christine Wright | G13: Julia Torres
... A851: PO10850 | B851: V1014 | C851: 45970 | D851: 4104.49 | E851: Marketing | F851: Stephen Mckee | G851: Shannon Walker

Sheet Goods_Receipt_Notes
A1: GRN_ID | B1: PO_ID | C1: Receipt_Date | D1: Received_Amount
A2: GRN20486 | B2: PO10487 | C2: 45690 | D2: 542.8
A3: GRN20559 | B3: PO10560 | C3: 45986 | D3: 829.86
A4: GRN20185 | B4: PO10186 | C4: 46079 | D4: 3351.54
A5: GRN20806 | B5: PO10807 | C5: 46100 | D5: 830.55
A6: GRN20493 | B6: PO10494 | C6: 45912 | D6: 607.61
A7: GRN20298 | B7: PO10299 | C7: 45957 | D7: 8486.94
A8: GRN20842 | B8: PO10843 | C8: 45703 | D8: 2224.01
A9: GRN20776 | B9: PO10777 | C9: 45863 | D9: 1467.37
A10: GRN20752 | B10: PO10753 | C10: 46125 | D10: 4765.29
A11: GRN20755 | B11: PO10756 | C11: 46079 | D11: 305.02
A12: GRN20008 | B12: PO10009 | C12: 46013 | D12: 6038.81
A13: GRN20819 | B13: PO10820 | C13: 45738 | D13: 424.45
... A791: GRN20466 | B791: PO10467 | C791: 45968 | D791: 2324.66

Sheet Vendor_Invoices_AP
A1: Invoice_ID | B1: PO_ID | C1: Vendor_ID | D1: Invoice_Date | E1: Invoice_Amount | F1: Due_Date
A2: INV30001 | B2: PO10001 | C2: V1020 | D2: 46109 | E2: 1417.41 | F2: 46139
A3: INV30002 | B3: PO10002 | C3: V1034 | D3: 45803 | E3: 1749.66 | F3: 45848
A4: INV30003 | B4: PO10003 | C4: V1014 | D4: 45676 | E4: 2691.35 | F4: 45706
A5: INV30004 | B5: PO10004 | C5: V1040 | D5: 45783 | E5: 889.24 | F5: 45798
A6: INV30005 | B6: PO10005 | C6: V1022 | D6: 45861 | E6: 3058.04 | F6: 45891
A7: INV30006 | B7: PO10006 | C7: V1040 | D7: 46132 | E7: 1359.77 | F7: 46147
A8: INV30007 | B8: PO10007 | C8: V1040 | D8: 46188 | E8: 3708.39 | F8: 46203
A9: INV30008 | B9: PO10008 | C9: V1015 | D9: 45833 | E9: 6081.19 | F9: 45863
A10: INV30009 | B10: PO10009 | C10: V1018 | D10: 46020 | E10: 6038.81 | F10: 46050
A11: INV30010 | B11: PO10010 | C11: V1005 | D11: 45878 | E11: 1466.07 | F11: 45893
A12: INV30011 | B12: PO10011 | C12: V1024 | D12: 46210 | E12: 760.24 | F12: 46270
A13: INV30012 | B13: PO10012 | C13: V1035 | D13: 45975 | E13: 15002.72 | F13: 45990
... A882: INV30881 | B882: PO10850 | C882: V1014 | D882: 45973 | E882: 4104.49 | F882: 46003

Sheet Payment_Log_AP
A1: Payment_ID | B1: Invoice_ID | C1: Vendor_ID | D1: Payment_Date | E1: Payment_Amount | F1: Approved_By
A2: PAY40001 | B2: INV30001 | C2: V1020 | D2: 46142 | E2: 1417.41 | F2: Shannon Walker
A3: PAY40002 | B3: INV30002 | C3: V1034 | D3: 45805 | E3: 1749.66 | F3: Richard Rodriguez
A4: PAY40003 | B4: INV30003 | C4: V1014 | D4: 45683 | E4: 2691.35 | F4: Julia Torres
A5: PAY40004 | B5: INV30004 | C5: V1040 | D5: 45805 | E5: 889.24 | F5: Julia Torres
A6: PAY40005 | B6: INV30005 | C6: V1022 | D6: 45883 | E6: 3058.04 | F6: Sierra Johnson
A7: PAY40006 | B7: INV30006 | C7: V1040 | D7: 46160 | E7: 1359.77 | F7: Evelyn Galvan
A8: PAY40007 | B8: INV30007 | C8: V1040 | D8: 46193 | E8: 3708.39 | F8: Evelyn Galvan
A9: PAY40008 | B9: INV30008 | C9: V1015 | D9: 45859 | E9: 6081.19 | F9: Evelyn Galvan
A10: PAY40009 | B10: INV30010 | C10: V1005 | D10: 45885 | E10: 1466.07 | F10: Richard Rodriguez
A11: PAY40010 | B11: INV30012 | C11: V1035 | D11: 45989 | E11: 15002.72 | F11: Richard Rodriguez
A12: PAY40011 | B12: INV30013 | C12: V1016 | D12: 46196 | E12: 911.91 | F12: Sharon Cochran
A13: PAY40012 | B13: INV30014 | C13: V1002 | D13: 45753 | E13: 1222.88 | F13: Shannon Walker
... A753: PAY40752 | B753: INV30881 | C753: V1014 | D753: 46002 | E753: 4104.49 | F753: Shannon Walker

Sheet Bank_Statement
A1: Bank_Txn_ID | B1: Date | C1: Amount | D1: Description | E1: Matched_Payment_ID
A2: BNK50001 | B2: 46144 | C2: -1417.41 | D2: PMT-V1020 | E2: PAY40001
A3: BNK50002 | B3: 45807 | C3: -1749.66 | D3: PMT-V1034 | E3: PAY40002
A4: BNK50003 | B4: 45683 | C4: -2691.35 | D4: PMT-V1014 | E4: PAY40003
A5: BNK50004 | B5: 45808 | C5: -889.24 | D5: PMT-V1040 | E5: PAY40004
A6: BNK50005 | B6: 45886 | C6: -3058.04 | D6: PMT-V1022 | E6: PAY40005
A7: BNK50006 | B7: 46161 | C7: -1359.77 | D7: PMT-V1040 | E7: PAY40006
A8: BNK50007 | B8: 46195 | C8: -3708.39 | D8: PMT-V1040 | E8: PAY40007
A9: BNK50008 | B9: 45861 | C9: -6081.19 | D9: PMT-V1015 | E9: PAY40008
A10: BNK50009 | B10: 45885 | C10: -1466.07 | D10: PMT-V1005 | E10: PAY40009
A11: BNK50010 | B11: 45992 | C11: -15002.72 | D11: PMT-V1035 | E11: PAY40010
A12: BNK50011 | B12: 46197 | C12: -911.91 | D12: PMT-V1016 | E12: PAY40011
A13: BNK50012 | B13: 45753 | C13: -1222.88 | D13: PMT-V1002 | E13: PAY40012
... A753: BNK50752 | B753: 46002 | C753: -4104.49 | D753: PMT-V1014 | E753: PAY40752
A754: BNK50753 | B754: 46044 | C754: -20.43 | D754: Bank Service Charge
A755: BNK50754 | B755: 45885 | C755: -142.45 | D755: FX Adjustment
A756: BNK50755 | B756: 45720 | C756: -198.25 | D756: Bank Service Charge
A757: BNK50756 | B757: 45669 | C757: -39.26 | D757: FX Adjustment
A758: BNK50757 | B758: 45834 | C758: -198.13 | D758: Bank Service Charge
A759: BNK50758 | B759: 46094 | C759: -432.76 | D759: Wire Transfer Fee
A760: BNK50759 | B760: 45994 | C760: -227.57 | D760: Bank Service Charge
A761: BNK50760 | B761: 46111 | C761: -110.81 | D761: Bank Service Charge
A762: BNK50761 | B762: 46159 | C762: -333.36 | D762: FX Adjustment
A763: BNK50762 | B763: 45706 | C763: -35.61 | D763: Wire Transfer Fee
A764: BNK50763 | B764: 46118 | C764: -25.34 | D764: Wire Transfer Fee
A765: BNK50764 | B765: 45790 | C765: -469.24 | D765: FX Adjustment
... A783: BNK50782 | B783: 45765 | C783: -475.97 | D783: Bank Service Charge

Sheet Customer_Invoices_AR
A1: AR_Invoice_ID | B1: Customer_ID | C1: Billing_Date | D1: Invoice_Amount | E1: Due_Date
A2: ARI60001 | B2: C2003 | C2: 45986 | D2: 6493.93 | E2: 46031
A3: ARI60002 | B3: C2014 | C3: 46072 | D3: 3250.9 | E3: 46102
A4: ARI60003 | B4: C2010 | C4: 46015 | D4: 715.25 | E4: 46075
A5: ARI60004 | B5: C2030 | C5: 45754 | D5: 3252.02 | E5: 45769
A6: ARI60005 | B6: C2014 | C6: 46079 | D6: 6622.57 | E6: 46109
A7: ARI60006 | B7: C2004 | C7: 45927 | D7: 8576.41 | E7: 45957
A8: ARI60007 | B8: C2027 | C8: 46069 | D8: 4091.62 | E8: 46129
A9: ARI60008 | B9: C2009 | C9: 46072 | D9: 673.49 | E9: 46117
A10: ARI60009 | B10: C2027 | C10: 45902 | D10: 4452.11 | E10: 45962
A11: ARI60010 | B11: C2008 | C11: 46161 | D11: 6127.03 | E11: 46221
A12: ARI60011 | B12: C2001 | C12: 45965 | D12: 3666.96 | E12: 46010
A13: ARI60012 | B13: C2016 | C13: 46004 | D13: 8288.62 | E13: 46034
... A601: ARI60600 | B601: C2021 | C601: 45706 | D601: 3855.14 | E601: 45766

Sheet Cash_Receipts_AR
A1: Receipt_ID | B1: AR_Invoice_ID | C1: Customer_ID | D1: Receipt_Date | E1: Receipt_Amount
A2: ARR70001 | B2: ARI60002 | C2: C2014 | D2: 46095 | E2: 1523.91
A3: ARR70002 | B3: ARI60003 | C3: C2010 | D3: 46049 | E3: 715.25
A4: ARR70003 | B4: ARI60004 | C4: C2030 | D4: 45766 | E4: 3252.02
A5: ARR70004 | B5: ARI60005 | C5: C2014 | D5: 46115 | E5: 6622.57
A6: ARR70005 | B6: ARI60006 | C6: C2004 | D6: 45970 | E6: 2625.84
A7: ARR70006 | B7: ARI60007 | C7: C2027 | D7: 46106 | E7: 4091.62
A8: ARR70007 | B8: ARI60008 | C8: C2009 | D8: 46083 | E8: 673.49
A9: ARR70008 | B9: ARI60009 | C9: C2027 | D9: 45935 | E9: 2365.68
A10: ARR70009 | B10: ARI60010 | C10: C2008 | D10: 46185 | E10: 6127.03
A11: ARR70010 | B11: ARI60011 | C11: C2001 | D11: 45982 | E11: 3666.96
A12: ARR70011 | B12: ARI60012 | C12: C2016 | D12: 46034 | E12: 8288.62
A13: ARR70012 | B13: ARI60013 | C13: C2025 | D13: 45999 | E13: 1708.27
... A503: ARR70502 | B503: ARI60600 | C503: C2021 | D503: 45739 | E503: 3855.14

Sheet 3Way_Match
A1: Reconciliation Module 1 — Three-Way Match (PO ↔ GRN ↔ Invoice)
A2: Base table: Purchase_Orders. Flags goods invoiced without receipt and amount mismatches beyond the tolerance in Assumptions!B6.
A4: PO_ID | B4: Vendor_ID | C4: Vendor_Name | D4: PO_Date | E4: PO_Amount | F4: GRN_Received_Amount | G4: Invoice_Amount | H4: Received_Flag | I4: Invoiced_Flag | J4: PO_vs_GRN_Variance | K4: PO_vs_Invoice_Variance | L4: Exception_Flag
A5: =Purchase_Orders!A2 -> PO10001 | B5: =Purchase_Orders!B2 -> V1020 | C5: =IFERROR(INDEX(Vendor_Master!$B$2:$B$41,MATCH(B5,Vendor_Master!$A$2:$A$41,0)),"Unknown Vendor") -> Lewis-Porter | D5: =Purchase_Orders!C2 -> 46091 | E5: =Purchase_Orders!D2 -> 1309.32 | F5: =SUMIFS(Goods_Receipt_Notes!$D$2:$D$791,Goods_Receipt_Notes!$B$2:$B$791,A5) -> 1309.32 | G5: =SUMIFS(Vendor_Invoices_AP!$E$2:$E$882,Vendor_Invoices_AP!$B$2:$B$882,A5) -> 1417.41 | H5: =IF(F5=0,"Not Received","Received") -> Received | I5: =IF(G5=0,"Not Invoiced","Invoiced") -> Invoiced | J5: =E5-F5 -> 0 | K5: =E5-G5 -> -108.09 | L5: =IF(OR(AND(I5="Invoiced",H5="Not Received"),AND(F5>0,ABS(J5)>Assumptions!$B$6),AND(G5>0,ABS(K5)>Assumptions!$B$6)),"EXCEPTION","OK") -> EXCEPTION
A6: =Purchase_Orders!A3 -> PO10002 | B6: =Purchase_Orders!B3 -> V1034 | C6: =IFERROR(INDEX(Vendor_Master!$B$2:$B$41,MATCH(B6,Vendor_Master!$A$2:$A$41,0)),"Unknown Vendor") -> Koch-Decker | D6: =Purchase_Orders!C3 -> 45782 | E6: =Purchase_Orders!D3 -> 1749.66 | F6: =SUMIFS(Goods_Receipt_Notes!$D$2:$D$791,Goods_Receipt_Notes!$B$2:$B$791,A6) -> 1749.66 | G6: =SUMIFS(Vendor_Invoices_AP!$E$2:$E$882,Vendor_Invoices_AP!$B$2:$B$882,A6) -> 1749.66 | H6: =IF(F6=0,"Not Received","Received") -> Received | I6: =IF(G6=0,"Not Invoiced","Invoiced") -> Invoiced | J6: =E6-F6 -> 0 | K6: =E6-G6 -> 0 | L6: =IF(OR(AND(I6="Invoiced",H6="Not Received"),AND(F6>0,ABS(J6)>Assumptions!$B$6),AND(G6>0,ABS(K6)>Assumptions!$B$6)),"EXCEPTION","OK") -> OK
A7: =Purchase_Orders!A4 -> PO10003 | B7: =Purchase_Orders!B4 -> V1014 | C7: =IFERROR(INDEX(Vendor_Master!$B$2:$B$41,MATCH(B7,Vendor_Master!$A$2:$A$41,0)),"Unknown Vendor") -> Flowers, Martin and Kelly | D7: =Purchase_Orders!C4 -> 45670 | E7: =Purchase_Orders!D4 -> 2691.35 | F7: =SUMIFS(Goods_Receipt_Notes!$D$2:$D$791,Goods_Receipt_Notes!$B$2:$B$791,A7) -> 1676.95 | G7: =SUMIFS(Vendor_Invoices_AP!$E$2:$E$882,Vendor_Invoices_AP!$B$2:$B$882,A7) -> 2691.35 | H7: =IF(F7=0,"Not Received","Received") -> Received | I7: =IF(G7=0,"Not Invoiced","Invoiced") -> Invoiced | J7: =E7-F7 -> 1014.4 | K7: =E7-G7 -> 0 | L7: =IF(OR(AND(I7="Invoiced",H7="Not Received"),AND(F7>0,ABS(J7)>Assumptions!$B$6),AND(G7>0,ABS(K7)>Assumptions!$B$6)),"EXCEPTION","OK") -> EXCEPTION
A8: =Purchase_Orders!A5 -> PO10004 | B8: =Purchase_Orders!B5 -> V1040 | C8: =IFERROR(INDEX(Vendor_Master!$B$2:$B$41,MATCH(B8,Vendor_Master!$A$2:$A$41,0)),"Unknown Vendor") -> Santos, Kim and Holmes | D8: =Purchase_Orders!C5 -> 45763 | E8: =Purchase_Orders!D5 -> 889.24 | F8: =SUMIFS(Goods_Receipt_Notes!$D$2:$D$791,Goods_Receipt_Notes!$B$2:$B$791,A8) -> 889.24 | G8: =SUMIFS(Vendor_Invoices_AP!$E$2:$E$882,Vendor_Invoices_AP!$B$2:$B$882,A8) -> 889.24 | H8: =IF(F8=0,"Not Received","Received") -> Received | I8: =IF(G8=0,"Not Invoiced","Invoiced") -> Invoiced | J8: =E8-F8 -> 0 | K8: =E8-G8 -> 0 | L8: =IF(OR(AND(I8="Invoiced",H8="Not Received"),AND(F8>0,ABS(J8)>Assumptions!$B$6),AND(G8>0,ABS(K8)>Assumptions!$B$6)),"EXCEPTION","OK") -> OK
A9: =Purchase_Orders!A6 -> PO10005 | B9: =Purchase_Orders!B6 -> V1022 | C9: =IFERROR(INDEX(Vendor_Master!$B$2:$B$41,MATCH(B9,Vendor_Master!$A$2:$A$41,0)),"Unknown Vendor") -> Burgess-Patterson | D9: =Purchase_Orders!C6 -> 45836 | E9: =Purchase_Orders!D6 -> 3058.04 | F9: =SUMIFS(Goods_Receipt_Notes!$D$2:$D$791,Goods_Receipt_Notes!$B$2:$B$791,A9) -> 3058.04 | G9: =SUMIFS(Vendor_Invoices_AP!$E$2:$E$882,Vendor_Invoices_AP!$B$2:$B$882,A9) -> 3058.04 | H9: =IF(F9=0,"Not Received","Received") -> Received | I9: =IF(G9=0,"Not Invoiced","Invoiced") -> Invoiced | J9: =E9-F9 -> 0 | K9: =E9-G9 -> 0 | L9: =IF(OR(AND(I9="Invoiced",H9="Not Received"),AND(F9>0,ABS(J9)>Assumptions!$B$6),AND(G9>0,ABS(K9)>Assumptions!$B$6)),"EXCEPTION","OK") -> OK
A10: =Purchase_Orders!A7 -> PO10006 | B10: =Purchase_Orders!B7 -> V1040 | C10: =IFERROR(INDEX(Vendor_Master!$B$2:$B$41,MATCH(B10,Vendor_Master!$A$2:$A$41,0)),"Unknown Vendor") -> Santos, Kim and Holmes | D10: =Purchase_Orders!C7 -> 46129 | E10: =Purchase_Orders!D7 -> 1359.77 | F10: =SUMIFS(Goods_Receipt_Notes!$D$2:$D$791,Goods_Receipt_Notes!$B$2:$B$791,A10) -> 1359.77 | G10: =SUMIFS(Vendor_Invoices_AP!$E$2:$E$882,Vendor_Invoices_AP!$B$2:$B$882,A10) -> 1359.77 | H10: =IF(F10=0,"Not Received","Received") -> Received | I10: =IF(G10=0,"Not Invoiced","Invoiced") -> Invoiced | J10: =E10-F10 -> 0 | K10: =E10-G10 -> 0 | L10: =IF(OR(AND(I10="Invoiced",H10="Not Received"),AND(F10>0,ABS(J10)>Assumptions!$B$6),AND(G10>0,ABS(K10)>Assumptions!$B$6)),"EXCEPTION","OK") -> OK
A11: =Purchase_Orders!A8 -> PO10007 | B11: =Purchase_Orders!B8 -> V1040 | C11: =IFERROR(INDEX(Vendor_Master!$B$2:$B$41,MATCH(B11,Vendor_Master!$A$2:$A$41,0)),"Unknown Vendor") -> Santos, Kim and Holmes | D11: =Purchase_Orders!C8 -> 46184 | E11: =Purchase_Orders!D8 -> 3708.39 | F11: =SUMIFS(Goods_Receipt_Notes!$D$2:$D$791,Goods_Receipt_Notes!$B$2:$B$791,A11) -> 3708.39 | G11: =SUMIFS(Vendor_Invoices_AP!$E$2:$E$882,Vendor_Invoices_AP!$B$2:$B$882,A11) -> 3708.39 | H11: =IF(F11=0,"Not Received","Received") -> Received | I11: =IF(G11=0,"Not Invoiced","Invoiced") -> Invoiced | J11: =E11-F11 -> 0 | K11: =E11-G11 -> 0 | L11: =IF(OR(AND(I11="Invoiced",H11="Not Received"),AND(F11>0,ABS(J11)>Assumptions!$B$6),AND(G11>0,ABS(K11)>Assumptions!$B$6)),"EXCEPTION","OK") -> OK
A12: =Purchase_Orders!A9 -> PO10008 | B12: =Purchase_Orders!B9 -> V1015 | C12: =IFERROR(INDEX(Vendor_Master!$B$2:$B$41,MATCH(B12,Vendor_Master!$A$2:$A$41,0)),"Unknown Vendor") -> Zuniga, Wong and Lynch | D12: =Purchase_Orders!C9 -> 45810 | E12: =Purchase_Orders!D9 -> 6081.19 | F12: =SUMIFS(Goods_Receipt_Notes!$D$2:$D$791,Goods_Receipt_Notes!$B$2:$B$791,A12) -> 0 | G12: =SUMIFS(Vendor_Invoices_AP!$E$2:$E$882,Vendor_Invoices_AP!$B$2:$B$882,A12) -> 6081.19 | H12: =IF(F12=0,"Not Received","Received") -> Not Received | I12: =IF(G12=0,"Not Invoiced","Invoiced") -> Invoiced | J12: =E12-F12 -> 6081.19 | K12: =E12-G12 -> 0 | L12: =IF(OR(AND(I12="Invoiced",H12="Not Received"),AND(F12>0,ABS(J12)>Assumptions!$B$6),AND(G12>0,ABS(K12)>Assumptions!$B$6)),"EXCEPTION","OK") -> EXCEPTION
A13: =Purchase_Orders!A10 -> PO10009 | B13: =Purchase_Orders!B10 -> V1018 | C13: =IFERROR(INDEX(Vendor_Master!$B$2:$B$41,MATCH(B13,Vendor_Master!$A$2:$A$41,0)),"Unknown Vendor") -> Underwood LLC | D13: =Purchase_Orders!C10 -> 46007 | E13: =Purchase_Orders!D10 -> 6038.81 | F13: =SUMIFS(Goods_Receipt_Notes!$D$2:$D$791,Goods_Receipt_Notes!$B$2:$B$791,A13) -> 6038.81 | G13: =SUMIFS(Vendor_Invoices_AP!$E$2:$E$882,Vendor_Invoices_AP!$B$2:$B$882,A13) -> 6038.81 | H13: =IF(F13=0,"Not Received","Received") -> Received | I13: =IF(G13=0,"Not Invoiced","Invoiced") -> Invoiced | J13: =E13-F13 -> 0 | K13: =E13-G13 -> 0 | L13: =IF(OR(AND(I13="Invoiced",H13="Not Received"),AND(F13>0,ABS(J13)>Assumptions!$B$6),AND(G13>0,ABS(K13)>Assumptions!$B$6)),"EXCEPTION","OK") -> OK
A14: =Purchase_Orders!A11 -> PO10010 | B14: =Purchase_Orders!B11 -> V1005 | C14: =IFERROR(INDEX(Vendor_Master!$B$2:$B$41,MATCH(B14,Vendor_Master!$A$2:$A$41,0)),"Unknown Vendor") -> Cole LLC | D14: =Purchase_Orders!C11 -> 45875 | E14: =Purchase_Orders!D11 -> 1250.19 | F14: =SUMIFS(Goods_Receipt_Notes!$D$2:$D$791,Goods_Receipt_Notes!$B$2:$B$791,A14) -> 721.2 | G14: =SUMIFS(Vendor_Invoices_AP!$E$2:$E$882,Vendor_Invoices_AP!$B$2:$B$882,A14) -> 1466.07 | H14: =IF(F14=0,"Not Received","Received") -> Received | I14: =IF(G14=0,"Not Invoiced","Invoiced") -> Invoiced | J14: =E14-F14 -> 528.99 | K14: =E14-G14 -> -215.88 | L14: =IF(OR(AND(I14="Invoiced",H14="Not Received"),AND(F14>0,ABS(J14)>Assumptions!$B$6),AND(G14>0,ABS(K14)>Assumptions!$B$6)),"EXCEPTION","OK") -> EXCEPTION
A15: =Purchase_Orders!A12 -> PO10011 | B15: =Purchase_Orders!B12 -> V1024 | C15: =IFERROR(INDEX(Vendor_Master!$B$2:$B$41,MATCH(B15,Vendor_Master!$A$2:$A$41,0)),"Unknown Vendor") -> Campos Inc | D15: =Purchase_Orders!C12 -> 46192 | E15: =Purchase_Orders!D12 -> 760.24 | F15: =SUMIFS(Goods_Receipt_Notes!$D$2:$D$791,Goods_Receipt_Notes!$B$2:$B$791,A15) -> 760.24 | G15: =SUMIFS(Vendor_Invoices_AP!$E$2:$E$882,Vendor_Invoices_AP!$B$2:$B$882,A15) -> 760.24 | H15: =IF(F15=0,"Not Received","Received") -> Received | I15: =IF(G15=0,"Not Invoiced","Invoiced") -> Invoiced | J15: =E15-F15 -> 0 | K15: =E15-G15 -> 0 | L15: =IF(OR(AND(I15="Invoiced",H15="Not Received"),AND(F15>0,ABS(J15)>Assumptions!$B$6),AND(G15>0,ABS(K15)>Assumptions!$B$6)),"EXCEPTION","OK") -> OK
A16: =Purchase_Orders!A13 -> PO10012 | B16: =Purchase_Orders!B13 -> V1035 | C16: =IFERROR(INDEX(Vendor_Master!$B$2:$B$41,MATCH(B16,Vendor_Master!$A$2:$A$41,0)),"Unknown Vendor") -> Allen PLC | D16: =Purchase_Orders!C13 -> 45950 | E16: =Purchase_Orders!D13 -> 15002.72 | F16: =SUMIFS(Goods_Receipt_Notes!$D$2:$D$791,Goods_Receipt_Notes!$B$2:$B$791,A16) -> 15002.72 | G16: =SUMIFS(Vendor_Invoices_AP!$E$2:$E$882,Vendor_Invoices_AP!$B$2:$B$882,A16) -> 15002.72 | H16: =IF(F16=0,"Not Received","Received") -> Received | I16: =IF(G16=0,"Not Invoiced","Invoiced") -> Invoiced | J16: =E16-F16 -> 0 | K16: =E16-G16 -> 0 | L16: =IF(OR(AND(I16="Invoiced",H16="Not Received"),AND(F16>0,ABS(J16)>Assumptions!$B$6),AND(G16>0,ABS(K16)>Assumptions!$B$6)),"EXCEPTION","OK") -> OK
... A854: =Purchase_Orders!A851 -> PO10850 | B854: =Purchase_Orders!B851 -> V1014 | C854: =IFERROR(INDEX(Vendor_Master!$B$2:$B$41,MATCH(B854,Vendor_Master!$A$2:$A$41,0)),"Unknown Vendor") -> Flowers, Martin and Kelly | D854: =Purchase_Orders!C851 -> 45970 | E854: =Purchase_Orders!D851 -> 4104.49 | F854: =SUMIFS(Goods_Receipt_Notes!$D$2:$D$791,Goods_Receipt_Notes!$B$2:$B$791,A854) -> 4104.49 | G854: =SUMIFS(Vendor_Invoices_AP!$E$2:$E$882,Vendor_Invoices_AP!$B$2:$B$882,A854) -> 4104.49 | H854: =IF(F854=0,"Not Received","Received") -> Received | I854: =IF(G854=0,"Not Invoiced","Invoiced") -> Invoiced | J854: =E854-F854 -> 0 | K854: =E854-G854 -> 0 | L854: =IF(OR(AND(I854="Invoiced",H854="Not Received"),AND(F854>0,ABS(J854)>Assumptions!$B$6),AND(G854>0,ABS(K854)>Assumptions!$B$6)),"EXCEPTION","OK") -> OK

Sheet Bank_Reconciliation
A1: Reconciliation Module 2 — Bank Reconciliation (Payment Log ↔ Bank Statement)
A2: Part A matches every AP payment to the bank statement. Part B (below) finds bank items with no matching payment — timing differences, unexplained fees, or other bank-only activity.
A4: Part A — Payments matched to Bank Statement
A5: Payment_ID | B5: Vendor_ID | C5: Payment_Date | D5: Payment_Amount | E5: Bank_Amount | F5: Bank_Txn_Found | G5: Amount_Diff | H5: Match_Status
A6: =Payment_Log_AP!A2 -> PAY40001 | B6: =Payment_Log_AP!C2 -> V1020 | C6: =Payment_Log_AP!D2 -> 46142 | D6: =Payment_Log_AP!E2 -> 1417.41 | E6: =IFERROR(INDEX(Bank_Statement!$C$2:$C$783,MATCH(A6,Bank_Statement!$E$2:$E$783,0)),"") -> -1417.41 | F6: =IF(E6="","No","Yes") -> Yes | G6: =IF(F6="No","N/A",D6-E6) -> 2834.82 | H6: =IF(F6="No","Unmatched - Investigate",IF(ABS(D6-E6)>Assumptions!$B$6,"Mismatch - Amount Differs","Matched")) -> Mismatch - Amount Differs
A7: =Payment_Log_AP!A3 -> PAY40002 | B7: =Payment_Log_AP!C3 -> V1034 | C7: =Payment_Log_AP!D3 -> 45805 | D7: =Payment_Log_AP!E3 -> 1749.66 | E7: =IFERROR(INDEX(Bank_Statement!$C$2:$C$783,MATCH(A7,Bank_Statement!$E$2:$E$783,0)),"") -> -1749.66 | F7: =IF(E7="","No","Yes") -> Yes | G7: =IF(F7="No","N/A",D7-E7) -> 3499.32 | H7: =IF(F7="No","Unmatched - Investigate",IF(ABS(D7-E7)>Assumptions!$B$6,"Mismatch - Amount Differs","Matched")) -> Mismatch - Amount Differs
A8: =Payment_Log_AP!A4 -> PAY40003 | B8: =Payment_Log_AP!C4 -> V1014 | C8: =Payment_Log_AP!D4 -> 45683 | D8: =Payment_Log_AP!E4 -> 2691.35 | E8: =IFERROR(INDEX(Bank_Statement!$C$2:$C$783,MATCH(A8,Bank_Statement!$E$2:$E$783,0)),"") -> -2691.35 | F8: =IF(E8="","No","Yes") -> Yes | G8: =IF(F8="No","N/A",D8-E8) -> 5382.7 | H8: =IF(F8="No","Unmatched - Investigate",IF(ABS(D8-E8)>Assumptions!$B$6,"Mismatch - Amount Differs","Matched")) -> Mismatch - Amount Differs
A9: =Payment_Log_AP!A5 -> PAY40004 | B9: =Payment_Log_AP!C5 -> V1040 | C9: =Payment_Log_AP!D5 -> 45805 | D9: =Payment_Log_AP!E5 -> 889.24 | E9: =IFERROR(INDEX(Bank_Statement!$C$2:$C$783,MATCH(A9,Bank_Statement!$E$2:$E$783,0)),"") -> -889.24 | F9: =IF(E9="","No","Yes") -> Yes | G9: =IF(F9="No","N/A",D9-E9) -> 1778.48 | H9: =IF(F9="No","Unmatched - Investigate",IF(ABS(D9-E9)>Assumptions!$B$6,"Mismatch - Amount Differs","Matched")) -> Mismatch - Amount Differs
A10: =Payment_Log_AP!A6 -> PAY40005 | B10: =Payment_Log_AP!C6 -> V1022 | C10: =Payment_Log_AP!D6 -> 45883 | D10: =Payment_Log_AP!E6 -> 3058.04 | E10: =IFERROR(INDEX(Bank_Statement!$C$2:$C$783,MATCH(A10,Bank_Statement!$E$2:$E$783,0)),"") -> -3058.04 | F10: =IF(E10="","No","Yes") -> Yes | G10: =IF(F10="No","N/A",D10-E10) -> 6116.08 | H10: =IF(F10="No","Unmatched - Investigate",IF(ABS(D10-E10)>Assumptions!$B$6,"Mismatch - Amount Differs","Matched")) -> Mismatch - Amount Differs
A11: =Payment_Log_AP!A7 -> PAY40006 | B11: =Payment_Log_AP!C7 -> V1040 | C11: =Payment_Log_AP!D7 -> 46160 | D11: =Payment_Log_AP!E7 -> 1359.77 | E11: =IFERROR(INDEX(Bank_Statement!$C$2:$C$783,MATCH(A11,Bank_Statement!$E$2:$E$783,0)),"") -> -1359.77 | F11: =IF(E11="","No","Yes") -> Yes | G11: =IF(F11="No","N/A",D11-E11) -> 2719.54 | H11: =IF(F11="No","Unmatched - Investigate",IF(ABS(D11-E11)>Assumptions!$B$6,"Mismatch - Amount Differs","Matched")) -> Mismatch - Amount Differs
A12: =Payment_Log_AP!A8 -> PAY40007 | B12: =Payment_Log_AP!C8 -> V1040 | C12: =Payment_Log_AP!D8 -> 46193 | D12: =Payment_Log_AP!E8 -> 3708.39 | E12: =IFERROR(INDEX(Bank_Statement!$C$2:$C$783,MATCH(A12,Bank_Statement!$E$2:$E$783,0)),"") -> -3708.39 | F12: =IF(E12="","No","Yes") -> Yes | G12: =IF(F12="No","N/A",D12-E12) -> 7416.78 | H12: =IF(F12="No","Unmatched - Investigate",IF(ABS(D12-E12)>Assumptions!$B$6,"Mismatch - Amount Differs","Matched")) -> Mismatch - Amount Differs
A13: =Payment_Log_AP!A9 -> PAY40008 | B13: =Payment_Log_AP!C9 -> V1015 | C13: =Payment_Log_AP!D9 -> 45859 | D13: =Payment_Log_AP!E9 -> 6081.19 | E13: =IFERROR(INDEX(Bank_Statement!$C$2:$C$783,MATCH(A13,Bank_Statement!$E$2:$E$783,0)),"") -> -6081.19 | F13: =IF(E13="","No","Yes") -> Yes | G13: =IF(F13="No","N/A",D13-E13) -> 12162.38 | H13: =IF(F13="No","Unmatched - Investigate",IF(ABS(D13-E13)>Assumptions!$B$6,"Mismatch - Amount Differs","Matched")) -> Mismatch - Amount Differs
A14: =Payment_Log_AP!A10 -> PAY40009 | B14: =Payment_Log_AP!C10 -> V1005 | C14: =Payment_Log_AP!D10 -> 45885 | D14: =Payment_Log_AP!E10 -> 1466.07 | E14: =IFERROR(INDEX(Bank_Statement!$C$2:$C$783,MATCH(A14,Bank_Statement!$E$2:$E$783,0)),"") -> -1466.07 | F14: =IF(E14="","No","Yes") -> Yes | G14: =IF(F14="No","N/A",D14-E14) -> 2932.14 | H14: =IF(F14="No","Unmatched - Investigate",IF(ABS(D14-E14)>Assumptions!$B$6,"Mismatch - Amount Differs","Matched")) -> Mismatch - Amount Differs
A15: =Payment_Log_AP!A11 -> PAY40010 | B15: =Payment_Log_AP!C11 -> V1035 | C15: =Payment_Log_AP!D11 -> 45989 | D15: =Payment_Log_AP!E11 -> 15002.72 | E15: =IFERROR(INDEX(Bank_Statement!$C$2:$C$783,MATCH(A15,Bank_Statement!$E$2:$E$783,0)),"") -> -15002.72 | F15: =IF(E15="","No","Yes") -> Yes | G15: =IF(F15="No","N/A",D15-E15) -> 30005.44 | H15: =IF(F15="No","Unmatched - Investigate",IF(ABS(D15-E15)>Assumptions!$B$6,"Mismatch - Amount Differs","Matched")) -> Mismatch - Amount Differs
A16: =Payment_Log_AP!A12 -> PAY40011 | B16: =Payment_Log_AP!C12 -> V1016 | C16: =Payment_Log_AP!D12 -> 46196 | D16: =Payment_Log_AP!E12 -> 911.91 | E16: =IFERROR(INDEX(Bank_Statement!$C$2:$C$783,MATCH(A16,Bank_Statement!$E$2:$E$783,0)),"") -> -911.91 | F16: =IF(E16="","No","Yes") -> Yes | G16: =IF(F16="No","N/A",D16-E16) -> 1823.82 | H16: =IF(F16="No","Unmatched - Investigate",IF(ABS(D16-E16)>Assumptions!$B$6,"Mismatch - Amount Differs","Matched")) -> Mismatch - Amount Differs
A17: =Payment_Log_AP!A13 -> PAY40012 | B17: =Payment_Log_AP!C13 -> V1002 | C17: =Payment_Log_AP!D13 -> 45753 | D17: =Payment_Log_AP!E13 -> 1222.88 | E17: =IFERROR(INDEX(Bank_Statement!$C$2:$C$783,MATCH(A17,Bank_Statement!$E$2:$E$783,0)),"") -> -1222.88 | F17: =IF(E17="","No","Yes") -> Yes | G17: =IF(F17="No","N/A",D17-E17) -> 2445.76 | H17: =IF(F17="No","Unmatched - Investigate",IF(ABS(D17-E17)>Assumptions!$B$6,"Mismatch - Amount Differs","Matched")) -> Mismatch - Amount Differs
... A757: =Payment_Log_AP!A753 -> PAY40752 | B757: =Payment_Log_AP!C753 -> V1014 | C757: =Payment_Log_AP!D753 -> 46002 | D757: =Payment_Log_AP!E753 -> 4104.49 | E757: =IFERROR(INDEX(Bank_Statement!$C$2:$C$783,MATCH(A757,Bank_Statement!$E$2:$E$783,0)),"") -> -4104.49 | F757: =IF(E757="","No","Yes") -> Yes | G757: =IF(F757="No","N/A",D757-E757) -> 8208.98 | H757: =IF(F757="No","Unmatched - Investigate",IF(ABS(D757-E757)>Assumptions!$B$6,"Mismatch - Amount Differs","Matched")) -> Mismatch - Amount Differs
A760: Part B — Bank Statement items matched back to Payments
A761: Bank_Txn_ID | B761: Date | C761: Amount | D761: Description | E761: Matched_Payment_ID | F761: Ref_Found_In_AP_Log | G761: Status
A762: =Bank_Statement!A2 -> BNK50001 | B762: =Bank_Statement!B2 -> 46144 | C762: =Bank_Statement!C2 -> -1417.41 | D762: =Bank_Statement!D2 -> PMT-V1020 | E762: =Bank_Statement!E2 -> PAY40001 | F762: =IF(E762="","N/A",IF(COUNTIF(Payment_Log_AP!$A$2:$A$753,E762)>0,"Yes","No")) -> Yes | G762: =IF(E762="","Unexplained Bank Item (fee/other - review)",IF(F762="Yes","Matched","Payment Reference Not Found in AP Log")) -> Matched
A763: =Bank_Statement!A3 -> BNK50002 | B763: =Bank_Statement!B3 -> 45807 | C763: =Bank_Statement!C3 -> -1749.66 | D763: =Bank_Statement!D3 -> PMT-V1034 | E763: =Bank_Statement!E3 -> PAY40002 | F763: =IF(E763="","N/A",IF(COUNTIF(Payment_Log_AP!$A$2:$A$753,E763)>0,"Yes","No")) -> Yes | G763: =IF(E763="","Unexplained Bank Item (fee/other - review)",IF(F763="Yes","Matched","Payment Reference Not Found in AP Log")) -> Matched
A764: =Bank_Statement!A4 -> BNK50003 | B764: =Bank_Statement!B4 -> 45683 | C764: =Bank_Statement!C4 -> -2691.35 | D764: =Bank_Statement!D4 -> PMT-V1014 | E764: =Bank_Statement!E4 -> PAY40003 | F764: =IF(E764="","N/A",IF(COUNTIF(Payment_Log_AP!$A$2:$A$753,E764)>0,"Yes","No")) -> Yes | G764: =IF(E764="","Unexplained Bank Item (fee/other - review)",IF(F764="Yes","Matched","Payment Reference Not Found in AP Log")) -> Matched
A765: =Bank_Statement!A5 -> BNK50004 | B765: =Bank_Statement!B5 -> 45808 | C765: =Bank_Statement!C5 -> -889.24 | D765: =Bank_Statement!D5 -> PMT-V1040 | E765: =Bank_Statement!E5 -> PAY40004 | F765: =IF(E765="","N/A",IF(COUNTIF(Payment_Log_AP!$A$2:$A$753,E765)>0,"Yes","No")) -> Yes | G765: =IF(E765="","Unexplained Bank Item (fee/other - review)",IF(F765="Yes","Matched","Payment Reference Not Found in AP Log")) -> Matched
A766: =Bank_Statement!A6 -> BNK50005 | B766: =Bank_Statement!B6 -> 45886 | C766: =Bank_Statement!C6 -> -3058.04 | D766: =Bank_Statement!D6 -> PMT-V1022 | E766: =Bank_Statement!E6 -> PAY40005 | F766: =IF(E766="","N/A",IF(COUNTIF(Payment_Log_AP!$A$2:$A$753,E766)>0,"Yes","No")) -> Yes | G766: =IF(E766="","Unexplained Bank Item (fee/other - review)",IF(F766="Yes","Matched","Payment Reference Not Found in AP Log")) -> Matched
A767: =Bank_Statement!A7 -> BNK50006 | B767: =Bank_Statement!B7 -> 46161 | C767: =Bank_Statement!C7 -> -1359.77 | D767: =Bank_Statement!D7 -> PMT-V1040 | E767: =Bank_Statement!E7 -> PAY40006 | F767: =IF(E767="","N/A",IF(COUNTIF(Payment_Log_AP!$A$2:$A$753,E767)>0,"Yes","No")) -> Yes | G767: =IF(E767="","Unexplained Bank Item (fee/other - review)",IF(F767="Yes","Matched","Payment Reference Not Found in AP Log")) -> Matched
A768: =Bank_Statement!A8 -> BNK50007 | B768: =Bank_Statement!B8 -> 46195 | C768: =Bank_Statement!C8 -> -3708.39 | D768: =Bank_Statement!D8 -> PMT-V1040 | E768: =Bank_Statement!E8 -> PAY40007 | F768: =IF(E768="","N/A",IF(COUNTIF(Payment_Log_AP!$A$2:$A$753,E768)>0,"Yes","No")) -> Yes | G768: =IF(E768="","Unexplained Bank Item (fee/other - review)",IF(F768="Yes","Matched","Payment Reference Not Found in AP Log")) -> Matched
A769: =Bank_Statement!A9 -> BNK50008 | B769: =Bank_Statement!B9 -> 45861 | C769: =Bank_Statement!C9 -> -6081.19 | D769: =Bank_Statement!D9 -> PMT-V1015 | E769: =Bank_Statement!E9 -> PAY40008 | F769: =IF(E769="","N/A",IF(COUNTIF(Payment_Log_AP!$A$2:$A$753,E769)>0,"Yes","No")) -> Yes | G769: =IF(E769="","Unexplained Bank Item (fee/other - review)",IF(F769="Yes","Matched","Payment Reference Not Found in AP Log")) -> Matched
A770: =Bank_Statement!A10 -> BNK50009 | B770: =Bank_Statement!B10 -> 45885 | C770: =Bank_Statement!C10 -> -1466.07 | D770: =Bank_Statement!D10 -> PMT-V1005 | E770: =Bank_Statement!E10 -> PAY40009 | F770: =IF(E770="","N/A",IF(COUNTIF(Payment_Log_AP!$A$2:$A$753,E770)>0,"Yes","No")) -> Yes | G770: =IF(E770="","Unexplained Bank Item (fee/other - review)",IF(F770="Yes","Matched","Payment Reference Not Found in AP Log")) -> Matched
A771: =Bank_Statement!A11 -> BNK50010 | B771: =Bank_Statement!B11 -> 45992 | C771: =Bank_Statement!C11 -> -15002.72 | D771: =Bank_Statement!D11 -> PMT-V1035 | E771: =Bank_Statement!E11 -> PAY40010 | F771: =IF(E771="","N/A",IF(COUNTIF(Payment_Log_AP!$A$2:$A$753,E771)>0,"Yes","No")) -> Yes | G771: =IF(E771="","Unexplained Bank Item (fee/other - review)",IF(F771="Yes","Matched","Payment Reference Not Found in AP Log")) -> Matched
A772: =Bank_Statement!A12 -> BNK50011 | B772: =Bank_Statement!B12 -> 46197 | C772: =Bank_Statement!C12 -> -911.91 | D772: =Bank_Statement!D12 -> PMT-V1016 | E772: =Bank_Statement!E12 -> PAY40011 | F772: =IF(E772="","N/A",IF(COUNTIF(Payment_Log_AP!$A$2:$A$753,E772)>0,"Yes","No")) -> Yes | G772: =IF(E772="","Unexplained Bank Item (fee/other - review)",IF(F772="Yes","Matched","Payment Reference Not Found in AP Log")) -> Matched
A773: =Bank_Statement!A13 -> BNK50012 | B773: =Bank_Statement!B13 -> 45753 | C773: =Bank_Statement!C13 -> -1222.88 | D773: =Bank_Statement!D13 -> PMT-V1002 | E773: =Bank_Statement!E13 -> PAY40012 | F773: =IF(E773="","N/A",IF(COUNTIF(Payment_Log_AP!$A$2:$A$753,E773)>0,"Yes","No")) -> Yes | G773: =IF(E773="","Unexplained Bank Item (fee/other - review)",IF(F773="Yes","Matched","Payment Reference Not Found in AP Log")) -> Matched
... A1543: =Bank_Statement!A783 -> BNK50782 | B1543: =Bank_Statement!B783 -> 45765 | C1543: =Bank_Statement!C783 -> -475.97 | D1543: =Bank_Statement!D783 -> Bank Service Charge | E1543: =Bank_Statement!E783 -> 0 | F1543: =IF(E1543="","N/A",IF(COUNTIF(Payment_Log_AP!$A$2:$A$753,E1543)>0,"Yes","No")) -> N/A | G1543: =IF(E1543="","Unexplained Bank Item (fee/other - review)",IF(F1543="Yes","Matched","Payment Reference Not Found in AP Log")) -> Unexplained Bank Item (fee/other - review)

Sheet AP_Aging
A1: Accounts Payable — Aging
A2: Base table: Vendor_Invoices_AP. Buckets outstanding balances as of Assumptions!B5.
A4: Invoice_ID | B4: Vendor_ID | C4: Vendor_Name | D4: Invoice_Date | E4: Due_Date | F4: Invoice_Amount | G4: Paid_Amount | H4: Outstanding_Balance | I4: Days_Outstanding | J4: Aging_Bucket | K4: Status
A5: =Vendor_Invoices_AP!A2 -> INV30001 | B5: =Vendor_Invoices_AP!C2 -> V1020 | C5: =IFERROR(INDEX(Vendor_Master!$B$2:$B$41,MATCH(B5,Vendor_Master!$A$2:$A$41,0)),"Unknown Vendor") -> Lewis-Porter | D5: =Vendor_Invoices_AP!D2 -> 46109 | E5: =Vendor_Invoices_AP!F2 -> 46139 | F5: =Vendor_Invoices_AP!E2 -> 1417.41 | G5: =SUMIFS(Payment_Log_AP!$E$2:$E$753,Payment_Log_AP!$B$2:$B$753,A5) -> 1417.41 | H5: =F5-G5 -> 0 | I5: =IF(H5<=0.01,0,MAX(Assumptions!$B$5-E5,0)) -> 0 | J5: =IF(H5<=0.01,"Paid",IF(I5<=30,"0-30",IF(I5<=60,"31-60",IF(I5<=90,"61-90","90+")))) -> Paid | K5: =IF(H5<=0.01,"Paid",IF(G5>0,"Partially Paid","Unpaid")) -> Paid
A6: =Vendor_Invoices_AP!A3 -> INV30002 | B6: =Vendor_Invoices_AP!C3 -> V1034 | C6: =IFERROR(INDEX(Vendor_Master!$B$2:$B$41,MATCH(B6,Vendor_Master!$A$2:$A$41,0)),"Unknown Vendor") -> Koch-Decker | D6: =Vendor_Invoices_AP!D3 -> 45803 | E6: =Vendor_Invoices_AP!F3 -> 45848 | F6: =Vendor_Invoices_AP!E3 -> 1749.66 | G6: =SUMIFS(Payment_Log_AP!$E$2:$E$753,Payment_Log_AP!$B$2:$B$753,A6) -> 1749.66 | H6: =F6-G6 -> 0 | I6: =IF(H6<=0.01,0,MAX(Assumptions!$B$5-E6,0)) -> 0 | J6: =IF(H6<=0.01,"Paid",IF(I6<=30,"0-30",IF(I6<=60,"31-60",IF(I6<=90,"61-90","90+")))) -> Paid | K6: =IF(H6<=0.01,"Paid",IF(G6>0,"Partially Paid","Unpaid")) -> Paid
A7: =Vendor_Invoices_AP!A4 -> INV30003 | B7: =Vendor_Invoices_AP!C4 -> V1014 | C7: =IFERROR(INDEX(Vendor_Master!$B$2:$B$41,MATCH(B7,Vendor_Master!$A$2:$A$41,0)),"Unknown Vendor") -> Flowers, Martin and Kelly | D7: =Vendor_Invoices_AP!D4 -> 45676 | E7: =Vendor_Invoices_AP!F4 -> 45706 | F7: =Vendor_Invoices_AP!E4 -> 2691.35 | G7: =SUMIFS(Payment_Log_AP!$E$2:$E$753,Payment_Log_AP!$B$2:$B$753,A7) -> 2691.35 | H7: =F7-G7 -> 0 | I7: =IF(H7<=0.01,0,MAX(Assumptions!$B$5-E7,0)) -> 0 | J7: =IF(H7<=0.01,"Paid",IF(I7<=30,"0-30",IF(I7<=60,"31-60",IF(I7<=90,"61-90","90+")))) -> Paid | K7: =IF(H7<=0.01,"Paid",IF(G7>0,"Partially Paid","Unpaid")) -> Paid
A8: =Vendor_Invoices_AP!A5 -> INV30004 | B8: =Vendor_Invoices_AP!C5 -> V1040 | C8: =IFERROR(INDEX(Vendor_Master!$B$2:$B$41,MATCH(B8,Vendor_Master!$A$2:$A$41,0)),"Unknown Vendor") -> Santos, Kim and Holmes | D8: =Vendor_Invoices_AP!D5 -> 45783 | E8: =Vendor_Invoices_AP!F5 -> 45798 | F8: =Vendor_Invoices_AP!E5 -> 889.24 | G8: =SUMIFS(Payment_Log_AP!$E$2:$E$753,Payment_Log_AP!$B$2:$B$753,A8) -> 889.24 | H8: =F8-G8 -> 0 | I8: =IF(H8<=0.01,0,MAX(Assumptions!$B$5-E8,0)) -> 0 | J8: =IF(H8<=0.01,"Paid",IF(I8<=30,"0-30",IF(I8<=60,"31-60",IF(I8<=90,"61-90","90+")))) -> Paid | K8: =IF(H8<=0.01,"Paid",IF(G8>0,"Partially Paid","Unpaid")) -> Paid
A9: =Vendor_Invoices_AP!A6 -> INV30005 | B9: =Vendor_Invoices_AP!C6 -> V1022 | C9: =IFERROR(INDEX(Vendor_Master!$B$2:$B$41,MATCH(B9,Vendor_Master!$A$2:$A$41,0)),"Unknown Vendor") -> Burgess-Patterson | D9: =Vendor_Invoices_AP!D6 -> 45861 | E9: =Vendor_Invoices_AP!F6 -> 45891 | F9: =Vendor_Invoices_AP!E6 -> 3058.04 | G9: =SUMIFS(Payment_Log_AP!$E$2:$E$753,Payment_Log_AP!$B$2:$B$753,A9) -> 3058.04 | H9: =F9-G9 -> 0 | I9: =IF(H9<=0.01,0,MAX(Assumptions!$B$5-E9,0)) -> 0 | J9: =IF(H9<=0.01,"Paid",IF(I9<=30,"0-30",IF(I9<=60,"31-60",IF(I9<=90,"61-90","90+")))) -> Paid | K9: =IF(H9<=0.01,"Paid",IF(G9>0,"Partially Paid","Unpaid")) -> Paid
A10: =Vendor_Invoices_AP!A7 -> INV30006 | B10: =Vendor_Invoices_AP!C7 -> V1040 | C10: =IFERROR(INDEX(Vendor_Master!$B$2:$B$41,MATCH(B10,Vendor_Master!$A$2:$A$41,0)),"Unknown Vendor") -> Santos, Kim and Holmes | D10: =Vendor_Invoices_AP!D7 -> 46132 | E10: =Vendor_Invoices_AP!F7 -> 46147 | F10: =Vendor_Invoices_AP!E7 -> 1359.77 | G10: =SUMIFS(Payment_Log_AP!$E$2:$E$753,Payment_Log_AP!$B$2:$B$753,A10) -> 1359.77 | H10: =F10-G10 -> 0 | I10: =IF(H10<=0.01,0,MAX(Assumptions!$B$5-E10,0)) -> 0 | J10: =IF(H10<=0.01,"Paid",IF(I10<=30,"0-30",IF(I10<=60,"31-60",IF(I10<=90,"61-90","90+")))) -> Paid | K10: =IF(H10<=0.01,"Paid",IF(G10>0,"Partially Paid","Unpaid")) -> Paid
A11: =Vendor_Invoices_AP!A8 -> INV30007 | B11: =Vendor_Invoices_AP!C8 -> V1040 | C11: =IFERROR(INDEX(Vendor_Master!$B$2:$B$41,MATCH(B11,Vendor_Master!$A$2:$A$41,0)),"Unknown Vendor") -> Santos, Kim and Holmes | D11: =Vendor_Invoices_AP!D8 -> 46188 | E11: =Vendor_Invoices_AP!F8 -> 46203 | F11: =Vendor_Invoices_AP!E8 -> 3708.39 | G11: =SUMIFS(Payment_Log_AP!$E$2:$E$753,Payment_Log_AP!$B$2:$B$753,A11) -> 3708.39 | H11: =F11-G11 -> 0 | I11: =IF(H11<=0.01,0,MAX(Assumptions!$B$5-E11,0)) -> 0 | J11: =IF(H11<=0.01,"Paid",IF(I11<=30,"0-30",IF(I11<=60,"31-60",IF(I11<=90,"61-90","90+")))) -> Paid | K11: =IF(H11<=0.01,"Paid",IF(G11>0,"Partially Paid","Unpaid")) -> Paid
A12: =Vendor_Invoices_AP!A9 -> INV30008 | B12: =Vendor_Invoices_AP!C9 -> V1015 | C12: =IFERROR(INDEX(Vendor_Master!$B$2:$B$41,MATCH(B12,Vendor_Master!$A$2:$A$41,0)),"Unknown Vendor") -> Zuniga, Wong and Lynch | D12: =Vendor_Invoices_AP!D9 -> 45833 | E12: =Vendor_Invoices_AP!F9 -> 45863 | F12: =Vendor_Invoices_AP!E9 -> 6081.19 | G12: =SUMIFS(Payment_Log_AP!$E$2:$E$753,Payment_Log_AP!$B$2:$B$753,A12) -> 6081.19 | H12: =F12-G12 -> 0 | I12: =IF(H12<=0.01,0,MAX(Assumptions!$B$5-E12,0)) -> 0 | J12: =IF(H12<=0.01,"Paid",IF(I12<=30,"0-30",IF(I12<=60,"31-60",IF(I12<=90,"61-90","90+")))) -> Paid | K12: =IF(H12<=0.01,"Paid",IF(G12>0,"Partially Paid","Unpaid")) -> Paid
A13: =Vendor_Invoices_AP!A10 -> INV30009 | B13: =Vendor_Invoices_AP!C10 -> V1018 | C13: =IFERROR(INDEX(Vendor_Master!$B$2:$B$41,MATCH(B13,Vendor_Master!$A$2:$A$41,0)),"Unknown Vendor") -> Underwood LLC | D13: =Vendor_Invoices_AP!D10 -> 46020 | E13: =Vendor_Invoices_AP!F10 -> 46050 | F13: =Vendor_Invoices_AP!E10 -> 6038.81 | G13: =SUMIFS(Payment_Log_AP!$E$2:$E$753,Payment_Log_AP!$B$2:$B$753,A13) -> 0 | H13: =F13-G13 -> 6038.81 | I13: =IF(H13<=0.01,0,MAX(Assumptions!$B$5-E13,0)) -> 184 | J13: =IF(H13<=0.01,"Paid",IF(I13<=30,"0-30",IF(I13<=60,"31-60",IF(I13<=90,"61-90","90+")))) -> 90+ | K13: =IF(H13<=0.01,"Paid",IF(G13>0,"Partially Paid","Unpaid")) -> Unpaid
A14: =Vendor_Invoices_AP!A11 -> INV30010 | B14: =Vendor_Invoices_AP!C11 -> V1005 | C14: =IFERROR(INDEX(Vendor_Master!$B$2:$B$41,MATCH(B14,Vendor_Master!$A$2:$A$41,0)),"Unknown Vendor") -> Cole LLC | D14: =Vendor_Invoices_AP!D11 -> 45878 | E14: =Vendor_Invoices_AP!F11 -> 45893 | F14: =Vendor_Invoices_AP!E11 -> 1466.07 | G14: =SUMIFS(Payment_Log_AP!$E$2:$E$753,Payment_Log_AP!$B$2:$B$753,A14) -> 1466.07 | H14: =F14-G14 -> 0 | I14: =IF(H14<=0.01,0,MAX(Assumptions!$B$5-E14,0)) -> 0 | J14: =IF(H14<=0.01,"Paid",IF(I14<=30,"0-30",IF(I14<=60,"31-60",IF(I14<=90,"61-90","90+")))) -> Paid | K14: =IF(H14<=0.01,"Paid",IF(G14>0,"Partially Paid","Unpaid")) -> Paid
A15: =Vendor_Invoices_AP!A12 -> INV30011 | B15: =Vendor_Invoices_AP!C12 -> V1024 | C15: =IFERROR(INDEX(Vendor_Master!$B$2:$B$41,MATCH(B15,Vendor_Master!$A$2:$A$41,0)),"Unknown Vendor") -> Campos Inc | D15: =Vendor_Invoices_AP!D12 -> 46210 | E15: =Vendor_Invoices_AP!F12 -> 46270 | F15: =Vendor_Invoices_AP!E12 -> 760.24 | G15: =SUMIFS(Payment_Log_AP!$E$2:$E$753,Payment_Log_AP!$B$2:$B$753,A15) -> 0 | H15: =F15-G15 -> 760.24 | I15: =IF(H15<=0.01,0,MAX(Assumptions!$B$5-E15,0)) -> 0 | J15: =IF(H15<=0.01,"Paid",IF(I15<=30,"0-30",IF(I15<=60,"31-60",IF(I15<=90,"61-90","90+")))) -> 0-30 | K15: =IF(H15<=0.01,"Paid",IF(G15>0,"Partially Paid","Unpaid")) -> Unpaid
A16: =Vendor_Invoices_AP!A13 -> INV30012 | B16: =Vendor_Invoices_AP!C13 -> V1035 | C16: =IFERROR(INDEX(Vendor_Master!$B$2:$B$41,MATCH(B16,Vendor_Master!$A$2:$A$41,0)),"Unknown Vendor") -> Allen PLC | D16: =Vendor_Invoices_AP!D13 -> 45975 | E16: =Vendor_Invoices_AP!F13 -> 45990 | F16: =Vendor_Invoices_AP!E13 -> 15002.72 | G16: =SUMIFS(Payment_Log_AP!$E$2:$E$753,Payment_Log_AP!$B$2:$B$753,A16) -> 15002.72 | H16: =F16-G16 -> 0 | I16: =IF(H16<=0.01,0,MAX(Assumptions!$B$5-E16,0)) -> 0 | J16: =IF(H16<=0.01,"Paid",IF(I16<=30,"0-30",IF(I16<=60,"31-60",IF(I16<=90,"61-90","90+")))) -> Paid | K16: =IF(H16<=0.01,"Paid",IF(G16>0,"Partially Paid","Unpaid")) -> Paid
... A885: =Vendor_Invoices_AP!A882 -> INV30881 | B885: =Vendor_Invoices_AP!C882 -> V1014 | C885: =IFERROR(INDEX(Vendor_Master!$B$2:$B$41,MATCH(B885,Vendor_Master!$A$2:$A$41,0)),"Unknown Vendor") -> Flowers, Martin and Kelly | D885: =Vendor_Invoices_AP!D882 -> 45973 | E885: =Vendor_Invoices_AP!F882 -> 46003 | F885: =Vendor_Invoices_AP!E882 -> 4104.49 | G885: =SUMIFS(Payment_Log_AP!$E$2:$E$753,Payment_Log_AP!$B$2:$B$753,A885) -> 4104.49 | H885: =F885-G885 -> 0 | I885: =IF(H885<=0.01,0,MAX(Assumptions!$B$5-E885,0)) -> 0 | J885: =IF(H885<=0.01,"Paid",IF(I885<=30,"0-30",IF(I885<=60,"31-60",IF(I885<=90,"61-90","90+")))) -> Paid | K885: =IF(H885<=0.01,"Paid",IF(G885>0,"Partially Paid","Unpaid")) -> Paid
A888: AP Aging Summary (as of Assumptions!B5)
A889: Bucket | B889: Outstanding $ | C889: Invoice Count
A890: 0-30 | B890: =SUMIFS($H$5:$H$885,$J$5:$J$885,A890) -> 248495.64 | C890: =COUNTIFS($J$5:$J$885,A890) -> 48
A891: 31-60 | B891: =SUMIFS($H$5:$H$885,$J$5:$J$885,A891) -> 15605.37 | C891: =COUNTIFS($J$5:$J$885,A891) -> 7
A892: 61-90 | B892: =SUMIFS($H$5:$H$885,$J$5:$J$885,A892) -> 24163.94 | C892: =COUNTIFS($J$5:$J$885,A892) -> 8
A893: 90+ | B893: =SUMIFS($H$5:$H$885,$J$5:$J$885,A893) -> 281252.27 | C893: =COUNTIFS($J$5:$J$885,A893) -> 82

Sheet Duplicate_Payments
A1: Accounts Payable — Duplicate Payment Detection
A2: Base table: Vendor_Invoices_AP (one row per invoice). Counts how many payments in Payment_Log_AP reference each invoice.
A4: Invoice_ID | B4: Vendor_ID | C4: Vendor_Name | D4: Invoice_Amount | E4: Payment_Count | F4: Total_Paid | G4: Overpayment_Amount | H4: Flag
A5: =Vendor_Invoices_AP!A2 -> INV30001 | B5: =Vendor_Invoices_AP!C2 -> V1020 | C5: =IFERROR(INDEX(Vendor_Master!$B$2:$B$41,MATCH(B5,Vendor_Master!$A$2:$A$41,0)),"Unknown Vendor") -> Lewis-Porter | D5: =Vendor_Invoices_AP!E2 -> 1417.41 | E5: =COUNTIF(Payment_Log_AP!$B$2:$B$753,A5) -> 1 | F5: =SUMIFS(Payment_Log_AP!$E$2:$E$753,Payment_Log_AP!$B$2:$B$753,A5) -> 1417.41 | G5: =MAX(F5-D5,0) -> 0 | H5: =IF(E5>1,"DUPLICATE - Review",IF(G5>Assumptions!$B$6,"OVERPAID - Review","OK")) -> OK
A6: =Vendor_Invoices_AP!A3 -> INV30002 | B6: =Vendor_Invoices_AP!C3 -> V1034 | C6: =IFERROR(INDEX(Vendor_Master!$B$2:$B$41,MATCH(B6,Vendor_Master!$A$2:$A$41,0)),"Unknown Vendor") -> Koch-Decker | D6: =Vendor_Invoices_AP!E3 -> 1749.66 | E6: =COUNTIF(Payment_Log_AP!$B$2:$B$753,A6) -> 1 | F6: =SUMIFS(Payment_Log_AP!$E$2:$E$753,Payment_Log_AP!$B$2:$B$753,A6) -> 1749.66 | G6: =MAX(F6-D6,0) -> 0 | H6: =IF(E6>1,"DUPLICATE - Review",IF(G6>Assumptions!$B$6,"OVERPAID - Review","OK")) -> OK
A7: =Vendor_Invoices_AP!A4 -> INV30003 | B7: =Vendor_Invoices_AP!C4 -> V1014 | C7: =IFERROR(INDEX(Vendor_Master!$B$2:$B$41,MATCH(B7,Vendor_Master!$A$2:$A$41,0)),"Unknown Vendor") -> Flowers, Martin and Kelly | D7: =Vendor_Invoices_AP!E4 -> 2691.35 | E7: =COUNTIF(Payment_Log_AP!$B$2:$B$753,A7) -> 1 | F7: =SUMIFS(Payment_Log_AP!$E$2:$E$753,Payment_Log_AP!$B$2:$B$753,A7) -> 2691.35 | G7: =MAX(F7-D7,0) -> 0 | H7: =IF(E7>1,"DUPLICATE - Review",IF(G7>Assumptions!$B$6,"OVERPAID - Review","OK")) -> OK
A8: =Vendor_Invoices_AP!A5 -> INV30004 | B8: =Vendor_Invoices_AP!C5 -> V1040 | C8: =IFERROR(INDEX(Vendor_Master!$B$2:$B$41,MATCH(B8,Vendor_Master!$A$2:$A$41,0)),"Unknown Vendor") -> Santos, Kim and Holmes | D8: =Vendor_Invoices_AP!E5 -> 889.24 | E8: =COUNTIF(Payment_Log_AP!$B$2:$B$753,A8) -> 1 | F8: =SUMIFS(Payment_Log_AP!$E$2:$E$753,Payment_Log_AP!$B$2:$B$753,A8) -> 889.24 | G8: =MAX(F8-D8,0) -> 0 | H8: =IF(E8>1,"DUPLICATE - Review",IF(G8>Assumptions!$B$6,"OVERPAID - Review","OK")) -> OK
A9: =Vendor_Invoices_AP!A6 -> INV30005 | B9: =Vendor_Invoices_AP!C6 -> V1022 | C9: =IFERROR(INDEX(Vendor_Master!$B$2:$B$41,MATCH(B9,Vendor_Master!$A$2:$A$41,0)),"Unknown Vendor") -> Burgess-Patterson | D9: =Vendor_Invoices_AP!E6 -> 3058.04 | E9: =COUNTIF(Payment_Log_AP!$B$2:$B$753,A9) -> 1 | F9: =SUMIFS(Payment_Log_AP!$E$2:$E$753,Payment_Log_AP!$B$2:$B$753,A9) -> 3058.04 | G9: =MAX(F9-D9,0) -> 0 | H9: =IF(E9>1,"DUPLICATE - Review",IF(G9>Assumptions!$B$6,"OVERPAID - Review","OK")) -> OK
A10: =Vendor_Invoices_AP!A7 -> INV30006 | B10: =Vendor_Invoices_AP!C7 -> V1040 | C10: =IFERROR(INDEX(Vendor_Master!$B$2:$B$41,MATCH(B10,Vendor_Master!$A$2:$A$41,0)),"Unknown Vendor") -> Santos, Kim and Holmes | D10: =Vendor_Invoices_AP!E7 -> 1359.77 | E10: =COUNTIF(Payment_Log_AP!$B$2:$B$753,A10) -> 1 | F10: =SUMIFS(Payment_Log_AP!$E$2:$E$753,Payment_Log_AP!$B$2:$B$753,A10) -> 1359.77 | G10: =MAX(F10-D10,0) -> 0 | H10: =IF(E10>1,"DUPLICATE - Review",IF(G10>Assumptions!$B$6,"OVERPAID - Review","OK")) -> OK
A11: =Vendor_Invoices_AP!A8 -> INV30007 | B11: =Vendor_Invoices_AP!C8 -> V1040 | C11: =IFERROR(INDEX(Vendor_Master!$B$2:$B$41,MATCH(B11,Vendor_Master!$A$2:$A$41,0)),"Unknown Vendor") -> Santos, Kim and Holmes | D11: =Vendor_Invoices_AP!E8 -> 3708.39 | E11: =COUNTIF(Payment_Log_AP!$B$2:$B$753,A11) -> 1 | F11: =SUMIFS(Payment_Log_AP!$E$2:$E$753,Payment_Log_AP!$B$2:$B$753,A11) -> 3708.39 | G11: =MAX(F11-D11,0) -> 0 | H11: =IF(E11>1,"DUPLICATE - Review",IF(G11>Assumptions!$B$6,"OVERPAID - Review","OK")) -> OK
A12: =Vendor_Invoices_AP!A9 -> INV30008 | B12: =Vendor_Invoices_AP!C9 -> V1015 | C12: =IFERROR(INDEX(Vendor_Master!$B$2:$B$41,MATCH(B12,Vendor_Master!$A$2:$A$41,0)),"Unknown Vendor") -> Zuniga, Wong and Lynch | D12: =Vendor_Invoices_AP!E9 -> 6081.19 | E12: =COUNTIF(Payment_Log_AP!$B$2:$B$753,A12) -> 1 | F12: =SUMIFS(Payment_Log_AP!$E$2:$E$753,Payment_Log_AP!$B$2:$B$753,A12) -> 6081.19 | G12: =MAX(F12-D12,0) -> 0 | H12: =IF(E12>1,"DUPLICATE - Review",IF(G12>Assumptions!$B$6,"OVERPAID - Review","OK")) -> OK
A13: =Vendor_Invoices_AP!A10 -> INV30009 | B13: =Vendor_Invoices_AP!C10 -> V1018 | C13: =IFERROR(INDEX(Vendor_Master!$B$2:$B$41,MATCH(B13,Vendor_Master!$A$2:$A$41,0)),"Unknown Vendor") -> Underwood LLC | D13: =Vendor_Invoices_AP!E10 -> 6038.81 | E13: =COUNTIF(Payment_Log_AP!$B$2:$B$753,A13) -> 0 | F13: =SUMIFS(Payment_Log_AP!$E$2:$E$753,Payment_Log_AP!$B$2:$B$753,A13) -> 0 | G13: =MAX(F13-D13,0) -> 0 | H13: =IF(E13>1,"DUPLICATE - Review",IF(G13>Assumptions!$B$6,"OVERPAID - Review","OK")) -> OK
A14: =Vendor_Invoices_AP!A11 -> INV30010 | B14: =Vendor_Invoices_AP!C11 -> V1005 | C14: =IFERROR(INDEX(Vendor_Master!$B$2:$B$41,MATCH(B14,Vendor_Master!$A$2:$A$41,0)),"Unknown Vendor") -> Cole LLC | D14: =Vendor_Invoices_AP!E11 -> 1466.07 | E14: =COUNTIF(Payment_Log_AP!$B$2:$B$753,A14) -> 1 | F14: =SUMIFS(Payment_Log_AP!$E$2:$E$753,Payment_Log_AP!$B$2:$B$753,A14) -> 1466.07 | G14: =MAX(F14-D14,0) -> 0 | H14: =IF(E14>1,"DUPLICATE - Review",IF(G14>Assumptions!$B$6,"OVERPAID - Review","OK")) -> OK
A15: =Vendor_Invoices_AP!A12 -> INV30011 | B15: =Vendor_Invoices_AP!C12 -> V1024 | C15: =IFERROR(INDEX(Vendor_Master!$B$2:$B$41,MATCH(B15,Vendor_Master!$A$2:$A$41,0)),"Unknown Vendor") -> Campos Inc | D15: =Vendor_Invoices_AP!E12 -> 760.24 | E15: =COUNTIF(Payment_Log_AP!$B$2:$B$753,A15) -> 0 | F15: =SUMIFS(Payment_Log_AP!$E$2:$E$753,Payment_Log_AP!$B$2:$B$753,A15) -> 0 | G15: =MAX(F15-D15,0) -> 0 | H15: =IF(E15>1,"DUPLICATE - Review",IF(G15>Assumptions!$B$6,"OVERPAID - Review","OK")) -> OK
A16: =Vendor_Invoices_AP!A13 -> INV30012 | B16: =Vendor_Invoices_AP!C13 -> V1035 | C16: =IFERROR(INDEX(Vendor_Master!$B$2:$B$41,MATCH(B16,Vendor_Master!$A$2:$A$41,0)),"Unknown Vendor") -> Allen PLC | D16: =Vendor_Invoices_AP!E13 -> 15002.72 | E16: =COUNTIF(Payment_Log_AP!$B$2:$B$753,A16) -> 1 | F16: =SUMIFS(Payment_Log_AP!$E$2:$E$753,Payment_Log_AP!$B$2:$B$753,A16) -> 15002.72 | G16: =MAX(F16-D16,0) -> 0 | H16: =IF(E16>1,"DUPLICATE - Review",IF(G16>Assumptions!$B$6,"OVERPAID - Review","OK")) -> OK
... A885: =Vendor_Invoices_AP!A882 -> INV30881 | B885: =Vendor_Invoices_AP!C882 -> V1014 | C885: =IFERROR(INDEX(Vendor_Master!$B$2:$B$41,MATCH(B885,Vendor_Master!$A$2:$A$41,0)),"Unknown Vendor") -> Flowers, Martin and Kelly | D885: =Vendor_Invoices_AP!E882 -> 4104.49 | E885: =COUNTIF(Payment_Log_AP!$B$2:$B$753,A885) -> 1 | F885: =SUMIFS(Payment_Log_AP!$E$2:$E$753,Payment_Log_AP!$B$2:$B$753,A885) -> 4104.49 | G885: =MAX(F885-D885,0) -> 0 | H885: =IF(E885>1,"DUPLICATE - Review",IF(G885>Assumptions!$B$6,"OVERPAID - Review","OK")) -> OK

Sheet AP_Payment_Detail
A1: Helper Table — AP Payment Detail (feeds DPO_Summary trend)
A2: One row per AP payment with its matched invoice date, used to compute actual days-to-pay by month.
A4: Payment_ID | B4: Vendor_ID | C4: Invoice_ID | D4: Payment_Date | E4: Payment_Amount | F4: Invoice_Date | G4: Days_To_Pay | H4: Month_Key
A5: =Payment_Log_AP!A2 -> PAY40001 | B5: =Payment_Log_AP!C2 -> V1020 | C5: =Payment_Log_AP!B2 -> INV30001 | D5: =Payment_Log_AP!D2 -> 46142 | E5: =Payment_Log_AP!E2 -> 1417.41 | F5: =IFERROR(INDEX(Vendor_Invoices_AP!$D$2:$D$882,MATCH(C5,Vendor_Invoices_AP!$A$2:$A$882,0)),"") -> 46109 | G5: =IF(F5="","",D5-F5) -> 33 | H5: =IF(F5="","",DATE(YEAR(D5),MONTH(D5),1)) -> 46113
A6: =Payment_Log_AP!A3 -> PAY40002 | B6: =Payment_Log_AP!C3 -> V1034 | C6: =Payment_Log_AP!B3 -> INV30002 | D6: =Payment_Log_AP!D3 -> 45805 | E6: =Payment_Log_AP!E3 -> 1749.66 | F6: =IFERROR(INDEX(Vendor_Invoices_AP!$D$2:$D$882,MATCH(C6,Vendor_Invoices_AP!$A$2:$A$882,0)),"") -> 45803 | G6: =IF(F6="","",D6-F6) -> 2 | H6: =IF(F6="","",DATE(YEAR(D6),MONTH(D6),1)) -> 45778
A7: =Payment_Log_AP!A4 -> PAY40003 | B7: =Payment_Log_AP!C4 -> V1014 | C7: =Payment_Log_AP!B4 -> INV30003 | D7: =Payment_Log_AP!D4 -> 45683 | E7: =Payment_Log_AP!E4 -> 2691.35 | F7: =IFERROR(INDEX(Vendor_Invoices_AP!$D$2:$D$882,MATCH(C7,Vendor_Invoices_AP!$A$2:$A$882,0)),"") -> 45676 | G7: =IF(F7="","",D7-F7) -> 7 | H7: =IF(F7="","",DATE(YEAR(D7),MONTH(D7),1)) -> 45658
A8: =Payment_Log_AP!A5 -> PAY40004 | B8: =Payment_Log_AP!C5 -> V1040 | C8: =Payment_Log_AP!B5 -> INV30004 | D8: =Payment_Log_AP!D5 -> 45805 | E8: =Payment_Log_AP!E5 -> 889.24 | F8: =IFERROR(INDEX(Vendor_Invoices_AP!$D$2:$D$882,MATCH(C8,Vendor_Invoices_AP!$A$2:$A$882,0)),"") -> 45783 | G8: =IF(F8="","",D8-F8) -> 22 | H8: =IF(F8="","",DATE(YEAR(D8),MONTH(D8),1)) -> 45778
A9: =Payment_Log_AP!A6 -> PAY40005 | B9: =Payment_Log_AP!C6 -> V1022 | C9: =Payment_Log_AP!B6 -> INV30005 | D9: =Payment_Log_AP!D6 -> 45883 | E9: =Payment_Log_AP!E6 -> 3058.04 | F9: =IFERROR(INDEX(Vendor_Invoices_AP!$D$2:$D$882,MATCH(C9,Vendor_Invoices_AP!$A$2:$A$882,0)),"") -> 45861 | G9: =IF(F9="","",D9-F9) -> 22 | H9: =IF(F9="","",DATE(YEAR(D9),MONTH(D9),1)) -> 45870
A10: =Payment_Log_AP!A7 -> PAY40006 | B10: =Payment_Log_AP!C7 -> V1040 | C10: =Payment_Log_AP!B7 -> INV30006 | D10: =Payment_Log_AP!D7 -> 46160 | E10: =Payment_Log_AP!E7 -> 1359.77 | F10: =IFERROR(INDEX(Vendor_Invoices_AP!$D$2:$D$882,MATCH(C10,Vendor_Invoices_AP!$A$2:$A$882,0)),"") -> 46132 | G10: =IF(F10="","",D10-F10) -> 28 | H10: =IF(F10="","",DATE(YEAR(D10),MONTH(D10),1)) -> 46143
A11: =Payment_Log_AP!A8 -> PAY40007 | B11: =Payment_Log_AP!C8 -> V1040 | C11: =Payment_Log_AP!B8 -> INV30007 | D11: =Payment_Log_AP!D8 -> 46193 | E11: =Payment_Log_AP!E8 -> 3708.39 | F11: =IFERROR(INDEX(Vendor_Invoices_AP!$D$2:$D$882,MATCH(C11,Vendor_Invoices_AP!$A$2:$A$882,0)),"") -> 46188 | G11: =IF(F11="","",D11-F11) -> 5 | H11: =IF(F11="","",DATE(YEAR(D11),MONTH(D11),1)) -> 46174
A12: =Payment_Log_AP!A9 -> PAY40008 | B12: =Payment_Log_AP!C9 -> V1015 | C12: =Payment_Log_AP!B9 -> INV30008 | D12: =Payment_Log_AP!D9 -> 45859 | E12: =Payment_Log_AP!E9 -> 6081.19 | F12: =IFERROR(INDEX(Vendor_Invoices_AP!$D$2:$D$882,MATCH(C12,Vendor_Invoices_AP!$A$2:$A$882,0)),"") -> 45833 | G12: =IF(F12="","",D12-F12) -> 26 | H12: =IF(F12="","",DATE(YEAR(D12),MONTH(D12),1)) -> 45839
A13: =Payment_Log_AP!A10 -> PAY40009 | B13: =Payment_Log_AP!C10 -> V1005 | C13: =Payment_Log_AP!B10 -> INV30010 | D13: =Payment_Log_AP!D10 -> 45885 | E13: =Payment_Log_AP!E10 -> 1466.07 | F13: =IFERROR(INDEX(Vendor_Invoices_AP!$D$2:$D$882,MATCH(C13,Vendor_Invoices_AP!$A$2:$A$882,0)),"") -> 45878 | G13: =IF(F13="","",D13-F13) -> 7 | H13: =IF(F13="","",DATE(YEAR(D13),MONTH(D13),1)) -> 45870
A14: =Payment_Log_AP!A11 -> PAY40010 | B14: =Payment_Log_AP!C11 -> V1035 | C14: =Payment_Log_AP!B11 -> INV30012 | D14: =Payment_Log_AP!D11 -> 45989 | E14: =Payment_Log_AP!E11 -> 15002.72 | F14: =IFERROR(INDEX(Vendor_Invoices_AP!$D$2:$D$882,MATCH(C14,Vendor_Invoices_AP!$A$2:$A$882,0)),"") -> 45975 | G14: =IF(F14="","",D14-F14) -> 14 | H14: =IF(F14="","",DATE(YEAR(D14),MONTH(D14),1)) -> 45962
A15: =Payment_Log_AP!A12 -> PAY40011 | B15: =Payment_Log_AP!C12 -> V1016 | C15: =Payment_Log_AP!B12 -> INV30013 | D15: =Payment_Log_AP!D12 -> 46196 | E15: =Payment_Log_AP!E12 -> 911.91 | F15: =IFERROR(INDEX(Vendor_Invoices_AP!$D$2:$D$882,MATCH(C15,Vendor_Invoices_AP!$A$2:$A$882,0)),"") -> 46176 | G15: =IF(F15="","",D15-F15) -> 20 | H15: =IF(F15="","",DATE(YEAR(D15),MONTH(D15),1)) -> 46174
A16: =Payment_Log_AP!A13 -> PAY40012 | B16: =Payment_Log_AP!C13 -> V1002 | C16: =Payment_Log_AP!B13 -> INV30014 | D16: =Payment_Log_AP!D13 -> 45753 | E16: =Payment_Log_AP!E13 -> 1222.88 | F16: =IFERROR(INDEX(Vendor_Invoices_AP!$D$2:$D$882,MATCH(C16,Vendor_Invoices_AP!$A$2:$A$882,0)),"") -> 45740 | G16: =IF(F16="","",D16-F16) -> 13 | H16: =IF(F16="","",DATE(YEAR(D16),MONTH(D16),1)) -> 45748
... A756: =Payment_Log_AP!A753 -> PAY40752 | B756: =Payment_Log_AP!C753 -> V1014 | C756: =Payment_Log_AP!B753 -> INV30881 | D756: =Payment_Log_AP!D753 -> 46002 | E756: =Payment_Log_AP!E753 -> 4104.49 | F756: =IFERROR(INDEX(Vendor_Invoices_AP!$D$2:$D$882,MATCH(C756,Vendor_Invoices_AP!$A$2:$A$882,0)),"") -> 45973 | G756: =IF(F756="","",D756-F756) -> 29 | H756: =IF(F756="","",DATE(YEAR(D756),MONTH(D756),1)) -> 45992

Sheet DPO_Summary
A1: Accounts Payable — Days Payable Outstanding (DPO)
A2: Headline formula-based DPO, plus an actual average days-to-pay trend by month from AP_Payment_Detail.
A4: Headline DPO (formula method)
A5: Ending AP (Outstanding Balance, all invoices) | B5: =SUM(AP_Aging!$B$890:$B$893) -> 569517.22
A6: Total AP Invoiced (full data period) | B6: =SUM(Vendor_Invoices_AP!$E$2:$E$882) -> 3067975.3
A7: Days in Period (data span) | B7: =MAX(Vendor_Invoices_AP!$D$2:$D$882)-MIN(Vendor_Invoices_AP!$D$2:$D$882) -> 558
A8: DPO = Ending AP / Total AP Invoiced x Days in Period | B8: =B5/B6*B7 -> 103.58317
A9: Actual Average Days-to-Pay (all settled invoices) | B9: =AVERAGE(AP_Payment_Detail!$G$5:$G$756) -> 17.986702
A11: Monthly Trend — Actual Average Days-to-Pay
A12: Month | B12: Avg Days to Pay | C12: Total Paid ($)
A13: 45658 | B13: =IFERROR(AVERAGEIFS(AP_Payment_Detail!$G$5:$G$756,AP_Payment_Detail!$H$5:$H$756,A13),0) -> 8.6666667 | C13: =SUMIFS(AP_Payment_Detail!$E$5:$E$756,AP_Payment_Detail!$H$5:$H$756,A13) -> 28576.85
A14: 45689 | B14: =IFERROR(AVERAGEIFS(AP_Payment_Detail!$G$5:$G$756,AP_Payment_Detail!$H$5:$H$756,A14),0) -> 16.484848 | C14: =SUMIFS(AP_Payment_Detail!$E$5:$E$756,AP_Payment_Detail!$H$5:$H$756,A14) -> 119868.99
A15: 45717 | B15: =IFERROR(AVERAGEIFS(AP_Payment_Detail!$G$5:$G$756,AP_Payment_Detail!$H$5:$H$756,A15),0) -> 16.052632 | C15: =SUMIFS(AP_Payment_Detail!$E$5:$E$756,AP_Payment_Detail!$H$5:$H$756,A15) -> 138285.77
A16: 45748 | B16: =IFERROR(AVERAGEIFS(AP_Payment_Detail!$G$5:$G$756,AP_Payment_Detail!$H$5:$H$756,A16),0) -> 18.475 | C16: =SUMIFS(AP_Payment_Detail!$E$5:$E$756,AP_Payment_Detail!$H$5:$H$756,A16) -> 151944.6
A17: 45778 | B17: =IFERROR(AVERAGEIFS(AP_Payment_Detail!$G$5:$G$756,AP_Payment_Detail!$H$5:$H$756,A17),0) -> 18.025 | C17: =SUMIFS(AP_Payment_Detail!$E$5:$E$756,AP_Payment_Detail!$H$5:$H$756,A17) -> 115131.97
A18: 45809 | B18: =IFERROR(AVERAGEIFS(AP_Payment_Detail!$G$5:$G$756,AP_Payment_Detail!$H$5:$H$756,A18),0) -> 16.512821 | C18: =SUMIFS(AP_Payment_Detail!$E$5:$E$756,AP_Payment_Detail!$H$5:$H$756,A18) -> 127916.17
A19: 45839 | B19: =IFERROR(AVERAGEIFS(AP_Payment_Detail!$G$5:$G$756,AP_Payment_Detail!$H$5:$H$756,A19),0) -> 17.745098 | C19: =SUMIFS(AP_Payment_Detail!$E$5:$E$756,AP_Payment_Detail!$H$5:$H$756,A19) -> 153034.98
A20: 45870 | B20: =IFERROR(AVERAGEIFS(AP_Payment_Detail!$G$5:$G$756,AP_Payment_Detail!$H$5:$H$756,A20),0) -> 18.04878 | C20: =SUMIFS(AP_Payment_Detail!$E$5:$E$756,AP_Payment_Detail!$H$5:$H$756,A20) -> 155487.54
A21: 45901 | B21: =IFERROR(AVERAGEIFS(AP_Payment_Detail!$G$5:$G$756,AP_Payment_Detail!$H$5:$H$756,A21),0) -> 17.142857 | C21: =SUMIFS(AP_Payment_Detail!$E$5:$E$756,AP_Payment_Detail!$H$5:$H$756,A21) -> 156557.35
A22: 45931 | B22: =IFERROR(AVERAGEIFS(AP_Payment_Detail!$G$5:$G$756,AP_Payment_Detail!$H$5:$H$756,A22),0) -> 18.75 | C22: =SUMIFS(AP_Payment_Detail!$E$5:$E$756,AP_Payment_Detail!$H$5:$H$756,A22) -> 180558.89
A23: 45962 | B23: =IFERROR(AVERAGEIFS(AP_Payment_Detail!$G$5:$G$756,AP_Payment_Detail!$H$5:$H$756,A23),0) -> 19.111111 | C23: =SUMIFS(AP_Payment_Detail!$E$5:$E$756,AP_Payment_Detail!$H$5:$H$756,A23) -> 124879.11
A24: 45992 | B24: =IFERROR(AVERAGEIFS(AP_Payment_Detail!$G$5:$G$756,AP_Payment_Detail!$H$5:$H$756,A24),0) -> 17.877551 | C24: =SUMIFS(AP_Payment_Detail!$E$5:$E$756,AP_Payment_Detail!$H$5:$H$756,A24) -> 128841.83
... A31: 46204 | B31: =IFERROR(AVERAGEIFS(AP_Payment_Detail!$G$5:$G$756,AP_Payment_Detail!$H$5:$H$756,A31),0) -> 11.75 | C31: =SUMIFS(AP_Payment_Detail!$E$5:$E$756,AP_Payment_Detail!$H$5:$H$756,A31) -> 13225.35

Sheet AR_Aging
A1: Accounts Receivable — Aging
A2: Base table: Customer_Invoices_AR. Buckets outstanding balances as of Assumptions!B5.
A4: AR_Invoice_ID | B4: Customer_ID | C4: Customer_Name | D4: Billing_Date | E4: Due_Date | F4: Invoice_Amount | G4: Receipts_Amount | H4: Outstanding_Balance | I4: Days_Outstanding | J4: Aging_Bucket | K4: Status
A5: =Customer_Invoices_AR!A2 -> ARI60001 | B5: =Customer_Invoices_AR!B2 -> C2003 | C5: =IFERROR(INDEX(Customer_Master!$B$2:$B$31,MATCH(B5,Customer_Master!$A$2:$A$31,0)),"Unknown Customer") -> Robinson, Jones and Welch | D5: =Customer_Invoices_AR!C2 -> 45986 | E5: =Customer_Invoices_AR!E2 -> 46031 | F5: =Customer_Invoices_AR!D2 -> 6493.93 | G5: =SUMIFS(Cash_Receipts_AR!$E$2:$E$503,Cash_Receipts_AR!$B$2:$B$503,A5) -> 0 | H5: =F5-G5 -> 6493.93 | I5: =IF(H5<=0.01,0,MAX(Assumptions!$B$5-E5,0)) -> 203 | J5: =IF(H5<=0.01,"Paid",IF(I5<=30,"0-30",IF(I5<=60,"31-60",IF(I5<=90,"61-90","90+")))) -> 90+ | K5: =IF(H5<=0.01,"Paid",IF(G5>0,"Partially Paid","Unpaid")) -> Unpaid
A6: =Customer_Invoices_AR!A3 -> ARI60002 | B6: =Customer_Invoices_AR!B3 -> C2014 | C6: =IFERROR(INDEX(Customer_Master!$B$2:$B$31,MATCH(B6,Customer_Master!$A$2:$A$31,0)),"Unknown Customer") -> Baxter Inc | D6: =Customer_Invoices_AR!C3 -> 46072 | E6: =Customer_Invoices_AR!E3 -> 46102 | F6: =Customer_Invoices_AR!D3 -> 3250.9 | G6: =SUMIFS(Cash_Receipts_AR!$E$2:$E$503,Cash_Receipts_AR!$B$2:$B$503,A6) -> 1523.91 | H6: =F6-G6 -> 1726.99 | I6: =IF(H6<=0.01,0,MAX(Assumptions!$B$5-E6,0)) -> 132 | J6: =IF(H6<=0.01,"Paid",IF(I6<=30,"0-30",IF(I6<=60,"31-60",IF(I6<=90,"61-90","90+")))) -> 90+ | K6: =IF(H6<=0.01,"Paid",IF(G6>0,"Partially Paid","Unpaid")) -> Partially Paid
A7: =Customer_Invoices_AR!A4 -> ARI60003 | B7: =Customer_Invoices_AR!B4 -> C2010 | C7: =IFERROR(INDEX(Customer_Master!$B$2:$B$31,MATCH(B7,Customer_Master!$A$2:$A$31,0)),"Unknown Customer") -> Brown, Valdez and Lucas | D7: =Customer_Invoices_AR!C4 -> 46015 | E7: =Customer_Invoices_AR!E4 -> 46075 | F7: =Customer_Invoices_AR!D4 -> 715.25 | G7: =SUMIFS(Cash_Receipts_AR!$E$2:$E$503,Cash_Receipts_AR!$B$2:$B$503,A7) -> 715.25 | H7: =F7-G7 -> 0 | I7: =IF(H7<=0.01,0,MAX(Assumptions!$B$5-E7,0)) -> 0 | J7: =IF(H7<=0.01,"Paid",IF(I7<=30,"0-30",IF(I7<=60,"31-60",IF(I7<=90,"61-90","90+")))) -> Paid | K7: =IF(H7<=0.01,"Paid",IF(G7>0,"Partially Paid","Unpaid")) -> Paid
A8: =Customer_Invoices_AR!A5 -> ARI60004 | B8: =Customer_Invoices_AR!B5 -> C2030 | C8: =IFERROR(INDEX(Customer_Master!$B$2:$B$31,MATCH(B8,Customer_Master!$A$2:$A$31,0)),"Unknown Customer") -> Sanchez, Wheeler and Harvey | D8: =Customer_Invoices_AR!C5 -> 45754 | E8: =Customer_Invoices_AR!E5 -> 45769 | F8: =Customer_Invoices_AR!D5 -> 3252.02 | G8: =SUMIFS(Cash_Receipts_AR!$E$2:$E$503,Cash_Receipts_AR!$B$2:$B$503,A8) -> 3252.02 | H8: =F8-G8 -> 0 | I8: =IF(H8<=0.01,0,MAX(Assumptions!$B$5-E8,0)) -> 0 | J8: =IF(H8<=0.01,"Paid",IF(I8<=30,"0-30",IF(I8<=60,"31-60",IF(I8<=90,"61-90","90+")))) -> Paid | K8: =IF(H8<=0.01,"Paid",IF(G8>0,"Partially Paid","Unpaid")) -> Paid
A9: =Customer_Invoices_AR!A6 -> ARI60005 | B9: =Customer_Invoices_AR!B6 -> C2014 | C9: =IFERROR(INDEX(Customer_Master!$B$2:$B$31,MATCH(B9,Customer_Master!$A$2:$A$31,0)),"Unknown Customer") -> Baxter Inc | D9: =Customer_Invoices_AR!C6 -> 46079 | E9: =Customer_Invoices_AR!E6 -> 46109 | F9: =Customer_Invoices_AR!D6 -> 6622.57 | G9: =SUMIFS(Cash_Receipts_AR!$E$2:$E$503,Cash_Receipts_AR!$B$2:$B$503,A9) -> 6622.57 | H9: =F9-G9 -> 0 | I9: =IF(H9<=0.01,0,MAX(Assumptions!$B$5-E9,0)) -> 0 | J9: =IF(H9<=0.01,"Paid",IF(I9<=30,"0-30",IF(I9<=60,"31-60",IF(I9<=90,"61-90","90+")))) -> Paid | K9: =IF(H9<=0.01,"Paid",IF(G9>0,"Partially Paid","Unpaid")) -> Paid
A10: =Customer_Invoices_AR!A7 -> ARI60006 | B10: =Customer_Invoices_AR!B7 -> C2004 | C10: =IFERROR(INDEX(Customer_Master!$B$2:$B$31,MATCH(B10,Customer_Master!$A$2:$A$31,0)),"Unknown Customer") -> Jones Inc | D10: =Customer_Invoices_AR!C7 -> 45927 | E10: =Customer_Invoices_AR!E7 -> 45957 | F10: =Customer_Invoices_AR!D7 -> 8576.41 | G10: =SUMIFS(Cash_Receipts_AR!$E$2:$E$503,Cash_Receipts_AR!$B$2:$B$503,A10) -> 2625.84 | H10: =F10-G10 -> 5950.57 | I10: =IF(H10<=0.01,0,MAX(Assumptions!$B$5-E10,0)) -> 277 | J10: =IF(H10<=0.01,"Paid",IF(I10<=30,"0-30",IF(I10<=60,"31-60",IF(I10<=90,"61-90","90+")))) -> 90+ | K10: =IF(H10<=0.01,"Paid",IF(G10>0,"Partially Paid","Unpaid")) -> Partially Paid
A11: =Customer_Invoices_AR!A8 -> ARI60007 | B11: =Customer_Invoices_AR!B8 -> C2027 | C11: =IFERROR(INDEX(Customer_Master!$B$2:$B$31,MATCH(B11,Customer_Master!$A$2:$A$31,0)),"Unknown Customer") -> Yu Inc | D11: =Customer_Invoices_AR!C8 -> 46069 | E11: =Customer_Invoices_AR!E8 -> 46129 | F11: =Customer_Invoices_AR!D8 -> 4091.62 | G11: =SUMIFS(Cash_Receipts_AR!$E$2:$E$503,Cash_Receipts_AR!$B$2:$B$503,A11) -> 4091.62 | H11: =F11-G11 -> 0 | I11: =IF(H11<=0.01,0,MAX(Assumptions!$B$5-E11,0)) -> 0 | J11: =IF(H11<=0.01,"Paid",IF(I11<=30,"0-30",IF(I11<=60,"31-60",IF(I11<=90,"61-90","90+")))) -> Paid | K11: =IF(H11<=0.01,"Paid",IF(G11>0,"Partially Paid","Unpaid")) -> Paid
A12: =Customer_Invoices_AR!A9 -> ARI60008 | B12: =Customer_Invoices_AR!B9 -> C2009 | C12: =IFERROR(INDEX(Customer_Master!$B$2:$B$31,MATCH(B12,Customer_Master!$A$2:$A$31,0)),"Unknown Customer") -> Gomez-Jenkins | D12: =Customer_Invoices_AR!C9 -> 46072 | E12: =Customer_Invoices_AR!E9 -> 46117 | F12: =Customer_Invoices_AR!D9 -> 673.49 | G12: =SUMIFS(Cash_Receipts_AR!$E$2:$E$503,Cash_Receipts_AR!$B$2:$B$503,A12) -> 673.49 | H12: =F12-G12 -> 0 | I12: =IF(H12<=0.01,0,MAX(Assumptions!$B$5-E12,0)) -> 0 | J12: =IF(H12<=0.01,"Paid",IF(I12<=30,"0-30",IF(I12<=60,"31-60",IF(I12<=90,"61-90","90+")))) -> Paid | K12: =IF(H12<=0.01,"Paid",IF(G12>0,"Partially Paid","Unpaid")) -> Paid
A13: =Customer_Invoices_AR!A10 -> ARI60009 | B13: =Customer_Invoices_AR!B10 -> C2027 | C13: =IFERROR(INDEX(Customer_Master!$B$2:$B$31,MATCH(B13,Customer_Master!$A$2:$A$31,0)),"Unknown Customer") -> Yu Inc | D13: =Customer_Invoices_AR!C10 -> 45902 | E13: =Customer_Invoices_AR!E10 -> 45962 | F13: =Customer_Invoices_AR!D10 -> 4452.11 | G13: =SUMIFS(Cash_Receipts_AR!$E$2:$E$503,Cash_Receipts_AR!$B$2:$B$503,A13) -> 2365.68 | H13: =F13-G13 -> 2086.43 | I13: =IF(H13<=0.01,0,MAX(Assumptions!$B$5-E13,0)) -> 272 | J13: =IF(H13<=0.01,"Paid",IF(I13<=30,"0-30",IF(I13<=60,"31-60",IF(I13<=90,"61-90","90+")))) -> 90+ | K13: =IF(H13<=0.01,"Paid",IF(G13>0,"Partially Paid","Unpaid")) -> Partially Paid
A14: =Customer_Invoices_AR!A11 -> ARI60010 | B14: =Customer_Invoices_AR!B11 -> C2008 | C14: =IFERROR(INDEX(Customer_Master!$B$2:$B$31,MATCH(B14,Customer_Master!$A$2:$A$31,0)),"Unknown Customer") -> Lee-Davis | D14: =Customer_Invoices_AR!C11 -> 46161 | E14: =Customer_Invoices_AR!E11 -> 46221 | F14: =Customer_Invoices_AR!D11 -> 6127.03 | G14: =SUMIFS(Cash_Receipts_AR!$E$2:$E$503,Cash_Receipts_AR!$B$2:$B$503,A14) -> 6127.03 | H14: =F14-G14 -> 0 | I14: =IF(H14<=0.01,0,MAX(Assumptions!$B$5-E14,0)) -> 0 | J14: =IF(H14<=0.01,"Paid",IF(I14<=30,"0-30",IF(I14<=60,"31-60",IF(I14<=90,"61-90","90+")))) -> Paid | K14: =IF(H14<=0.01,"Paid",IF(G14>0,"Partially Paid","Unpaid")) -> Paid
A15: =Customer_Invoices_AR!A12 -> ARI60011 | B15: =Customer_Invoices_AR!B12 -> C2001 | C15: =IFERROR(INDEX(Customer_Master!$B$2:$B$31,MATCH(B15,Customer_Master!$A$2:$A$31,0)),"Unknown Customer") -> Wright Inc | D15: =Customer_Invoices_AR!C12 -> 45965 | E15: =Customer_Invoices_AR!E12 -> 46010 | F15: =Customer_Invoices_AR!D12 -> 3666.96 | G15: =SUMIFS(Cash_Receipts_AR!$E$2:$E$503,Cash_Receipts_AR!$B$2:$B$503,A15) -> 3666.96 | H15: =F15-G15 -> 0 | I15: =IF(H15<=0.01,0,MAX(Assumptions!$B$5-E15,0)) -> 0 | J15: =IF(H15<=0.01,"Paid",IF(I15<=30,"0-30",IF(I15<=60,"31-60",IF(I15<=90,"61-90","90+")))) -> Paid | K15: =IF(H15<=0.01,"Paid",IF(G15>0,"Partially Paid","Unpaid")) -> Paid
A16: =Customer_Invoices_AR!A13 -> ARI60012 | B16: =Customer_Invoices_AR!B13 -> C2016 | C16: =IFERROR(INDEX(Customer_Master!$B$2:$B$31,MATCH(B16,Customer_Master!$A$2:$A$31,0)),"Unknown Customer") -> Williams PLC | D16: =Customer_Invoices_AR!C13 -> 46004 | E16: =Customer_Invoices_AR!E13 -> 46034 | F16: =Customer_Invoices_AR!D13 -> 8288.62 | G16: =SUMIFS(Cash_Receipts_AR!$E$2:$E$503,Cash_Receipts_AR!$B$2:$B$503,A16) -> 8288.62 | H16: =F16-G16 -> 0 | I16: =IF(H16<=0.01,0,MAX(Assumptions!$B$5-E16,0)) -> 0 | J16: =IF(H16<=0.01,"Paid",IF(I16<=30,"0-30",IF(I16<=60,"31-60",IF(I16<=90,"61-90","90+")))) -> Paid | K16: =IF(H16<=0.01,"Paid",IF(G16>0,"Partially Paid","Unpaid")) -> Paid
... A604: =Customer_Invoices_AR!A601 -> ARI60600 | B604: =Customer_Invoices_AR!B601 -> C2021 | C604: =IFERROR(INDEX(Customer_Master!$B$2:$B$31,MATCH(B604,Customer_Master!$A$2:$A$31,0)),"Unknown Customer") -> House-Glover | D604: =Customer_Invoices_AR!C601 -> 45706 | E604: =Customer_Invoices_AR!E601 -> 45766 | F604: =Customer_Invoices_AR!D601 -> 3855.14 | G604: =SUMIFS(Cash_Receipts_AR!$E$2:$E$503,Cash_Receipts_AR!$B$2:$B$503,A604) -> 3855.14 | H604: =F604-G604 -> 0 | I604: =IF(H604<=0.01,0,MAX(Assumptions!$B$5-E604,0)) -> 0 | J604: =IF(H604<=0.01,"Paid",IF(I604<=30,"0-30",IF(I604<=60,"31-60",IF(I604<=90,"61-90","90+")))) -> Paid | K604: =IF(H604<=0.01,"Paid",IF(G604>0,"Partially Paid","Unpaid")) -> Paid
A607: AR Aging Summary (as of Assumptions!B5)
A608: Bucket | B608: Outstanding $ | C608: Invoice Count
A609: 0-30 | B609: =SUMIFS($H$5:$H$604,$J$5:$J$604,A609) -> 36608.27 | C609: =COUNTIFS($J$5:$J$604,A609) -> 19
A610: 31-60 | B610: =SUMIFS($H$5:$H$604,$J$5:$J$604,A610) -> 46667.73 | C610: =COUNTIFS($J$5:$J$604,A610) -> 17
A611: 61-90 | B611: =SUMIFS($H$5:$H$604,$J$5:$J$604,A611) -> 23901.13 | C611: =COUNTIFS($J$5:$J$604,A611) -> 5
A612: 90+ | B612: =SUMIFS($H$5:$H$604,$J$5:$J$604,A612) -> 323070.04 | C612: =COUNTIFS($J$5:$J$604,A612) -> 143

Sheet AR_Partial_Unpaid
A1: Accounts Receivable — Partial / Unpaid Invoice Tracking
A2: Flags customer invoices that are short-paid or fully overdue and unpaid, pulling live from AR_Aging.
A4: AR_Invoice_ID | B4: Customer_Name | C4: Invoice_Amount | D4: Receipts_Amount | E4: Outstanding_Balance | F4: Days_Outstanding | G4: Status | H4: Risk_Flag
A5: =AR_Aging!A5 -> ARI60001 | B5: =AR_Aging!C5 -> Robinson, Jones and Welch | C5: =AR_Aging!F5 -> 6493.93 | D5: =AR_Aging!G5 -> 0 | E5: =AR_Aging!H5 -> 6493.93 | F5: =AR_Aging!I5 -> 203 | G5: =AR_Aging!K5 -> Unpaid | H5: =IF(AND(G5="Unpaid",F5>90),"HIGH - Fully Overdue 90+ Days",IF(G5="Partially Paid","MEDIUM - Short Paid","OK")) -> HIGH - Fully Overdue 90+ Days
A6: =AR_Aging!A6 -> ARI60002 | B6: =AR_Aging!C6 -> Baxter Inc | C6: =AR_Aging!F6 -> 3250.9 | D6: =AR_Aging!G6 -> 1523.91 | E6: =AR_Aging!H6 -> 1726.99 | F6: =AR_Aging!I6 -> 132 | G6: =AR_Aging!K6 -> Partially Paid | H6: =IF(AND(G6="Unpaid",F6>90),"HIGH - Fully Overdue 90+ Days",IF(G6="Partially Paid","MEDIUM - Short Paid","OK")) -> MEDIUM - Short Paid
A7: =AR_Aging!A7 -> ARI60003 | B7: =AR_Aging!C7 -> Brown, Valdez and Lucas | C7: =AR_Aging!F7 -> 715.25 | D7: =AR_Aging!G7 -> 715.25 | E7: =AR_Aging!H7 -> 0 | F7: =AR_Aging!I7 -> 0 | G7: =AR_Aging!K7 -> Paid | H7: =IF(AND(G7="Unpaid",F7>90),"HIGH - Fully Overdue 90+ Days",IF(G7="Partially Paid","MEDIUM - Short Paid","OK")) -> OK
A8: =AR_Aging!A8 -> ARI60004 | B8: =AR_Aging!C8 -> Sanchez, Wheeler and Harvey | C8: =AR_Aging!F8 -> 3252.02 | D8: =AR_Aging!G8 -> 3252.02 | E8: =AR_Aging!H8 -> 0 | F8: =AR_Aging!I8 -> 0 | G8: =AR_Aging!K8 -> Paid | H8: =IF(AND(G8="Unpaid",F8>90),"HIGH - Fully Overdue 90+ Days",IF(G8="Partially Paid","MEDIUM - Short Paid","OK")) -> OK
A9: =AR_Aging!A9 -> ARI60005 | B9: =AR_Aging!C9 -> Baxter Inc | C9: =AR_Aging!F9 -> 6622.57 | D9: =AR_Aging!G9 -> 6622.57 | E9: =AR_Aging!H9 -> 0 | F9: =AR_Aging!I9 -> 0 | G9: =AR_Aging!K9 -> Paid | H9: =IF(AND(G9="Unpaid",F9>90),"HIGH - Fully Overdue 90+ Days",IF(G9="Partially Paid","MEDIUM - Short Paid","OK")) -> OK
A10: =AR_Aging!A10 -> ARI60006 | B10: =AR_Aging!C10 -> Jones Inc | C10: =AR_Aging!F10 -> 8576.41 | D10: =AR_Aging!G10 -> 2625.84 | E10: =AR_Aging!H10 -> 5950.57 | F10: =AR_Aging!I10 -> 277 | G10: =AR_Aging!K10 -> Partially Paid | H10: =IF(AND(G10="Unpaid",F10>90),"HIGH - Fully Overdue 90+ Days",IF(G10="Partially Paid","MEDIUM - Short Paid","OK")) -> MEDIUM - Short Paid
A11: =AR_Aging!A11 -> ARI60007 | B11: =AR_Aging!C11 -> Yu Inc | C11: =AR_Aging!F11 -> 4091.62 | D11: =AR_Aging!G11 -> 4091.62 | E11: =AR_Aging!H11 -> 0 | F11: =AR_Aging!I11 -> 0 | G11: =AR_Aging!K11 -> Paid | H11: =IF(AND(G11="Unpaid",F11>90),"HIGH - Fully Overdue 90+ Days",IF(G11="Partially Paid","MEDIUM - Short Paid","OK")) -> OK
A12: =AR_Aging!A12 -> ARI60008 | B12: =AR_Aging!C12 -> Gomez-Jenkins | C12: =AR_Aging!F12 -> 673.49 | D12: =AR_Aging!G12 -> 673.49 | E12: =AR_Aging!H12 -> 0 | F12: =AR_Aging!I12 -> 0 | G12: =AR_Aging!K12 -> Paid | H12: =IF(AND(G12="Unpaid",F12>90),"HIGH - Fully Overdue 90+ Days",IF(G12="Partially Paid","MEDIUM - Short Paid","OK")) -> OK
A13: =AR_Aging!A13 -> ARI60009 | B13: =AR_Aging!C13 -> Yu Inc | C13: =AR_Aging!F13 -> 4452.11 | D13: =AR_Aging!G13 -> 2365.68 | E13: =AR_Aging!H13 -> 2086.43 | F13: =AR_Aging!I13 -> 272 | G13: =AR_Aging!K13 -> Partially Paid | H13: =IF(AND(G13="Unpaid",F13>90),"HIGH - Fully Overdue 90+ Days",IF(G13="Partially Paid","MEDIUM - Short Paid","OK")) -> MEDIUM - Short Paid
A14: =AR_Aging!A14 -> ARI60010 | B14: =AR_Aging!C14 -> Lee-Davis | C14: =AR_Aging!F14 -> 6127.03 | D14: =AR_Aging!G14 -> 6127.03 | E14: =AR_Aging!H14 -> 0 | F14: =AR_Aging!I14 -> 0 | G14: =AR_Aging!K14 -> Paid | H14: =IF(AND(G14="Unpaid",F14>90),"HIGH - Fully Overdue 90+ Days",IF(G14="Partially Paid","MEDIUM - Short Paid","OK")) -> OK
A15: =AR_Aging!A15 -> ARI60011 | B15: =AR_Aging!C15 -> Wright Inc | C15: =AR_Aging!F15 -> 3666.96 | D15: =AR_Aging!G15 -> 3666.96 | E15: =AR_Aging!H15 -> 0 | F15: =AR_Aging!I15 -> 0 | G15: =AR_Aging!K15 -> Paid | H15: =IF(AND(G15="Unpaid",F15>90),"HIGH - Fully Overdue 90+ Days",IF(G15="Partially Paid","MEDIUM - Short Paid","OK")) -> OK
A16: =AR_Aging!A16 -> ARI60012 | B16: =AR_Aging!C16 -> Williams PLC | C16: =AR_Aging!F16 -> 8288.62 | D16: =AR_Aging!G16 -> 8288.62 | E16: =AR_Aging!H16 -> 0 | F16: =AR_Aging!I16 -> 0 | G16: =AR_Aging!K16 -> Paid | H16: =IF(AND(G16="Unpaid",F16>90),"HIGH - Fully Overdue 90+ Days",IF(G16="Partially Paid","MEDIUM - Short Paid","OK")) -> OK
... A604: =AR_Aging!A604 -> ARI60600 | B604: =AR_Aging!C604 -> House-Glover | C604: =AR_Aging!F604 -> 3855.14 | D604: =AR_Aging!G604 -> 3855.14 | E604: =AR_Aging!H604 -> 0 | F604: =AR_Aging!I604 -> 0 | G604: =AR_Aging!K604 -> Paid | H604: =IF(AND(G604="Unpaid",F604>90),"HIGH - Fully Overdue 90+ Days",IF(G604="Partially Paid","MEDIUM - Short Paid","OK")) -> OK

Sheet AR_Payment_Detail
A1: Helper Table — AR Receipt Detail (feeds DSO_Summary trend)
A2: One row per cash receipt with its matched invoice billing date, used to compute actual days-to-collect by month.
A4: Receipt_ID | B4: Customer_ID | C4: AR_Invoice_ID | D4: Receipt_Date | E4: Receipt_Amount | F4: Billing_Date | G4: Days_To_Collect | H4: Month_Key
A5: =Cash_Receipts_AR!A2 -> ARR70001 | B5: =Cash_Receipts_AR!C2 -> C2014 | C5: =Cash_Receipts_AR!B2 -> ARI60002 | D5: =Cash_Receipts_AR!D2 -> 46095 | E5: =Cash_Receipts_AR!E2 -> 1523.91 | F5: =IFERROR(INDEX(Customer_Invoices_AR!$C$2:$C$601,MATCH(C5,Customer_Invoices_AR!$A$2:$A$601,0)),"") -> 46072 | G5: =IF(F5="","",D5-F5) -> 23 | H5: =IF(F5="","",DATE(YEAR(D5),MONTH(D5),1)) -> 46082
A6: =Cash_Receipts_AR!A3 -> ARR70002 | B6: =Cash_Receipts_AR!C3 -> C2010 | C6: =Cash_Receipts_AR!B3 -> ARI60003 | D6: =Cash_Receipts_AR!D3 -> 46049 | E6: =Cash_Receipts_AR!E3 -> 715.25 | F6: =IFERROR(INDEX(Customer_Invoices_AR!$C$2:$C$601,MATCH(C6,Customer_Invoices_AR!$A$2:$A$601,0)),"") -> 46015 | G6: =IF(F6="","",D6-F6) -> 34 | H6: =IF(F6="","",DATE(YEAR(D6),MONTH(D6),1)) -> 46023
A7: =Cash_Receipts_AR!A4 -> ARR70003 | B7: =Cash_Receipts_AR!C4 -> C2030 | C7: =Cash_Receipts_AR!B4 -> ARI60004 | D7: =Cash_Receipts_AR!D4 -> 45766 | E7: =Cash_Receipts_AR!E4 -> 3252.02 | F7: =IFERROR(INDEX(Customer_Invoices_AR!$C$2:$C$601,MATCH(C7,Customer_Invoices_AR!$A$2:$A$601,0)),"") -> 45754 | G7: =IF(F7="","",D7-F7) -> 12 | H7: =IF(F7="","",DATE(YEAR(D7),MONTH(D7),1)) -> 45748
A8: =Cash_Receipts_AR!A5 -> ARR70004 | B8: =Cash_Receipts_AR!C5 -> C2014 | C8: =Cash_Receipts_AR!B5 -> ARI60005 | D8: =Cash_Receipts_AR!D5 -> 46115 | E8: =Cash_Receipts_AR!E5 -> 6622.57 | F8: =IFERROR(INDEX(Customer_Invoices_AR!$C$2:$C$601,MATCH(C8,Customer_Invoices_AR!$A$2:$A$601,0)),"") -> 46079 | G8: =IF(F8="","",D8-F8) -> 36 | H8: =IF(F8="","",DATE(YEAR(D8),MONTH(D8),1)) -> 46113
A9: =Cash_Receipts_AR!A6 -> ARR70005 | B9: =Cash_Receipts_AR!C6 -> C2004 | C9: =Cash_Receipts_AR!B6 -> ARI60006 | D9: =Cash_Receipts_AR!D6 -> 45970 | E9: =Cash_Receipts_AR!E6 -> 2625.84 | F9: =IFERROR(INDEX(Customer_Invoices_AR!$C$2:$C$601,MATCH(C9,Customer_Invoices_AR!$A$2:$A$601,0)),"") -> 45927 | G9: =IF(F9="","",D9-F9) -> 43 | H9: =IF(F9="","",DATE(YEAR(D9),MONTH(D9),1)) -> 45962
A10: =Cash_Receipts_AR!A7 -> ARR70006 | B10: =Cash_Receipts_AR!C7 -> C2027 | C10: =Cash_Receipts_AR!B7 -> ARI60007 | D10: =Cash_Receipts_AR!D7 -> 46106 | E10: =Cash_Receipts_AR!E7 -> 4091.62 | F10: =IFERROR(INDEX(Customer_Invoices_AR!$C$2:$C$601,MATCH(C10,Customer_Invoices_AR!$A$2:$A$601,0)),"") -> 46069 | G10: =IF(F10="","",D10-F10) -> 37 | H10: =IF(F10="","",DATE(YEAR(D10),MONTH(D10),1)) -> 46082
A11: =Cash_Receipts_AR!A8 -> ARR70007 | B11: =Cash_Receipts_AR!C8 -> C2009 | C11: =Cash_Receipts_AR!B8 -> ARI60008 | D11: =Cash_Receipts_AR!D8 -> 46083 | E11: =Cash_Receipts_AR!E8 -> 673.49 | F11: =IFERROR(INDEX(Customer_Invoices_AR!$C$2:$C$601,MATCH(C11,Customer_Invoices_AR!$A$2:$A$601,0)),"") -> 46072 | G11: =IF(F11="","",D11-F11) -> 11 | H11: =IF(F11="","",DATE(YEAR(D11),MONTH(D11),1)) -> 46082
A12: =Cash_Receipts_AR!A9 -> ARR70008 | B12: =Cash_Receipts_AR!C9 -> C2027 | C12: =Cash_Receipts_AR!B9 -> ARI60009 | D12: =Cash_Receipts_AR!D9 -> 45935 | E12: =Cash_Receipts_AR!E9 -> 2365.68 | F12: =IFERROR(INDEX(Customer_Invoices_AR!$C$2:$C$601,MATCH(C12,Customer_Invoices_AR!$A$2:$A$601,0)),"") -> 45902 | G12: =IF(F12="","",D12-F12) -> 33 | H12: =IF(F12="","",DATE(YEAR(D12),MONTH(D12),1)) -> 45931
A13: =Cash_Receipts_AR!A10 -> ARR70009 | B13: =Cash_Receipts_AR!C10 -> C2008 | C13: =Cash_Receipts_AR!B10 -> ARI60010 | D13: =Cash_Receipts_AR!D10 -> 46185 | E13: =Cash_Receipts_AR!E10 -> 6127.03 | F13: =IFERROR(INDEX(Customer_Invoices_AR!$C$2:$C$601,MATCH(C13,Customer_Invoices_AR!$A$2:$A$601,0)),"") -> 46161 | G13: =IF(F13="","",D13-F13) -> 24 | H13: =IF(F13="","",DATE(YEAR(D13),MONTH(D13),1)) -> 46174
A14: =Cash_Receipts_AR!A11 -> ARR70010 | B14: =Cash_Receipts_AR!C11 -> C2001 | C14: =Cash_Receipts_AR!B11 -> ARI60011 | D14: =Cash_Receipts_AR!D11 -> 45982 | E14: =Cash_Receipts_AR!E11 -> 3666.96 | F14: =IFERROR(INDEX(Customer_Invoices_AR!$C$2:$C$601,MATCH(C14,Customer_Invoices_AR!$A$2:$A$601,0)),"") -> 45965 | G14: =IF(F14="","",D14-F14) -> 17 | H14: =IF(F14="","",DATE(YEAR(D14),MONTH(D14),1)) -> 45962
A15: =Cash_Receipts_AR!A12 -> ARR70011 | B15: =Cash_Receipts_AR!C12 -> C2016 | C15: =Cash_Receipts_AR!B12 -> ARI60012 | D15: =Cash_Receipts_AR!D12 -> 46034 | E15: =Cash_Receipts_AR!E12 -> 8288.62 | F15: =IFERROR(INDEX(Customer_Invoices_AR!$C$2:$C$601,MATCH(C15,Customer_Invoices_AR!$A$2:$A$601,0)),"") -> 46004 | G15: =IF(F15="","",D15-F15) -> 30 | H15: =IF(F15="","",DATE(YEAR(D15),MONTH(D15),1)) -> 46023
A16: =Cash_Receipts_AR!A13 -> ARR70012 | B16: =Cash_Receipts_AR!C13 -> C2025 | C16: =Cash_Receipts_AR!B13 -> ARI60013 | D16: =Cash_Receipts_AR!D13 -> 45999 | E16: =Cash_Receipts_AR!E13 -> 1708.27 | F16: =IFERROR(INDEX(Customer_Invoices_AR!$C$2:$C$601,MATCH(C16,Customer_Invoices_AR!$A$2:$A$601,0)),"") -> 45998 | G16: =IF(F16="","",D16-F16) -> 1 | H16: =IF(F16="","",DATE(YEAR(D16),MONTH(D16),1)) -> 45992
... A506: =Cash_Receipts_AR!A503 -> ARR70502 | B506: =Cash_Receipts_AR!C503 -> C2021 | C506: =Cash_Receipts_AR!B503 -> ARI60600 | D506: =Cash_Receipts_AR!D503 -> 45739 | E506: =Cash_Receipts_AR!E503 -> 3855.14 | F506: =IFERROR(INDEX(Customer_Invoices_AR!$C$2:$C$601,MATCH(C506,Customer_Invoices_AR!$A$2:$A$601,0)),"") -> 45706 | G506: =IF(F506="","",D506-F506) -> 33 | H506: =IF(F506="","",DATE(YEAR(D506),MONTH(D506),1)) -> 45717

Sheet DSO_Summary
A1: Accounts Receivable — Days Sales Outstanding (DSO)
A2: Headline formula-based DSO, plus an actual average days-to-collect trend by month from AR_Payment_Detail.
A4: Headline DSO (formula method)
A5: Ending AR (Outstanding Balance, all invoices) | B5: =SUM(AR_Aging!$B$609:$B$612) -> 430247.17
A6: Total AR Billed (full data period) | B6: =SUM(Customer_Invoices_AR!$D$2:$D$601) -> 2319894.6
A7: Days in Period (data span) | B7: =MAX(Customer_Invoices_AR!$C$2:$C$601)-MIN(Customer_Invoices_AR!$C$2:$C$601) -> 542
A8: DSO = Ending AR / Total AR Billed x Days in Period | B8: =B5/B6*B7 -> 100.51921
A9: Actual Average Days-to-Collect (all settled invoices) | B9: =AVERAGE(AR_Payment_Detail!$G$5:$G$506) -> 18.183267
A11: Monthly Trend — Actual Average Days-to-Collect
A12: Month | B12: Avg Days to Collect | C12: Total Collected ($)
A13: 45658 | B13: =IFERROR(AVERAGEIFS(AR_Payment_Detail!$G$5:$G$506,AR_Payment_Detail!$H$5:$H$506,A13),0) -> 6.5714286 | C13: =SUMIFS(AR_Payment_Detail!$E$5:$E$506,AR_Payment_Detail!$H$5:$H$506,A13) -> 34490.06
A14: 45689 | B14: =IFERROR(AVERAGEIFS(AR_Payment_Detail!$G$5:$G$506,AR_Payment_Detail!$H$5:$H$506,A14),0) -> 19.05 | C14: =SUMIFS(AR_Payment_Detail!$E$5:$E$506,AR_Payment_Detail!$H$5:$H$506,A14) -> 63240.58
A15: 45717 | B15: =IFERROR(AVERAGEIFS(AR_Payment_Detail!$G$5:$G$506,AR_Payment_Detail!$H$5:$H$506,A15),0) -> 21.925926 | C15: =SUMIFS(AR_Payment_Detail!$E$5:$E$506,AR_Payment_Detail!$H$5:$H$506,A15) -> 149556.12
A16: 45748 | B16: =IFERROR(AVERAGEIFS(AR_Payment_Detail!$G$5:$G$506,AR_Payment_Detail!$H$5:$H$506,A16),0) -> 19.705882 | C16: =SUMIFS(AR_Payment_Detail!$E$5:$E$506,AR_Payment_Detail!$H$5:$H$506,A16) -> 154341.64
A17: 45778 | B17: =IFERROR(AVERAGEIFS(AR_Payment_Detail!$G$5:$G$506,AR_Payment_Detail!$H$5:$H$506,A17),0) -> 15.666667 | C17: =SUMIFS(AR_Payment_Detail!$E$5:$E$506,AR_Payment_Detail!$H$5:$H$506,A17) -> 44704.87
A18: 45809 | B18: =IFERROR(AVERAGEIFS(AR_Payment_Detail!$G$5:$G$506,AR_Payment_Detail!$H$5:$H$506,A18),0) -> 16.096774 | C18: =SUMIFS(AR_Payment_Detail!$E$5:$E$506,AR_Payment_Detail!$H$5:$H$506,A18) -> 132992.65
A19: 45839 | B19: =IFERROR(AVERAGEIFS(AR_Payment_Detail!$G$5:$G$506,AR_Payment_Detail!$H$5:$H$506,A19),0) -> 14.974359 | C19: =SUMIFS(AR_Payment_Detail!$E$5:$E$506,AR_Payment_Detail!$H$5:$H$506,A19) -> 96608.09
A20: 45870 | B20: =IFERROR(AVERAGEIFS(AR_Payment_Detail!$G$5:$G$506,AR_Payment_Detail!$H$5:$H$506,A20),0) -> 19.6875 | C20: =SUMIFS(AR_Payment_Detail!$E$5:$E$506,AR_Payment_Detail!$H$5:$H$506,A20) -> 137059.13
A21: 45901 | B21: =IFERROR(AVERAGEIFS(AR_Payment_Detail!$G$5:$G$506,AR_Payment_Detail!$H$5:$H$506,A21),0) -> 14.1 | C21: =SUMIFS(AR_Payment_Detail!$E$5:$E$506,AR_Payment_Detail!$H$5:$H$506,A21) -> 92067.87
A22: 45931 | B22: =IFERROR(AVERAGEIFS(AR_Payment_Detail!$G$5:$G$506,AR_Payment_Detail!$H$5:$H$506,A22),0) -> 17.125 | C22: =SUMIFS(AR_Payment_Detail!$E$5:$E$506,AR_Payment_Detail!$H$5:$H$506,A22) -> 111747.18
A23: 45962 | B23: =IFERROR(AVERAGEIFS(AR_Payment_Detail!$G$5:$G$506,AR_Payment_Detail!$H$5:$H$506,A23),0) -> 19.4 | C23: =SUMIFS(AR_Payment_Detail!$E$5:$E$506,AR_Payment_Detail!$H$5:$H$506,A23) -> 103697.61
A24: 45992 | B24: =IFERROR(AVERAGEIFS(AR_Payment_Detail!$G$5:$G$506,AR_Payment_Detail!$H$5:$H$506,A24),0) -> 17.655172 | C24: =SUMIFS(AR_Payment_Detail!$E$5:$E$506,AR_Payment_Detail!$H$5:$H$506,A24) -> 108692.29
... A31: 46204 | B31: =IFERROR(AVERAGEIFS(AR_Payment_Detail!$G$5:$G$506,AR_Payment_Detail!$H$5:$H$506,A31),0) -> 0 | C31: =SUMIFS(AR_Payment_Detail!$E$5:$E$506,AR_Payment_Detail!$H$5:$H$506,A31) -> 0

Sheet SoD_Check
A1: Compliance — Segregation of Duties (SoD) Check
A2: Base table: Purchase_Orders. Flags any PO where the same person both requested and approved it.
A4: PO_ID | B4: Vendor_ID | C4: PO_Date | D4: PO_Amount | E4: Requested_By | F4: Approved_By | G4: SoD_Flag
A5: =Purchase_Orders!A2 -> PO10001 | B5: =Purchase_Orders!B2 -> V1020 | C5: =Purchase_Orders!C2 -> 46091 | D5: =Purchase_Orders!D2 -> 1309.32 | E5: =Purchase_Orders!F2 -> Shirley Suarez | F5: =Purchase_Orders!G2 -> Evelyn Galvan | G5: =IF(E5=F5,"VIOLATION - Same Person Requested & Approved","OK") -> OK
A6: =Purchase_Orders!A3 -> PO10002 | B6: =Purchase_Orders!B3 -> V1034 | C6: =Purchase_Orders!C3 -> 45782 | D6: =Purchase_Orders!D3 -> 1749.66 | E6: =Purchase_Orders!F3 -> Jimmy Murillo | F6: =Purchase_Orders!G3 -> Shannon Walker | G6: =IF(E6=F6,"VIOLATION - Same Person Requested & Approved","OK") -> OK
A7: =Purchase_Orders!A4 -> PO10003 | B7: =Purchase_Orders!B4 -> V1014 | C7: =Purchase_Orders!C4 -> 45670 | D7: =Purchase_Orders!D4 -> 2691.35 | E7: =Purchase_Orders!F4 -> John Whitehead | F7: =Purchase_Orders!G4 -> Evelyn Galvan | G7: =IF(E7=F7,"VIOLATION - Same Person Requested & Approved","OK") -> OK
A8: =Purchase_Orders!A5 -> PO10004 | B8: =Purchase_Orders!B5 -> V1040 | C8: =Purchase_Orders!C5 -> 45763 | D8: =Purchase_Orders!D5 -> 889.24 | E8: =Purchase_Orders!F5 -> James Powers | F8: =Purchase_Orders!G5 -> Julia Torres | G8: =IF(E8=F8,"VIOLATION - Same Person Requested & Approved","OK") -> OK
A9: =Purchase_Orders!A6 -> PO10005 | B9: =Purchase_Orders!B6 -> V1022 | C9: =Purchase_Orders!C6 -> 45836 | D9: =Purchase_Orders!D6 -> 3058.04 | E9: =Purchase_Orders!F6 -> Deborah Figueroa | F9: =Purchase_Orders!G6 -> Sharon Cherry | G9: =IF(E9=F9,"VIOLATION - Same Person Requested & Approved","OK") -> OK
A10: =Purchase_Orders!A7 -> PO10006 | B10: =Purchase_Orders!B7 -> V1040 | C10: =Purchase_Orders!C7 -> 46129 | D10: =Purchase_Orders!D7 -> 1359.77 | E10: =Purchase_Orders!F7 -> Deborah Figueroa | F10: =Purchase_Orders!G7 -> Marc Moore | G10: =IF(E10=F10,"VIOLATION - Same Person Requested & Approved","OK") -> OK
A11: =Purchase_Orders!A8 -> PO10007 | B11: =Purchase_Orders!B8 -> V1040 | C11: =Purchase_Orders!C8 -> 46184 | D11: =Purchase_Orders!D8 -> 3708.39 | E11: =Purchase_Orders!F8 -> Richard Henson | F11: =Purchase_Orders!G8 -> Evelyn Galvan | G11: =IF(E11=F11,"VIOLATION - Same Person Requested & Approved","OK") -> OK
A12: =Purchase_Orders!A9 -> PO10008 | B12: =Purchase_Orders!B9 -> V1015 | C12: =Purchase_Orders!C9 -> 45810 | D12: =Purchase_Orders!D9 -> 6081.19 | E12: =Purchase_Orders!F9 -> Anna Henderson | F12: =Purchase_Orders!G9 -> Julia Torres | G12: =IF(E12=F12,"VIOLATION - Same Person Requested & Approved","OK") -> OK
A13: =Purchase_Orders!A10 -> PO10009 | B13: =Purchase_Orders!B10 -> V1018 | C13: =Purchase_Orders!C10 -> 46007 | D13: =Purchase_Orders!D10 -> 6038.81 | E13: =Purchase_Orders!F10 -> Denise Jacobs | F13: =Purchase_Orders!G10 -> Marc Moore | G13: =IF(E13=F13,"VIOLATION - Same Person Requested & Approved","OK") -> OK
A14: =Purchase_Orders!A11 -> PO10010 | B14: =Purchase_Orders!B11 -> V1005 | C14: =Purchase_Orders!C11 -> 45875 | D14: =Purchase_Orders!D11 -> 1250.19 | E14: =Purchase_Orders!F11 -> Kevin Mills | F14: =Purchase_Orders!G11 -> Shannon Walker | G14: =IF(E14=F14,"VIOLATION - Same Person Requested & Approved","OK") -> OK
A15: =Purchase_Orders!A12 -> PO10011 | B15: =Purchase_Orders!B12 -> V1024 | C15: =Purchase_Orders!C12 -> 46192 | D15: =Purchase_Orders!D12 -> 760.24 | E15: =Purchase_Orders!F12 -> John Whitehead | F15: =Purchase_Orders!G12 -> Sharon Cochran | G15: =IF(E15=F15,"VIOLATION - Same Person Requested & Approved","OK") -> OK
A16: =Purchase_Orders!A13 -> PO10012 | B16: =Purchase_Orders!B13 -> V1035 | C16: =Purchase_Orders!C13 -> 45950 | D16: =Purchase_Orders!D13 -> 15002.72 | E16: =Purchase_Orders!F13 -> Christine Wright | F16: =Purchase_Orders!G13 -> Julia Torres | G16: =IF(E16=F16,"VIOLATION - Same Person Requested & Approved","OK") -> OK
... A854: =Purchase_Orders!A851 -> PO10850 | B854: =Purchase_Orders!B851 -> V1014 | C854: =Purchase_Orders!C851 -> 45970 | D854: =Purchase_Orders!D851 -> 4104.49 | E854: =Purchase_Orders!F851 -> Stephen Mckee | F854: =Purchase_Orders!G851 -> Shannon Walker | G854: =IF(E854=F854,"VIOLATION - Same Person Requested & Approved","OK") -> OK
A857: Total SoD Violations | B857: =COUNTIF($G$5:$G$854,"VIOLATION*") -> 21

Sheet Risk_Scoring
A1: Risk Assessment — Weighted Transaction Risk Score (AML-style)
A2: Base table: Payment_Log_AP. Score = Large Amount + Round-Dollar + New Vendor + Higher-Risk Geography. Thresholds live in Assumptions.
A4: Payment_ID | B4: Vendor_ID | C4: Vendor_Name | D4: Country | E4: Onboarding_Date | F4: Payment_Date | G4: Payment_Amount | H4: Score_Large_Amount | I4: Score_Round_Dollar | J4: Score_New_Vendor | K4: Score_High_Risk_Geo | L4: Total_Risk_Score | M4: Risk_Level
A5: =Payment_Log_AP!A2 -> PAY40001 | B5: =Payment_Log_AP!C2 -> V1020 | C5: =IFERROR(INDEX(Vendor_Master!$B$2:$B$41,MATCH(B5,Vendor_Master!$A$2:$A$41,0)),"Unknown Vendor") -> Lewis-Porter | D5: =IFERROR(INDEX(Vendor_Master!$D$2:$D$41,MATCH(B5,Vendor_Master!$A$2:$A$41,0)),"Unknown") -> UAE | E5: =IFERROR(INDEX(Vendor_Master!$E$2:$E$41,MATCH(B5,Vendor_Master!$A$2:$A$41,0)),"") -> 45947 | F5: =Payment_Log_AP!D2 -> 46142 | G5: =Payment_Log_AP!E2 -> 1417.41 | H5: =IF(G5>=Assumptions!$B$7,40,IF(G5>=Assumptions!$B$8,20,0)) -> 0 | I5: =IF(MOD(G5,500)=0,20,IF(MOD(G5,100)=0,10,0)) -> 0 | J5: =IF(AND(E5<>"",F5-E5<=Assumptions!$B$9),25,0) -> 0 | K5: =IF(ISNUMBER(SEARCH(D5,Assumptions!$B$10)),15,0) -> 15 | L5: =H5+I5+J5+K5 -> 15 | M5: =IF(L5>=60,"High",IF(L5>=30,"Medium","Low")) -> Low
A6: =Payment_Log_AP!A3 -> PAY40002 | B6: =Payment_Log_AP!C3 -> V1034 | C6: =IFERROR(INDEX(Vendor_Master!$B$2:$B$41,MATCH(B6,Vendor_Master!$A$2:$A$41,0)),"Unknown Vendor") -> Koch-Decker | D6: =IFERROR(INDEX(Vendor_Master!$D$2:$D$41,MATCH(B6,Vendor_Master!$A$2:$A$41,0)),"Unknown") -> Germany | E6: =IFERROR(INDEX(Vendor_Master!$E$2:$E$41,MATCH(B6,Vendor_Master!$A$2:$A$41,0)),"") -> 44738 | F6: =Payment_Log_AP!D3 -> 45805 | G6: =Payment_Log_AP!E3 -> 1749.66 | H6: =IF(G6>=Assumptions!$B$7,40,IF(G6>=Assumptions!$B$8,20,0)) -> 0 | I6: =IF(MOD(G6,500)=0,20,IF(MOD(G6,100)=0,10,0)) -> 0 | J6: =IF(AND(E6<>"",F6-E6<=Assumptions!$B$9),25,0) -> 0 | K6: =IF(ISNUMBER(SEARCH(D6,Assumptions!$B$10)),15,0) -> 0 | L6: =H6+I6+J6+K6 -> 0 | M6: =IF(L6>=60,"High",IF(L6>=30,"Medium","Low")) -> Low
A7: =Payment_Log_AP!A4 -> PAY40003 | B7: =Payment_Log_AP!C4 -> V1014 | C7: =IFERROR(INDEX(Vendor_Master!$B$2:$B$41,MATCH(B7,Vendor_Master!$A$2:$A$41,0)),"Unknown Vendor") -> Flowers, Martin and Kelly | D7: =IFERROR(INDEX(Vendor_Master!$D$2:$D$41,MATCH(B7,Vendor_Master!$A$2:$A$41,0)),"Unknown") -> India | E7: =IFERROR(INDEX(Vendor_Master!$E$2:$E$41,MATCH(B7,Vendor_Master!$A$2:$A$41,0)),"") -> 45001 | F7: =Payment_Log_AP!D4 -> 45683 | G7: =Payment_Log_AP!E4 -> 2691.35 | H7: =IF(G7>=Assumptions!$B$7,40,IF(G7>=Assumptions!$B$8,20,0)) -> 0 | I7: =IF(MOD(G7,500)=0,20,IF(MOD(G7,100)=0,10,0)) -> 0 | J7: =IF(AND(E7<>"",F7-E7<=Assumptions!$B$9),25,0) -> 0 | K7: =IF(ISNUMBER(SEARCH(D7,Assumptions!$B$10)),15,0) -> 15 | L7: =H7+I7+J7+K7 -> 15 | M7: =IF(L7>=60,"High",IF(L7>=30,"Medium","Low")) -> Low
A8: =Payment_Log_AP!A5 -> PAY40004 | B8: =Payment_Log_AP!C5 -> V1040 | C8: =IFERROR(INDEX(Vendor_Master!$B$2:$B$41,MATCH(B8,Vendor_Master!$A$2:$A$41,0)),"Unknown Vendor") -> Santos, Kim and Holmes | D8: =IFERROR(INDEX(Vendor_Master!$D$2:$D$41,MATCH(B8,Vendor_Master!$A$2:$A$41,0)),"Unknown") -> India | E8: =IFERROR(INDEX(Vendor_Master!$E$2:$E$41,MATCH(B8,Vendor_Master!$A$2:$A$41,0)),"") -> 45192 | F8: =Payment_Log_AP!D5 -> 45805 | G8: =Payment_Log_AP!E5 -> 889.24 | H8: =IF(G8>=Assumptions!$B$7,40,IF(G8>=Assumptions!$B$8,20,0)) -> 0 | I8: =IF(MOD(G8,500)=0,20,IF(MOD(G8,100)=0,10,0)) -> 0 | J8: =IF(AND(E8<>"",F8-E8<=Assumptions!$B$9),25,0) -> 0 | K8: =IF(ISNUMBER(SEARCH(D8,Assumptions!$B$10)),15,0) -> 15 | L8: =H8+I8+J8+K8 -> 15 | M8: =IF(L8>=60,"High",IF(L8>=30,"Medium","Low")) -> Low
A9: =Payment_Log_AP!A6 -> PAY40005 | B9: =Payment_Log_AP!C6 -> V1022 | C9: =IFERROR(INDEX(Vendor_Master!$B$2:$B$41,MATCH(B9,Vendor_Master!$A$2:$A$41,0)),"Unknown Vendor") -> Burgess-Patterson | D9: =IFERROR(INDEX(Vendor_Master!$D$2:$D$41,MATCH(B9,Vendor_Master!$A$2:$A$41,0)),"Unknown") -> Germany | E9: =IFERROR(INDEX(Vendor_Master!$E$2:$E$41,MATCH(B9,Vendor_Master!$A$2:$A$41,0)),"") -> 45449 | F9: =Payment_Log_AP!D6 -> 45883 | G9: =Payment_Log_AP!E6 -> 3058.04 | H9: =IF(G9>=Assumptions!$B$7,40,IF(G9>=Assumptions!$B$8,20,0)) -> 0 | I9: =IF(MOD(G9,500)=0,20,IF(MOD(G9,100)=0,10,0)) -> 0 | J9: =IF(AND(E9<>"",F9-E9<=Assumptions!$B$9),25,0) -> 0 | K9: =IF(ISNUMBER(SEARCH(D9,Assumptions!$B$10)),15,0) -> 0 | L9: =H9+I9+J9+K9 -> 0 | M9: =IF(L9>=60,"High",IF(L9>=30,"Medium","Low")) -> Low
A10: =Payment_Log_AP!A7 -> PAY40006 | B10: =Payment_Log_AP!C7 -> V1040 | C10: =IFERROR(INDEX(Vendor_Master!$B$2:$B$41,MATCH(B10,Vendor_Master!$A$2:$A$41,0)),"Unknown Vendor") -> Santos, Kim and Holmes | D10: =IFERROR(INDEX(Vendor_Master!$D$2:$D$41,MATCH(B10,Vendor_Master!$A$2:$A$41,0)),"Unknown") -> India | E10: =IFERROR(INDEX(Vendor_Master!$E$2:$E$41,MATCH(B10,Vendor_Master!$A$2:$A$41,0)),"") -> 45192 | F10: =Payment_Log_AP!D7 -> 46160 | G10: =Payment_Log_AP!E7 -> 1359.77 | H10: =IF(G10>=Assumptions!$B$7,40,IF(G10>=Assumptions!$B$8,20,0)) -> 0 | I10: =IF(MOD(G10,500)=0,20,IF(MOD(G10,100)=0,10,0)) -> 0 | J10: =IF(AND(E10<>"",F10-E10<=Assumptions!$B$9),25,0) -> 0 | K10: =IF(ISNUMBER(SEARCH(D10,Assumptions!$B$10)),15,0) -> 15 | L10: =H10+I10+J10+K10 -> 15 | M10: =IF(L10>=60,"High",IF(L10>=30,"Medium","Low")) -> Low
A11: =Payment_Log_AP!A8 -> PAY40007 | B11: =Payment_Log_AP!C8 -> V1040 | C11: =IFERROR(INDEX(Vendor_Master!$B$2:$B$41,MATCH(B11,Vendor_Master!$A$2:$A$41,0)),"Unknown Vendor") -> Santos, Kim and Holmes | D11: =IFERROR(INDEX(Vendor_Master!$D$2:$D$41,MATCH(B11,Vendor_Master!$A$2:$A$41,0)),"Unknown") -> India | E11: =IFERROR(INDEX(Vendor_Master!$E$2:$E$41,MATCH(B11,Vendor_Master!$A$2:$A$41,0)),"") -> 45192 | F11: =Payment_Log_AP!D8 -> 46193 | G11: =Payment_Log_AP!E8 -> 3708.39 | H11: =IF(G11>=Assumptions!$B$7,40,IF(G11>=Assumptions!$B$8,20,0)) -> 0 | I11: =IF(MOD(G11,500)=0,20,IF(MOD(G11,100)=0,10,0)) -> 0 | J11: =IF(AND(E11<>"",F11-E11<=Assumptions!$B$9),25,0) -> 0 | K11: =IF(ISNUMBER(SEARCH(D11,Assumptions!$B$10)),15,0) -> 15 | L11: =H11+I11+J11+K11 -> 15 | M11: =IF(L11>=60,"High",IF(L11>=30,"Medium","Low")) -> Low
A12: =Payment_Log_AP!A9 -> PAY40008 | B12: =Payment_Log_AP!C9 -> V1015 | C12: =IFERROR(INDEX(Vendor_Master!$B$2:$B$41,MATCH(B12,Vendor_Master!$A$2:$A$41,0)),"Unknown Vendor") -> Zuniga, Wong and Lynch | D12: =IFERROR(INDEX(Vendor_Master!$D$2:$D$41,MATCH(B12,Vendor_Master!$A$2:$A$41,0)),"Unknown") -> USA | E12: =IFERROR(INDEX(Vendor_Master!$E$2:$E$41,MATCH(B12,Vendor_Master!$A$2:$A$41,0)),"") -> 45621 | F12: =Payment_Log_AP!D9 -> 45859 | G12: =Payment_Log_AP!E9 -> 6081.19 | H12: =IF(G12>=Assumptions!$B$7,40,IF(G12>=Assumptions!$B$8,20,0)) -> 20 | I12: =IF(MOD(G12,500)=0,20,IF(MOD(G12,100)=0,10,0)) -> 0 | J12: =IF(AND(E12<>"",F12-E12<=Assumptions!$B$9),25,0) -> 0 | K12: =IF(ISNUMBER(SEARCH(D12,Assumptions!$B$10)),15,0) -> 0 | L12: =H12+I12+J12+K12 -> 20 | M12: =IF(L12>=60,"High",IF(L12>=30,"Medium","Low")) -> Low
A13: =Payment_Log_AP!A10 -> PAY40009 | B13: =Payment_Log_AP!C10 -> V1005 | C13: =IFERROR(INDEX(Vendor_Master!$B$2:$B$41,MATCH(B13,Vendor_Master!$A$2:$A$41,0)),"Unknown Vendor") -> Cole LLC | D13: =IFERROR(INDEX(Vendor_Master!$D$2:$D$41,MATCH(B13,Vendor_Master!$A$2:$A$41,0)),"Unknown") -> UK | E13: =IFERROR(INDEX(Vendor_Master!$E$2:$E$41,MATCH(B13,Vendor_Master!$A$2:$A$41,0)),"") -> 45423 | F13: =Payment_Log_AP!D10 -> 45885 | G13: =Payment_Log_AP!E10 -> 1466.07 | H13: =IF(G13>=Assumptions!$B$7,40,IF(G13>=Assumptions!$B$8,20,0)) -> 0 | I13: =IF(MOD(G13,500)=0,20,IF(MOD(G13,100)=0,10,0)) -> 0 | J13: =IF(AND(E13<>"",F13-E13<=Assumptions!$B$9),25,0) -> 0 | K13: =IF(ISNUMBER(SEARCH(D13,Assumptions!$B$10)),15,0) -> 0 | L13: =H13+I13+J13+K13 -> 0 | M13: =IF(L13>=60,"High",IF(L13>=30,"Medium","Low")) -> Low
A14: =Payment_Log_AP!A11 -> PAY40010 | B14: =Payment_Log_AP!C11 -> V1035 | C14: =IFERROR(INDEX(Vendor_Master!$B$2:$B$41,MATCH(B14,Vendor_Master!$A$2:$A$41,0)),"Unknown Vendor") -> Allen PLC | D14: =IFERROR(INDEX(Vendor_Master!$D$2:$D$41,MATCH(B14,Vendor_Master!$A$2:$A$41,0)),"Unknown") -> Canada | E14: =IFERROR(INDEX(Vendor_Master!$E$2:$E$41,MATCH(B14,Vendor_Master!$A$2:$A$41,0)),"") -> 45048 | F14: =Payment_Log_AP!D11 -> 45989 | G14: =Payment_Log_AP!E11 -> 15002.72 | H14: =IF(G14>=Assumptions!$B$7,40,IF(G14>=Assumptions!$B$8,20,0)) -> 40 | I14: =IF(MOD(G14,500)=0,20,IF(MOD(G14,100)=0,10,0)) -> 0 | J14: =IF(AND(E14<>"",F14-E14<=Assumptions!$B$9),25,0) -> 0 | K14: =IF(ISNUMBER(SEARCH(D14,Assumptions!$B$10)),15,0) -> 0 | L14: =H14+I14+J14+K14 -> 40 | M14: =IF(L14>=60,"High",IF(L14>=30,"Medium","Low")) -> Medium
A15: =Payment_Log_AP!A12 -> PAY40011 | B15: =Payment_Log_AP!C12 -> V1016 | C15: =IFERROR(INDEX(Vendor_Master!$B$2:$B$41,MATCH(B15,Vendor_Master!$A$2:$A$41,0)),"Unknown Vendor") -> Sanchez, Ford and Nelson | D15: =IFERROR(INDEX(Vendor_Master!$D$2:$D$41,MATCH(B15,Vendor_Master!$A$2:$A$41,0)),"Unknown") -> India | E15: =IFERROR(INDEX(Vendor_Master!$E$2:$E$41,MATCH(B15,Vendor_Master!$A$2:$A$41,0)),"") -> 44832 | F15: =Payment_Log_AP!D12 -> 46196 | G15: =Payment_Log_AP!E12 -> 911.91 | H15: =IF(G15>=Assumptions!$B$7,40,IF(G15>=Assumptions!$B$8,20,0)) -> 0 | I15: =IF(MOD(G15,500)=0,20,IF(MOD(G15,100)=0,10,0)) -> 0 | J15: =IF(AND(E15<>"",F15-E15<=Assumptions!$B$9),25,0) -> 0 | K15: =IF(ISNUMBER(SEARCH(D15,Assumptions!$B$10)),15,0) -> 15 | L15: =H15+I15+J15+K15 -> 15 | M15: =IF(L15>=60,"High",IF(L15>=30,"Medium","Low")) -> Low
A16: =Payment_Log_AP!A13 -> PAY40012 | B16: =Payment_Log_AP!C13 -> V1002 | C16: =IFERROR(INDEX(Vendor_Master!$B$2:$B$41,MATCH(B16,Vendor_Master!$A$2:$A$41,0)),"Unknown Vendor") -> Garcia, Yang and Gardner | D16: =IFERROR(INDEX(Vendor_Master!$D$2:$D$41,MATCH(B16,Vendor_Master!$A$2:$A$41,0)),"Unknown") -> UK | E16: =IFERROR(INDEX(Vendor_Master!$E$2:$E$41,MATCH(B16,Vendor_Master!$A$2:$A$41,0)),"") -> 44914 | F16: =Payment_Log_AP!D13 -> 45753 | G16: =Payment_Log_AP!E13 -> 1222.88 | H16: =IF(G16>=Assumptions!$B$7,40,IF(G16>=Assumptions!$B$8,20,0)) -> 0 | I16: =IF(MOD(G16,500)=0,20,IF(MOD(G16,100)=0,10,0)) -> 0 | J16: =IF(AND(E16<>"",F16-E16<=Assumptions!$B$9),25,0) -> 0 | K16: =IF(ISNUMBER(SEARCH(D16,Assumptions!$B$10)),15,0) -> 0 | L16: =H16+I16+J16+K16 -> 0 | M16: =IF(L16>=60,"High",IF(L16>=30,"Medium","Low")) -> Low
... A756: =Payment_Log_AP!A753 -> PAY40752 | B756: =Payment_Log_AP!C753 -> V1014 | C756: =IFERROR(INDEX(Vendor_Master!$B$2:$B$41,MATCH(B756,Vendor_Master!$A$2:$A$41,0)),"Unknown Vendor") -> Flowers, Martin and Kelly | D756: =IFERROR(INDEX(Vendor_Master!$D$2:$D$41,MATCH(B756,Vendor_Master!$A$2:$A$41,0)),"Unknown") -> India | E756: =IFERROR(INDEX(Vendor_Master!$E$2:$E$41,MATCH(B756,Vendor_Master!$A$2:$A$41,0)),"") -> 45001 | F756: =Payment_Log_AP!D753 -> 46002 | G756: =Payment_Log_AP!E753 -> 4104.49 | H756: =IF(G756>=Assumptions!$B$7,40,IF(G756>=Assumptions!$B$8,20,0)) -> 0 | I756: =IF(MOD(G756,500)=0,20,IF(MOD(G756,100)=0,10,0)) -> 0 | J756: =IF(AND(E756<>"",F756-E756<=Assumptions!$B$9),25,0) -> 0 | K756: =IF(ISNUMBER(SEARCH(D756,Assumptions!$B$10)),15,0) -> 15 | L756: =H756+I756+J756+K756 -> 15 | M756: =IF(L756>=60,"High",IF(L756>=30,"Medium","Low")) -> Low
A759: Risk Level Summary
A760: High | B760: =COUNTIF($M$5:$M$756,A760) -> 21
A761: Medium | B761: =COUNTIF($M$5:$M$756,A761) -> 151
A762: Low | B762: =COUNTIF($M$5:$M$756,A762) -> 580

Sheet Vendor_Spend
A1: Procurement — Vendor Spend Analysis (Pareto 80/20)
A2: Base table: Vendor_Master. Total spend = sum of all PO amounts by vendor. Ranked so cumulative % reveals the vendors driving 80% of spend.
A4: Vendor_ID | B4: Vendor_Name | C4: Category | D4: Country | E4: Total_PO_Spend | F4: Spend_Rank | G4: Cumulative_Spend | H4: Cumulative_% | I4: Pareto_Flag
A5: =Vendor_Master!A2 -> V1001 | B5: =Vendor_Master!B2 -> Figueroa and Sons | C5: =Vendor_Master!C2 -> Travel & Logistics | D5: =Vendor_Master!D2 -> USA | E5: =SUMIFS(Purchase_Orders!$D$2:$D$851,Purchase_Orders!$B$2:$B$851,A5) -> 105301.08 | F5: =RANK(E5,$E$5:$E$44) -> 3 | G5: =SUMIF($F$5:$F$44,"<="&F5,$E$5:$E$44) -> 404791.72 | H5: =G5/SUM($E$5:$E$44) -> 0.1358115 | I5: =IF(H5<=0.8,"Top 80% Driver","Remaining 20%") -> Top 80% Driver
A6: =Vendor_Master!A3 -> V1002 | B6: =Vendor_Master!B3 -> Garcia, Yang and Gardner | C6: =Vendor_Master!C3 -> Office Supplies | D6: =Vendor_Master!D3 -> UK | E6: =SUMIFS(Purchase_Orders!$D$2:$D$851,Purchase_Orders!$B$2:$B$851,A6) -> 86264.39 | F6: =RANK(E6,$E$5:$E$44) -> 13 | G6: =SUMIF($F$5:$F$44,"<="&F6,$E$5:$E$44) -> 1332666.2 | H6: =G6/SUM($E$5:$E$44) -> 0.44712229 | I6: =IF(H6<=0.8,"Top 80% Driver","Remaining 20%") -> Top 80% Driver
A7: =Vendor_Master!A4 -> V1003 | B7: =Vendor_Master!B4 -> Johnson and Sons | C7: =Vendor_Master!C4 -> Travel & Logistics | D7: =Vendor_Master!D4 -> UAE | E7: =SUMIFS(Purchase_Orders!$D$2:$D$851,Purchase_Orders!$B$2:$B$851,A7) -> 36190.95 | F7: =RANK(E7,$E$5:$E$44) -> 38 | G7: =SUMIF($F$5:$F$44,"<="&F7,$E$5:$E$44) -> 2915931.3 | H7: =G7/SUM($E$5:$E$44) -> 0.9783229 | I7: =IF(H7<=0.8,"Top 80% Driver","Remaining 20%") -> Remaining 20%
A8: =Vendor_Master!A5 -> V1004 | B8: =Vendor_Master!B5 -> Johnson, Gonzalez and Santos | C8: =Vendor_Master!C5 -> Marketing | D8: =Vendor_Master!D5 -> Germany | E8: =SUMIFS(Purchase_Orders!$D$2:$D$851,Purchase_Orders!$B$2:$B$851,A8) -> 50472.02 | F8: =RANK(E8,$E$5:$E$44) -> 33 | G8: =SUMIF($F$5:$F$44,"<="&F8,$E$5:$E$44) -> 2693184.2 | H8: =G8/SUM($E$5:$E$44) -> 0.90358909 | I8: =IF(H8<=0.8,"Top 80% Driver","Remaining 20%") -> Remaining 20%
A9: =Vendor_Master!A6 -> V1005 | B9: =Vendor_Master!B6 -> Cole LLC | C9: =Vendor_Master!C6 -> IT Services | D9: =Vendor_Master!D6 -> UK | E9: =SUMIFS(Purchase_Orders!$D$2:$D$851,Purchase_Orders!$B$2:$B$851,A9) -> 96640.97 | F9: =RANK(E9,$E$5:$E$44) -> 6 | G9: =SUMIF($F$5:$F$44,"<="&F9,$E$5:$E$44) -> 701396.43 | H9: =G9/SUM($E$5:$E$44) -> 0.23532522 | I9: =IF(H9<=0.8,"Top 80% Driver","Remaining 20%") -> Top 80% Driver
A10: =Vendor_Master!A7 -> V1006 | B10: =Vendor_Master!B7 -> Blake and Sons | C10: =Vendor_Master!C7 -> Marketing | D10: =Vendor_Master!D7 -> UK | E10: =SUMIFS(Purchase_Orders!$D$2:$D$851,Purchase_Orders!$B$2:$B$851,A10) -> 64172.49 | F10: =RANK(E10,$E$5:$E$44) -> 25 | G10: =SUMIF($F$5:$F$44,"<="&F10,$E$5:$E$44) -> 2228370.2 | H10: =G10/SUM($E$5:$E$44) -> 0.74763954 | I10: =IF(H10<=0.8,"Top 80% Driver","Remaining 20%") -> Top 80% Driver
A11: =Vendor_Master!A8 -> V1007 | B11: =Vendor_Master!B8 -> Ramirez-Lewis | C11: =Vendor_Master!C8 -> Office Supplies | D11: =Vendor_Master!D8 -> Germany | E11: =SUMIFS(Purchase_Orders!$D$2:$D$851,Purchase_Orders!$B$2:$B$851,A11) -> 98769.41 | F11: =RANK(E11,$E$5:$E$44) -> 5 | G11: =SUMIF($F$5:$F$44,"<="&F11,$E$5:$E$44) -> 604755.46 | H11: =G11/SUM($E$5:$E$44) -> 0.20290125 | I11: =IF(H11<=0.8,"Top 80% Driver","Remaining 20%") -> Top 80% Driver
A12: =Vendor_Master!A9 -> V1008 | B12: =Vendor_Master!B9 -> Davis Inc | C12: =Vendor_Master!C9 -> Software Licensing | D12: =Vendor_Master!D9 -> Canada | E12: =SUMIFS(Purchase_Orders!$D$2:$D$851,Purchase_Orders!$B$2:$B$851,A12) -> 42190.54 | F12: =RANK(E12,$E$5:$E$44) -> 37 | G12: =SUMIF($F$5:$F$44,"<="&F12,$E$5:$E$44) -> 2879740.4 | H12: =G12/SUM($E$5:$E$44) -> 0.96618049 | I12: =IF(H12<=0.8,"Top 80% Driver","Remaining 20%") -> Remaining 20%
A13: =Vendor_Master!A10 -> V1009 | B13: =Vendor_Master!B10 -> Munoz-Roman | C13: =Vendor_Master!C10 -> Professional Services | D13: =Vendor_Master!D10 -> India | E13: =SUMIFS(Purchase_Orders!$D$2:$D$851,Purchase_Orders!$B$2:$B$851,A13) -> 79994.73 | F13: =RANK(E13,$E$5:$E$44) -> 17 | G13: =SUMIF($F$5:$F$44,"<="&F13,$E$5:$E$44) -> 1658621.5 | H13: =G13/SUM($E$5:$E$44) -> 0.5564834 | I13: =IF(H13<=0.8,"Top 80% Driver","Remaining 20%") -> Top 80% Driver
A14: =Vendor_Master!A11 -> V1010 | B14: =Vendor_Master!B11 -> Martinez, Nielsen and Miller | C14: =Vendor_Master!C11 -> Software Licensing | D14: =Vendor_Master!D11 -> India | E14: =SUMIFS(Purchase_Orders!$D$2:$D$851,Purchase_Orders!$B$2:$B$851,A14) -> 60363.6 | F14: =RANK(E14,$E$5:$E$44) -> 28 | G14: =SUMIF($F$5:$F$44,"<="&F14,$E$5:$E$44) -> 2412746 | H14: =G14/SUM($E$5:$E$44) -> 0.80949941 | I14: =IF(H14<=0.8,"Top 80% Driver","Remaining 20%") -> Remaining 20%
A15: =Vendor_Master!A12 -> V1011 | B15: =Vendor_Master!B12 -> Montgomery, Hensley and Ray | C15: =Vendor_Master!C12 -> Facilities | D15: =Vendor_Master!D12 -> USA | E15: =SUMIFS(Purchase_Orders!$D$2:$D$851,Purchase_Orders!$B$2:$B$851,A15) -> 90489.59 | F15: =RANK(E15,$E$5:$E$44) -> 10 | G15: =SUMIF($F$5:$F$44,"<="&F15,$E$5:$E$44) -> 1069138.9 | H15: =G15/SUM($E$5:$E$44) -> 0.35870635 | I15: =IF(H15<=0.8,"Top 80% Driver","Remaining 20%") -> Top 80% Driver
A16: =Vendor_Master!A13 -> V1012 | B16: =Vendor_Master!B13 -> Stanley LLC | C16: =Vendor_Master!C13 -> Marketing | D16: =Vendor_Master!D13 -> India | E16: =SUMIFS(Purchase_Orders!$D$2:$D$851,Purchase_Orders!$B$2:$B$851,A16) -> 127808.51 | F16: =RANK(E16,$E$5:$E$44) -> 2 | G16: =SUMIF($F$5:$F$44,"<="&F16,$E$5:$E$44) -> 299490.64 | H16: =G16/SUM($E$5:$E$44) -> 0.10048198 | I16: =IF(H16<=0.8,"Top 80% Driver","Remaining 20%") -> Top 80% Driver
... A44: =Vendor_Master!A41 -> V1040 | B44: =Vendor_Master!B41 -> Santos, Kim and Holmes | C44: =Vendor_Master!C41 -> Office Supplies | D44: =Vendor_Master!D41 -> India | E44: =SUMIFS(Purchase_Orders!$D$2:$D$851,Purchase_Orders!$B$2:$B$851,A44) -> 57641.69 | F44: =RANK(E44,$E$5:$E$44) -> 31 | G44: =SUMIF($F$5:$F$44,"<="&F44,$E$5:$E$44) -> 2588703.7 | H44: =G44/SUM($E$5:$E$44) -> 0.8685349 | I44: =IF(H44<=0.8,"Top 80% Driver","Remaining 20%") -> Remaining 20%

Sheet New_Vendor_Risk
A1: Procurement — New Vendor Risk Flagging
A2: Flags vendors onboarded recently (within Assumptions!B9 days of the report date) whose total spend is unusually large relative to the vendor base.
A4: Vendor_ID | B4: Vendor_Name | C4: Category | D4: Onboarding_Date | E4: Days_Since_Onboarding | F4: Total_PO_Spend | G4: Avg_Vendor_Spend (all) | H4: Flag
A5: =Vendor_Master!A2 -> V1001 | B5: =Vendor_Master!B2 -> Figueroa and Sons | C5: =Vendor_Master!C2 -> Travel & Logistics | D5: =Vendor_Master!E2 -> 45572 | E5: =Assumptions!$B$5-D5 -> 662 | F5: =Vendor_Spend!E5 -> 105301.08 | G5: =AVERAGE(Vendor_Spend!$E$5:$E$44) -> 74513.52 | H5: =IF(AND(E5<=Assumptions!$B$9,F5>G5*2),"FLAG - New Vendor, High Spend","OK") -> OK
A6: =Vendor_Master!A3 -> V1002 | B6: =Vendor_Master!B3 -> Garcia, Yang and Gardner | C6: =Vendor_Master!C3 -> Office Supplies | D6: =Vendor_Master!E3 -> 44914 | E6: =Assumptions!$B$5-D6 -> 1320 | F6: =Vendor_Spend!E6 -> 86264.39 | G6: =AVERAGE(Vendor_Spend!$E$5:$E$44) -> 74513.52 | H6: =IF(AND(E6<=Assumptions!$B$9,F6>G6*2),"FLAG - New Vendor, High Spend","OK") -> OK
A7: =Vendor_Master!A4 -> V1003 | B7: =Vendor_Master!B4 -> Johnson and Sons | C7: =Vendor_Master!C4 -> Travel & Logistics | D7: =Vendor_Master!E4 -> 45495 | E7: =Assumptions!$B$5-D7 -> 739 | F7: =Vendor_Spend!E7 -> 36190.95 | G7: =AVERAGE(Vendor_Spend!$E$5:$E$44) -> 74513.52 | H7: =IF(AND(E7<=Assumptions!$B$9,F7>G7*2),"FLAG - New Vendor, High Spend","OK") -> OK
A8: =Vendor_Master!A5 -> V1004 | B8: =Vendor_Master!B5 -> Johnson, Gonzalez and Santos | C8: =Vendor_Master!C5 -> Marketing | D8: =Vendor_Master!E5 -> 44929 | E8: =Assumptions!$B$5-D8 -> 1305 | F8: =Vendor_Spend!E8 -> 50472.02 | G8: =AVERAGE(Vendor_Spend!$E$5:$E$44) -> 74513.52 | H8: =IF(AND(E8<=Assumptions!$B$9,F8>G8*2),"FLAG - New Vendor, High Spend","OK") -> OK
A9: =Vendor_Master!A6 -> V1005 | B9: =Vendor_Master!B6 -> Cole LLC | C9: =Vendor_Master!C6 -> IT Services | D9: =Vendor_Master!E6 -> 45423 | E9: =Assumptions!$B$5-D9 -> 811 | F9: =Vendor_Spend!E9 -> 96640.97 | G9: =AVERAGE(Vendor_Spend!$E$5:$E$44) -> 74513.52 | H9: =IF(AND(E9<=Assumptions!$B$9,F9>G9*2),"FLAG - New Vendor, High Spend","OK") -> OK
A10: =Vendor_Master!A7 -> V1006 | B10: =Vendor_Master!B7 -> Blake and Sons | C10: =Vendor_Master!C7 -> Marketing | D10: =Vendor_Master!E7 -> 45841 | E10: =Assumptions!$B$5-D10 -> 393 | F10: =Vendor_Spend!E10 -> 64172.49 | G10: =AVERAGE(Vendor_Spend!$E$5:$E$44) -> 74513.52 | H10: =IF(AND(E10<=Assumptions!$B$9,F10>G10*2),"FLAG - New Vendor, High Spend","OK") -> OK
A11: =Vendor_Master!A8 -> V1007 | B11: =Vendor_Master!B8 -> Ramirez-Lewis | C11: =Vendor_Master!C8 -> Office Supplies | D11: =Vendor_Master!E8 -> 45665 | E11: =Assumptions!$B$5-D11 -> 569 | F11: =Vendor_Spend!E11 -> 98769.41 | G11: =AVERAGE(Vendor_Spend!$E$5:$E$44) -> 74513.52 | H11: =IF(AND(E11<=Assumptions!$B$9,F11>G11*2),"FLAG - New Vendor, High Spend","OK") -> OK
A12: =Vendor_Master!A9 -> V1008 | B12: =Vendor_Master!B9 -> Davis Inc | C12: =Vendor_Master!C9 -> Software Licensing | D12: =Vendor_Master!E9 -> 45769 | E12: =Assumptions!$B$5-D12 -> 465 | F12: =Vendor_Spend!E12 -> 42190.54 | G12: =AVERAGE(Vendor_Spend!$E$5:$E$44) -> 74513.52 | H12: =IF(AND(E12<=Assumptions!$B$9,F12>G12*2),"FLAG - New Vendor, High Spend","OK") -> OK
A13: =Vendor_Master!A10 -> V1009 | B13: =Vendor_Master!B10 -> Munoz-Roman | C13: =Vendor_Master!C10 -> Professional Services | D13: =Vendor_Master!E10 -> 45129 | E13: =Assumptions!$B$5-D13 -> 1105 | F13: =Vendor_Spend!E13 -> 79994.73 | G13: =AVERAGE(Vendor_Spend!$E$5:$E$44) -> 74513.52 | H13: =IF(AND(E13<=Assumptions!$B$9,F13>G13*2),"FLAG - New Vendor, High Spend","OK") -> OK
A14: =Vendor_Master!A11 -> V1010 | B14: =Vendor_Master!B11 -> Martinez, Nielsen and Miller | C14: =Vendor_Master!C11 -> Software Licensing | D14: =Vendor_Master!E11 -> 45715 | E14: =Assumptions!$B$5-D14 -> 519 | F14: =Vendor_Spend!E14 -> 60363.6 | G14: =AVERAGE(Vendor_Spend!$E$5:$E$44) -> 74513.52 | H14: =IF(AND(E14<=Assumptions!$B$9,F14>G14*2),"FLAG - New Vendor, High Spend","OK") -> OK
A15: =Vendor_Master!A12 -> V1011 | B15: =Vendor_Master!B12 -> Montgomery, Hensley and Ray | C15: =Vendor_Master!C12 -> Facilities | D15: =Vendor_Master!E12 -> 45025 | E15: =Assumptions!$B$5-D15 -> 1209 | F15: =Vendor_Spend!E15 -> 90489.59 | G15: =AVERAGE(Vendor_Spend!$E$5:$E$44) -> 74513.52 | H15: =IF(AND(E15<=Assumptions!$B$9,F15>G15*2),"FLAG - New Vendor, High Spend","OK") -> OK
A16: =Vendor_Master!A13 -> V1012 | B16: =Vendor_Master!B13 -> Stanley LLC | C16: =Vendor_Master!C13 -> Marketing | D16: =Vendor_Master!E13 -> 45675 | E16: =Assumptions!$B$5-D16 -> 559 | F16: =Vendor_Spend!E16 -> 127808.51 | G16: =AVERAGE(Vendor_Spend!$E$5:$E$44) -> 74513.52 | H16: =IF(AND(E16<=Assumptions!$B$9,F16>G16*2),"FLAG - New Vendor, High Spend","OK") -> OK
... A44: =Vendor_Master!A41 -> V1040 | B44: =Vendor_Master!B41 -> Santos, Kim and Holmes | C44: =Vendor_Master!C41 -> Office Supplies | D44: =Vendor_Master!E41 -> 45192 | E44: =Assumptions!$B$5-D44 -> 1042 | F44: =Vendor_Spend!E44 -> 57641.69 | G44: =AVERAGE(Vendor_Spend!$E$5:$E$44) -> 74513.52 | H44: =IF(AND(E44<=Assumptions!$B$9,F44>G44*2),"FLAG - New Vendor, High Spend","OK") -> OK
A47: New Vendor Risk Flags Count | B47: =COUNTIF($H$5:$H$44,"FLAG*") -> 0

Sheet Cash_Outflow_Forecast
A1: Forecasting — Cash Outflow / AP Payment Forecast
A2: Historical monthly AP payments (from DPO_Summary) projected forward 3 months with FORECAST (classic linear-regression function, compatible with older Excel).
A4: Month | B4: Month_Index | C4: Actual_AP_Paid ($) | D4: Forecast_AP_Paid ($)
A5: 45658 | B5: 1 | C5: =DPO_Summary!C13 -> 28576.85
A6: 45689 | B6: 2 | C6: =DPO_Summary!C14 -> 119868.99
A7: 45717 | B7: 3 | C7: =DPO_Summary!C15 -> 138285.77
A8: 45748 | B8: 4 | C8: =DPO_Summary!C16 -> 151944.6
A9: 45778 | B9: 5 | C9: =DPO_Summary!C17 -> 115131.97
A10: 45809 | B10: 6 | C10: =DPO_Summary!C18 -> 127916.17
A11: 45839 | B11: 7 | C11: =DPO_Summary!C19 -> 153034.98
A12: 45870 | B12: 8 | C12: =DPO_Summary!C20 -> 155487.54
A13: 45901 | B13: 9 | C13: =DPO_Summary!C21 -> 156557.35
A14: 45931 | B14: 10 | C14: =DPO_Summary!C22 -> 180558.89
A15: 45962 | B15: 11 | C15: =DPO_Summary!C23 -> 124879.11
A16: 45992 | B16: 12 | C16: =DPO_Summary!C24 -> 128841.83
... A23: 46204 | B23: 19 | C23: =DPO_Summary!C31 -> 13225.35
A24: 46235 | B24: 20 | D24: =FORECAST(B24,$C$5:$C$23,$B$5:$B$23) -> 143281.12
A25: 46266 | B25: 21 | D25: =FORECAST(B25,$C$5:$C$23,$B$5:$B$23) -> 144233.91
A26: 46296 | B26: 22 | D26: =FORECAST(B26,$C$5:$C$23,$B$5:$B$23) -> 145186.7
A29: 3-Month Forward Cash Outflow Obligation (sum of forecast) | B29: =SUM(D24:D26) -> 432701.73

Sheet RCM
A1: Compliance — Risk & Control Matrix (RCM)
A2: Internal-audit style RCM. Result and Pass/Fail columns are live formulas pulling straight from the modules — refresh the workbook and this re-tests itself.
A4: Process | B4: Key Risk | C4: Control | D4: Test Performed | E4: Result (live) | F4: Pass / Fail
A5: Procurement – PO Approval | B5: Requester also approves their own PO (segregation-of-duties break) | C5: System/policy requires a different approver than requester | D5: Count POs where Requested_By = Approved_By | E5: =SoD_Check!$B$857 -> 21 | F5: =IF(E5=0,"PASS","FAIL - Exceptions Found") -> FAIL - Exceptions Found
A6: Procurement – 3-Way Match | B6: Goods/services invoiced without a matching receipt, or PO/GRN/Invoice amounts disagree | C6: 3-way match required before payment release | D6: Count PO rows flagged EXCEPTION on 3Way_Match | E6: =COUNTIF(3Way_Match!$L$5:$L$854,"EXCEPTION") -> 160 | F6: =IF(E6=0,"PASS","FAIL - Exceptions Found") -> FAIL - Exceptions Found
A7: Accounts Payable – Duplicate Payment | B7: Same invoice paid more than once | C7: System blocks a second payment against a settled invoice; periodic duplicate-payment review | D7: Count invoices flagged DUPLICATE on Duplicate_Payments | E7: =COUNTIF(Duplicate_Payments!$H$5:$H$885,"DUPLICATE*") -> 16 | F7: =IF(E7=0,"PASS","FAIL - Exceptions Found") -> FAIL - Exceptions Found
A8: Treasury – Bank Reconciliation | B8: Payments booked but never clear the bank, or bank activity with no AP record (fraud / error indicator) | C8: Monthly bank reconciliation performed and signed off | D8: Count unmatched payments (Part A) + unexplained bank items (Part B) | E8: =COUNTIF(Bank_Reconciliation!$H$6:$H$757,"Unmatched*")+COUNTIF(Bank_Reconciliation!$G$762:$G$1543,"Unexplained*") -> 30 | F8: =IF(E8=0,"PASS","FAIL - Exceptions Found") -> FAIL - Exceptions Found
A9: Accounts Receivable – Collections | B9: Customer balances aged past 90 days go uncollected, increasing bad-debt risk | C9: Aging reviewed weekly; collections escalation at 90 days | D9: Count AR invoices in the 90+ aging bucket | E9: =AR_Aging!$C$612 -> 143 | F9: =IF(E9=0,"PASS","FAIL - Exceptions Found") -> FAIL - Exceptions Found
A10: Risk – AML Transaction Monitoring | B10: Large, round-dollar, or new-vendor payments to higher-risk geographies go unreviewed | C10: Weighted risk scoring reviewed for every High-risk transaction before/after payment | D10: Count payments scored High risk on Risk_Scoring | E10: =Risk_Scoring!$B$760 -> 21 | F10: =IF(E10=0,"PASS","FAIL - Exceptions Found") -> FAIL - Exceptions Found
A11: Procurement – Vendor Onboarding | B11: A newly onboarded vendor receives unusually large orders before it is vetted | C11: New-vendor spend reviewed against onboarding date and peer average | D11: Count vendors flagged on New_Vendor_Risk | E11: =New_Vendor_Risk!$B$47 -> 0 | F11: =IF(E11=0,"PASS","FAIL - Exceptions Found") -> PASS
A14: Overall Audit Status | B14: =IF(COUNTIF($F$5:$F$11,"PASS")=COUNTA($F$5:$F$11),"ALL CONTROLS PASS","REVIEW REQUIRED - One or more controls FAILED") -> REVIEW REQUIRED - One or more controls FAILED

Sheet Report_Monthly
A1: Recurring Report — Monthly
A2: Recurring management report, grouped by period. Built from the reconciliation / AP / AR / risk modules — the VBA macro refreshes and exports this tab.
A4: Period | B4: AP Payments ($) | C4: AR Receipts ($) | D4: 3-Way Match Exceptions | E4: Duplicate Payment Flags | F4: SoD Violations | G4: High-Risk Transactions | H4: New POs Raised
A5: Jan-2025 | B5: =SUMIFS(Payment_Log_AP!$E$2:$E$753,Payment_Log_AP!$D$2:$D$753,">="&DATE(2025,1,1),Payment_Log_AP!$D$2:$D$753,"<"&DATE(2025,2,1)) -> 28576.85 | C5: =SUMIFS(Cash_Receipts_AR!$E$2:$E$503,Cash_Receipts_AR!$D$2:$D$503,">="&DATE(2025,1,1),Cash_Receipts_AR!$D$2:$D$503,"<"&DATE(2025,2,1)) -> 34490.06 | D5: =COUNTIFS(3Way_Match!$L$5:$L$854,"EXCEPTION",3Way_Match!$D$5:$D$854,">="&DATE(2025,1,1),3Way_Match!$D$5:$D$854,"<"&DATE(2025,2,1)) -> 11 | E5: =COUNTIFS(Duplicate_Payments!$H$5:$H$885,"DUPLICATE*") -> 16 | F5: =COUNTIFS(SoD_Check!$G$5:$G$854,"VIOLATION*",SoD_Check!$C$5:$C$854,">="&DATE(2025,1,1),SoD_Check!$C$5:$C$854,"<"&DATE(2025,2,1)) -> 2 | G5: =COUNTIFS(Risk_Scoring!$M$5:$M$756,"High",Risk_Scoring!$F$5:$F$756,">="&DATE(2025,1,1),Risk_Scoring!$F$5:$F$756,"<"&DATE(2025,2,1)) -> 0 | H5: =COUNTIFS(Purchase_Orders!$C$2:$C$851,">="&DATE(2025,1,1),Purchase_Orders!$C$2:$C$851,"<"&DATE(2025,2,1)) -> 46
A6: Feb-2025 | B6: =SUMIFS(Payment_Log_AP!$E$2:$E$753,Payment_Log_AP!$D$2:$D$753,">="&DATE(2025,2,1),Payment_Log_AP!$D$2:$D$753,"<"&DATE(2025,3,1)) -> 119868.99 | C6: =SUMIFS(Cash_Receipts_AR!$E$2:$E$503,Cash_Receipts_AR!$D$2:$D$503,">="&DATE(2025,2,1),Cash_Receipts_AR!$D$2:$D$503,"<"&DATE(2025,3,1)) -> 63240.58 | D6: =COUNTIFS(3Way_Match!$L$5:$L$854,"EXCEPTION",3Way_Match!$D$5:$D$854,">="&DATE(2025,2,1),3Way_Match!$D$5:$D$854,"<"&DATE(2025,3,1)) -> 10 | E6: =COUNTIFS(Duplicate_Payments!$H$5:$H$885,"DUPLICATE*") -> 16 | F6: =COUNTIFS(SoD_Check!$G$5:$G$854,"VIOLATION*",SoD_Check!$C$5:$C$854,">="&DATE(2025,2,1),SoD_Check!$C$5:$C$854,"<"&DATE(2025,3,1)) -> 2 | G6: =COUNTIFS(Risk_Scoring!$M$5:$M$756,"High",Risk_Scoring!$F$5:$F$756,">="&DATE(2025,2,1),Risk_Scoring!$F$5:$F$756,"<"&DATE(2025,3,1)) -> 0 | H6: =COUNTIFS(Purchase_Orders!$C$2:$C$851,">="&DATE(2025,2,1),Purchase_Orders!$C$2:$C$851,"<"&DATE(2025,3,1)) -> 43
A7: Mar-2025 | B7: =SUMIFS(Payment_Log_AP!$E$2:$E$753,Payment_Log_AP!$D$2:$D$753,">="&DATE(2025,3,1),Payment_Log_AP!$D$2:$D$753,"<"&DATE(2025,4,1)) -> 138285.77 | C7: =SUMIFS(Cash_Receipts_AR!$E$2:$E$503,Cash_Receipts_AR!$D$2:$D$503,">="&DATE(2025,3,1),Cash_Receipts_AR!$D$2:$D$503,"<"&DATE(2025,4,1)) -> 149556.12 | D7: =COUNTIFS(3Way_Match!$L$5:$L$854,"EXCEPTION",3Way_Match!$D$5:$D$854,">="&DATE(2025,3,1),3Way_Match!$D$5:$D$854,"<"&DATE(2025,4,1)) -> 9 | E7: =COUNTIFS(Duplicate_Payments!$H$5:$H$885,"DUPLICATE*") -> 16 | F7: =COUNTIFS(SoD_Check!$G$5:$G$854,"VIOLATION*",SoD_Check!$C$5:$C$854,">="&DATE(2025,3,1),SoD_Check!$C$5:$C$854,"<"&DATE(2025,4,1)) -> 2 | G7: =COUNTIFS(Risk_Scoring!$M$5:$M$756,"High",Risk_Scoring!$F$5:$F$756,">="&DATE(2025,3,1),Risk_Scoring!$F$5:$F$756,"<"&DATE(2025,4,1)) -> 4 | H7: =COUNTIFS(Purchase_Orders!$C$2:$C$851,">="&DATE(2025,3,1),Purchase_Orders!$C$2:$C$851,"<"&DATE(2025,4,1)) -> 45
A8: Apr-2025 | B8: =SUMIFS(Payment_Log_AP!$E$2:$E$753,Payment_Log_AP!$D$2:$D$753,">="&DATE(2025,4,1),Payment_Log_AP!$D$2:$D$753,"<"&DATE(2025,5,1)) -> 151944.6 | C8: =SUMIFS(Cash_Receipts_AR!$E$2:$E$503,Cash_Receipts_AR!$D$2:$D$503,">="&DATE(2025,4,1),Cash_Receipts_AR!$D$2:$D$503,"<"&DATE(2025,5,1)) -> 154341.64 | D8: =COUNTIFS(3Way_Match!$L$5:$L$854,"EXCEPTION",3Way_Match!$D$5:$D$854,">="&DATE(2025,4,1),3Way_Match!$D$5:$D$854,"<"&DATE(2025,5,1)) -> 9 | E8: =COUNTIFS(Duplicate_Payments!$H$5:$H$885,"DUPLICATE*") -> 16 | F8: =COUNTIFS(SoD_Check!$G$5:$G$854,"VIOLATION*",SoD_Check!$C$5:$C$854,">="&DATE(2025,4,1),SoD_Check!$C$5:$C$854,"<"&DATE(2025,5,1)) -> 1 | G8: =COUNTIFS(Risk_Scoring!$M$5:$M$756,"High",Risk_Scoring!$F$5:$F$756,">="&DATE(2025,4,1),Risk_Scoring!$F$5:$F$756,"<"&DATE(2025,5,1)) -> 5 | H8: =COUNTIFS(Purchase_Orders!$C$2:$C$851,">="&DATE(2025,4,1),Purchase_Orders!$C$2:$C$851,"<"&DATE(2025,5,1)) -> 43
A9: May-2025 | B9: =SUMIFS(Payment_Log_AP!$E$2:$E$753,Payment_Log_AP!$D$2:$D$753,">="&DATE(2025,5,1),Payment_Log_AP!$D$2:$D$753,"<"&DATE(2025,6,1)) -> 115131.97 | C9: =SUMIFS(Cash_Receipts_AR!$E$2:$E$503,Cash_Receipts_AR!$D$2:$D$503,">="&DATE(2025,5,1),Cash_Receipts_AR!$D$2:$D$503,"<"&DATE(2025,6,1)) -> 44704.87 | D9: =COUNTIFS(3Way_Match!$L$5:$L$854,"EXCEPTION",3Way_Match!$D$5:$D$854,">="&DATE(2025,5,1),3Way_Match!$D$5:$D$854,"<"&DATE(2025,6,1)) -> 11 | E9: =COUNTIFS(Duplicate_Payments!$H$5:$H$885,"DUPLICATE*") -> 16 | F9: =COUNTIFS(SoD_Check!$G$5:$G$854,"VIOLATION*",SoD_Check!$C$5:$C$854,">="&DATE(2025,5,1),SoD_Check!$C$5:$C$854,"<"&DATE(2025,6,1)) -> 0 | G9: =COUNTIFS(Risk_Scoring!$M$5:$M$756,"High",Risk_Scoring!$F$5:$F$756,">="&DATE(2025,5,1),Risk_Scoring!$F$5:$F$756,"<"&DATE(2025,6,1)) -> 1 | H9: =COUNTIFS(Purchase_Orders!$C$2:$C$851,">="&DATE(2025,5,1),Purchase_Orders!$C$2:$C$851,"<"&DATE(2025,6,1)) -> 51
A10: Jun-2025 | B10: =SUMIFS(Payment_Log_AP!$E$2:$E$753,Payment_Log_AP!$D$2:$D$753,">="&DATE(2025,6,1),Payment_Log_AP!$D$2:$D$753,"<"&DATE(2025,7,1)) -> 127916.17 | C10: =SUMIFS(Cash_Receipts_AR!$E$2:$E$503,Cash_Receipts_AR!$D$2:$D$503,">="&DATE(2025,6,1),Cash_Receipts_AR!$D$2:$D$503,"<"&DATE(2025,7,1)) -> 132992.65 | D10: =COUNTIFS(3Way_Match!$L$5:$L$854,"EXCEPTION",3Way_Match!$D$5:$D$854,">="&DATE(2025,6,1),3Way_Match!$D$5:$D$854,"<"&DATE(2025,7,1)) -> 6 | E10: =COUNTIFS(Duplicate_Payments!$H$5:$H$885,"DUPLICATE*") -> 16 | F10: =COUNTIFS(SoD_Check!$G$5:$G$854,"VIOLATION*",SoD_Check!$C$5:$C$854,">="&DATE(2025,6,1),SoD_Check!$C$5:$C$854,"<"&DATE(2025,7,1)) -> 0 | G10: =COUNTIFS(Risk_Scoring!$M$5:$M$756,"High",Risk_Scoring!$F$5:$F$756,">="&DATE(2025,6,1),Risk_Scoring!$F$5:$F$756,"<"&DATE(2025,7,1)) -> 2 | H10: =COUNTIFS(Purchase_Orders!$C$2:$C$851,">="&DATE(2025,6,1),Purchase_Orders!$C$2:$C$851,"<"&DATE(2025,7,1)) -> 46
A11: Jul-2025 | B11: =SUMIFS(Payment_Log_AP!$E$2:$E$753,Payment_Log_AP!$D$2:$D$753,">="&DATE(2025,7,1),Payment_Log_AP!$D$2:$D$753,"<"&DATE(2025,8,1)) -> 153034.98 | C11: =SUMIFS(Cash_Receipts_AR!$E$2:$E$503,Cash_Receipts_AR!$D$2:$D$503,">="&DATE(2025,7,1),Cash_Receipts_AR!$D$2:$D$503,"<"&DATE(2025,8,1)) -> 96608.09 | D11: =COUNTIFS(3Way_Match!$L$5:$L$854,"EXCEPTION",3Way_Match!$D$5:$D$854,">="&DATE(2025,7,1),3Way_Match!$D$5:$D$854,"<"&DATE(2025,8,1)) -> 6 | E11: =COUNTIFS(Duplicate_Payments!$H$5:$H$885,"DUPLICATE*") -> 16 | F11: =COUNTIFS(SoD_Check!$G$5:$G$854,"VIOLATION*",SoD_Check!$C$5:$C$854,">="&DATE(2025,7,1),SoD_Check!$C$5:$C$854,"<"&DATE(2025,8,1)) -> 2 | G11: =COUNTIFS(Risk_Scoring!$M$5:$M$756,"High",Risk_Scoring!$F$5:$F$756,">="&DATE(2025,7,1),Risk_Scoring!$F$5:$F$756,"<"&DATE(2025,8,1)) -> 3 | H11: =COUNTIFS(Purchase_Orders!$C$2:$C$851,">="&DATE(2025,7,1),Purchase_Orders!$C$2:$C$851,"<"&DATE(2025,8,1)) -> 39
A12: Aug-2025 | B12: =SUMIFS(Payment_Log_AP!$E$2:$E$753,Payment_Log_AP!$D$2:$D$753,">="&DATE(2025,8,1),Payment_Log_AP!$D$2:$D$753,"<"&DATE(2025,9,1)) -> 155487.54 | C12: =SUMIFS(Cash_Receipts_AR!$E$2:$E$503,Cash_Receipts_AR!$D$2:$D$503,">="&DATE(2025,8,1),Cash_Receipts_AR!$D$2:$D$503,"<"&DATE(2025,9,1)) -> 137059.13 | D12: =COUNTIFS(3Way_Match!$L$5:$L$854,"EXCEPTION",3Way_Match!$D$5:$D$854,">="&DATE(2025,8,1),3Way_Match!$D$5:$D$854,"<"&DATE(2025,9,1)) -> 10 | E12: =COUNTIFS(Duplicate_Payments!$H$5:$H$885,"DUPLICATE*") -> 16 | F12: =COUNTIFS(SoD_Check!$G$5:$G$854,"VIOLATION*",SoD_Check!$C$5:$C$854,">="&DATE(2025,8,1),SoD_Check!$C$5:$C$854,"<"&DATE(2025,9,1)) -> 1 | G12: =COUNTIFS(Risk_Scoring!$M$5:$M$756,"High",Risk_Scoring!$F$5:$F$756,">="&DATE(2025,8,1),Risk_Scoring!$F$5:$F$756,"<"&DATE(2025,9,1)) -> 0 | H12: =COUNTIFS(Purchase_Orders!$C$2:$C$851,">="&DATE(2025,8,1),Purchase_Orders!$C$2:$C$851,"<"&DATE(2025,9,1)) -> 51
A13: Sep-2025 | B13: =SUMIFS(Payment_Log_AP!$E$2:$E$753,Payment_Log_AP!$D$2:$D$753,">="&DATE(2025,9,1),Payment_Log_AP!$D$2:$D$753,"<"&DATE(2025,10,1)) -> 156557.35 | C13: =SUMIFS(Cash_Receipts_AR!$E$2:$E$503,Cash_Receipts_AR!$D$2:$D$503,">="&DATE(2025,9,1),Cash_Receipts_AR!$D$2:$D$503,"<"&DATE(2025,10,1)) -> 92067.87 | D13: =COUNTIFS(3Way_Match!$L$5:$L$854,"EXCEPTION",3Way_Match!$D$5:$D$854,">="&DATE(2025,9,1),3Way_Match!$D$5:$D$854,"<"&DATE(2025,10,1)) -> 13 | E13: =COUNTIFS(Duplicate_Payments!$H$5:$H$885,"DUPLICATE*") -> 16 | F13: =COUNTIFS(SoD_Check!$G$5:$G$854,"VIOLATION*",SoD_Check!$C$5:$C$854,">="&DATE(2025,9,1),SoD_Check!$C$5:$C$854,"<"&DATE(2025,10,1)) -> 1 | G13: =COUNTIFS(Risk_Scoring!$M$5:$M$756,"High",Risk_Scoring!$F$5:$F$756,">="&DATE(2025,9,1),Risk_Scoring!$F$5:$F$756,"<"&DATE(2025,10,1)) -> 0 | H13: =COUNTIFS(Purchase_Orders!$C$2:$C$851,">="&DATE(2025,9,1),Purchase_Orders!$C$2:$C$851,"<"&DATE(2025,10,1)) -> 51
A14: Oct-2025 | B14: =SUMIFS(Payment_Log_AP!$E$2:$E$753,Payment_Log_AP!$D$2:$D$753,">="&DATE(2025,10,1),Payment_Log_AP!$D$2:$D$753,"<"&DATE(2025,11,1)) -> 180558.89 | C14: =SUMIFS(Cash_Receipts_AR!$E$2:$E$503,Cash_Receipts_AR!$D$2:$D$503,">="&DATE(2025,10,1),Cash_Receipts_AR!$D$2:$D$503,"<"&DATE(2025,11,1)) -> 111747.18 | D14: =COUNTIFS(3Way_Match!$L$5:$L$854,"EXCEPTION",3Way_Match!$D$5:$D$854,">="&DATE(2025,10,1),3Way_Match!$D$5:$D$854,"<"&DATE(2025,11,1)) -> 6 | E14: =COUNTIFS(Duplicate_Payments!$H$5:$H$885,"DUPLICATE*") -> 16 | F14: =COUNTIFS(SoD_Check!$G$5:$G$854,"VIOLATION*",SoD_Check!$C$5:$C$854,">="&DATE(2025,10,1),SoD_Check!$C$5:$C$854,"<"&DATE(2025,11,1)) -> 2 | G14: =COUNTIFS(Risk_Scoring!$M$5:$M$756,"High",Risk_Scoring!$F$5:$F$756,">="&DATE(2025,10,1),Risk_Scoring!$F$5:$F$756,"<"&DATE(2025,11,1)) -> 1 | H14: =COUNTIFS(Purchase_Orders!$C$2:$C$851,">="&DATE(2025,10,1),Purchase_Orders!$C$2:$C$851,"<"&DATE(2025,11,1)) -> 49
A15: Nov-2025 | B15: =SUMIFS(Payment_Log_AP!$E$2:$E$753,Payment_Log_AP!$D$2:$D$753,">="&DATE(2025,11,1),Payment_Log_AP!$D$2:$D$753,"<"&DATE(2025,12,1)) -> 124879.11 | C15: =SUMIFS(Cash_Receipts_AR!$E$2:$E$503,Cash_Receipts_AR!$D$2:$D$503,">="&DATE(2025,11,1),Cash_Receipts_AR!$D$2:$D$503,"<"&DATE(2025,12,1)) -> 103697.61 | D15: =COUNTIFS(3Way_Match!$L$5:$L$854,"EXCEPTION",3Way_Match!$D$5:$D$854,">="&DATE(2025,11,1),3Way_Match!$D$5:$D$854,"<"&DATE(2025,12,1)) -> 7 | E15: =COUNTIFS(Duplicate_Payments!$H$5:$H$885,"DUPLICATE*") -> 16 | F15: =COUNTIFS(SoD_Check!$G$5:$G$854,"VIOLATION*",SoD_Check!$C$5:$C$854,">="&DATE(2025,11,1),SoD_Check!$C$5:$C$854,"<"&DATE(2025,12,1)) -> 3 | G15: =COUNTIFS(Risk_Scoring!$M$5:$M$756,"High",Risk_Scoring!$F$5:$F$756,">="&DATE(2025,11,1),Risk_Scoring!$F$5:$F$756,"<"&DATE(2025,12,1)) -> 0 | H15: =COUNTIFS(Purchase_Orders!$C$2:$C$851,">="&DATE(2025,11,1),Purchase_Orders!$C$2:$C$851,"<"&DATE(2025,12,1)) -> 49
A16: Dec-2025 | B16: =SUMIFS(Payment_Log_AP!$E$2:$E$753,Payment_Log_AP!$D$2:$D$753,">="&DATE(2025,12,1),Payment_Log_AP!$D$2:$D$753,"<"&DATE(2026,1,1)) -> 128841.83 | C16: =SUMIFS(Cash_Receipts_AR!$E$2:$E$503,Cash_Receipts_AR!$D$2:$D$503,">="&DATE(2025,12,1),Cash_Receipts_AR!$D$2:$D$503,"<"&DATE(2026,1,1)) -> 108692.29 | D16: =COUNTIFS(3Way_Match!$L$5:$L$854,"EXCEPTION",3Way_Match!$D$5:$D$854,">="&DATE(2025,12,1),3Way_Match!$D$5:$D$854,"<"&DATE(2026,1,1)) -> 9 | E16: =COUNTIFS(Duplicate_Payments!$H$5:$H$885,"DUPLICATE*") -> 16 | F16: =COUNTIFS(SoD_Check!$G$5:$G$854,"VIOLATION*",SoD_Check!$C$5:$C$854,">="&DATE(2025,12,1),SoD_Check!$C$5:$C$854,"<"&DATE(2026,1,1)) -> 2 | G16: =COUNTIFS(Risk_Scoring!$M$5:$M$756,"High",Risk_Scoring!$F$5:$F$756,">="&DATE(2025,12,1),Risk_Scoring!$F$5:$F$756,"<"&DATE(2026,1,1)) -> 0 | H16: =COUNTIFS(Purchase_Orders!$C$2:$C$851,">="&DATE(2025,12,1),Purchase_Orders!$C$2:$C$851,"<"&DATE(2026,1,1)) -> 55
A17: Jan-2026 | B17: =SUMIFS(Payment_Log_AP!$E$2:$E$753,Payment_Log_AP!$D$2:$D$753,">="&DATE(2026,1,1),Payment_Log_AP!$D$2:$D$753,"<"&DATE(2026,2,1)) -> 114036.6 | C17: =SUMIFS(Cash_Receipts_AR!$E$2:$E$503,Cash_Receipts_AR!$D$2:$D$503,">="&DATE(2026,1,1),Cash_Receipts_AR!$D$2:$D$503,"<"&DATE(2026,2,1)) -> 154059.34 | D17: =COUNTIFS(3Way_Match!$L$5:$L$854,"EXCEPTION",3Way_Match!$D$5:$D$854,">="&DATE(2026,1,1),3Way_Match!$D$5:$D$854,"<"&DATE(2026,2,1)) -> 13 | E17: =COUNTIFS(Duplicate_Payments!$H$5:$H$885,"DUPLICATE*") -> 16 | F17: =COUNTIFS(SoD_Check!$G$5:$G$854,"VIOLATION*",SoD_Check!$C$5:$C$854,">="&DATE(2026,1,1),SoD_Check!$C$5:$C$854,"<"&DATE(2026,2,1)) -> 0 | G17: =COUNTIFS(Risk_Scoring!$M$5:$M$756,"High",Risk_Scoring!$F$5:$F$756,">="&DATE(2026,1,1),Risk_Scoring!$F$5:$F$756,"<"&DATE(2026,2,1)) -> 0 | H17: =COUNTIFS(Purchase_Orders!$C$2:$C$851,">="&DATE(2026,1,1),Purchase_Orders!$C$2:$C$851,"<"&DATE(2026,2,1)) -> 58
A18: Feb-2026 | B18: =SUMIFS(Payment_Log_AP!$E$2:$E$753,Payment_Log_AP!$D$2:$D$753,">="&DATE(2026,2,1),Payment_Log_AP!$D$2:$D$753,"<"&DATE(2026,3,1)) -> 214951.16 | C18: =SUMIFS(Cash_Receipts_AR!$E$2:$E$503,Cash_Receipts_AR!$D$2:$D$503,">="&DATE(2026,2,1),Cash_Receipts_AR!$D$2:$D$503,"<"&DATE(2026,3,1)) -> 86519.12 | D18: =COUNTIFS(3Way_Match!$L$5:$L$854,"EXCEPTION",3Way_Match!$D$5:$D$854,">="&DATE(2026,2,1),3Way_Match!$D$5:$D$854,"<"&DATE(2026,3,1)) -> 10 | E18: =COUNTIFS(Duplicate_Payments!$H$5:$H$885,"DUPLICATE*") -> 16 | F18: =COUNTIFS(SoD_Check!$G$5:$G$854,"VIOLATION*",SoD_Check!$C$5:$C$854,">="&DATE(2026,2,1),SoD_Check!$C$5:$C$854,"<"&DATE(2026,3,1)) -> 2 | G18: =COUNTIFS(Risk_Scoring!$M$5:$M$756,"High",Risk_Scoring!$F$5:$F$756,">="&DATE(2026,2,1),Risk_Scoring!$F$5:$F$756,"<"&DATE(2026,3,1)) -> 3 | H18: =COUNTIFS(Purchase_Orders!$C$2:$C$851,">="&DATE(2026,2,1),Purchase_Orders!$C$2:$C$851,"<"&DATE(2026,3,1)) -> 48
A19: Mar-2026 | B19: =SUMIFS(Payment_Log_AP!$E$2:$E$753,Payment_Log_AP!$D$2:$D$753,">="&DATE(2026,3,1),Payment_Log_AP!$D$2:$D$753,"<"&DATE(2026,4,1)) -> 175339.43 | C19: =SUMIFS(Cash_Receipts_AR!$E$2:$E$503,Cash_Receipts_AR!$D$2:$D$503,">="&DATE(2026,3,1),Cash_Receipts_AR!$D$2:$D$503,"<"&DATE(2026,4,1)) -> 103135.14 | D19: =COUNTIFS(3Way_Match!$L$5:$L$854,"EXCEPTION",3Way_Match!$D$5:$D$854,">="&DATE(2026,3,1),3Way_Match!$D$5:$D$854,"<"&DATE(2026,4,1)) -> 8 | E19: =COUNTIFS(Duplicate_Payments!$H$5:$H$885,"DUPLICATE*") -> 16 | F19: =COUNTIFS(SoD_Check!$G$5:$G$854,"VIOLATION*",SoD_Check!$C$5:$C$854,">="&DATE(2026,3,1),SoD_Check!$C$5:$C$854,"<"&DATE(2026,4,1)) -> 0 | G19: =COUNTIFS(Risk_Scoring!$M$5:$M$756,"High",Risk_Scoring!$F$5:$F$756,">="&DATE(2026,3,1),Risk_Scoring!$F$5:$F$756,"<"&DATE(2026,4,1)) -> 0 | H19: =COUNTIFS(Purchase_Orders!$C$2:$C$851,">="&DATE(2026,3,1),Purchase_Orders!$C$2:$C$851,"<"&DATE(2026,4,1)) -> 48
A20: Apr-2026 | B20: =SUMIFS(Payment_Log_AP!$E$2:$E$753,Payment_Log_AP!$D$2:$D$753,">="&DATE(2026,4,1),Payment_Log_AP!$D$2:$D$753,"<"&DATE(2026,5,1)) -> 169620.51 | C20: =SUMIFS(Cash_Receipts_AR!$E$2:$E$503,Cash_Receipts_AR!$D$2:$D$503,">="&DATE(2026,4,1),Cash_Receipts_AR!$D$2:$D$503,"<"&DATE(2026,5,1)) -> 115139.1 | D20: =COUNTIFS(3Way_Match!$L$5:$L$854,"EXCEPTION",3Way_Match!$D$5:$D$854,">="&DATE(2026,4,1),3Way_Match!$D$5:$D$854,"<"&DATE(2026,5,1)) -> 9 | E20: =COUNTIFS(Duplicate_Payments!$H$5:$H$885,"DUPLICATE*") -> 16 | F20: =COUNTIFS(SoD_Check!$G$5:$G$854,"VIOLATION*",SoD_Check!$C$5:$C$854,">="&DATE(2026,4,1),SoD_Check!$C$5:$C$854,"<"&DATE(2026,5,1)) -> 0 | G20: =COUNTIFS(Risk_Scoring!$M$5:$M$756,"High",Risk_Scoring!$F$5:$F$756,">="&DATE(2026,4,1),Risk_Scoring!$F$5:$F$756,"<"&DATE(2026,5,1)) -> 0 | H20: =COUNTIFS(Purchase_Orders!$C$2:$C$851,">="&DATE(2026,4,1),Purchase_Orders!$C$2:$C$851,"<"&DATE(2026,5,1)) -> 44
A21: May-2026 | B21: =SUMIFS(Payment_Log_AP!$E$2:$E$753,Payment_Log_AP!$D$2:$D$753,">="&DATE(2026,5,1),Payment_Log_AP!$D$2:$D$753,"<"&DATE(2026,6,1)) -> 129491.66 | C21: =SUMIFS(Cash_Receipts_AR!$E$2:$E$503,Cash_Receipts_AR!$D$2:$D$503,">="&DATE(2026,5,1),Cash_Receipts_AR!$D$2:$D$503,"<"&DATE(2026,6,1)) -> 91241.32 | D21: =COUNTIFS(3Way_Match!$L$5:$L$854,"EXCEPTION",3Way_Match!$D$5:$D$854,">="&DATE(2026,5,1),3Way_Match!$D$5:$D$854,"<"&DATE(2026,6,1)) -> 7 | E21: =COUNTIFS(Duplicate_Payments!$H$5:$H$885,"DUPLICATE*") -> 16 | F21: =COUNTIFS(SoD_Check!$G$5:$G$854,"VIOLATION*",SoD_Check!$C$5:$C$854,">="&DATE(2026,5,1),SoD_Check!$C$5:$C$854,"<"&DATE(2026,6,1)) -> 1 | G21: =COUNTIFS(Risk_Scoring!$M$5:$M$756,"High",Risk_Scoring!$F$5:$F$756,">="&DATE(2026,5,1),Risk_Scoring!$F$5:$F$756,"<"&DATE(2026,6,1)) -> 0 | H21: =COUNTIFS(Purchase_Orders!$C$2:$C$851,">="&DATE(2026,5,1),Purchase_Orders!$C$2:$C$851,"<"&DATE(2026,6,1)) -> 37
A22: Jun-2026 | B22: =SUMIFS(Payment_Log_AP!$E$2:$E$753,Payment_Log_AP!$D$2:$D$753,">="&DATE(2026,6,1),Payment_Log_AP!$D$2:$D$753,"<"&DATE(2026,7,1)) -> 143562.16 | C22: =SUMIFS(Cash_Receipts_AR!$E$2:$E$503,Cash_Receipts_AR!$D$2:$D$503,">="&DATE(2026,6,1),Cash_Receipts_AR!$D$2:$D$503,"<"&DATE(2026,7,1)) -> 110355.33 | D22: =COUNTIFS(3Way_Match!$L$5:$L$854,"EXCEPTION",3Way_Match!$D$5:$D$854,">="&DATE(2026,6,1),3Way_Match!$D$5:$D$854,"<"&DATE(2026,7,1)) -> 6 | E22: =COUNTIFS(Duplicate_Payments!$H$5:$H$885,"DUPLICATE*") -> 16 | F22: =COUNTIFS(SoD_Check!$G$5:$G$854,"VIOLATION*",SoD_Check!$C$5:$C$854,">="&DATE(2026,6,1),SoD_Check!$C$5:$C$854,"<"&DATE(2026,7,1)) -> 0 | G22: =COUNTIFS(Risk_Scoring!$M$5:$M$756,"High",Risk_Scoring!$F$5:$F$756,">="&DATE(2026,6,1),Risk_Scoring!$F$5:$F$756,"<"&DATE(2026,7,1)) -> 2 | H22: =COUNTIFS(Purchase_Orders!$C$2:$C$851,">="&DATE(2026,6,1),Purchase_Orders!$C$2:$C$851,"<"&DATE(2026,7,1)) -> 47
A23: Jul-2026 | B23: =SUMIFS(Payment_Log_AP!$E$2:$E$753,Payment_Log_AP!$D$2:$D$753,">="&DATE(2026,7,1),Payment_Log_AP!$D$2:$D$753,"<"&DATE(2026,8,1)) -> 13225.35 | C23: =SUMIFS(Cash_Receipts_AR!$E$2:$E$503,Cash_Receipts_AR!$D$2:$D$503,">="&DATE(2026,7,1),Cash_Receipts_AR!$D$2:$D$503,"<"&DATE(2026,8,1)) -> 0 | D23: =COUNTIFS(3Way_Match!$L$5:$L$854,"EXCEPTION",3Way_Match!$D$5:$D$854,">="&DATE(2026,7,1),3Way_Match!$D$5:$D$854,"<"&DATE(2026,8,1)) -> 0 | E23: =COUNTIFS(Duplicate_Payments!$H$5:$H$885,"DUPLICATE*") -> 16 | F23: =COUNTIFS(SoD_Check!$G$5:$G$854,"VIOLATION*",SoD_Check!$C$5:$C$854,">="&DATE(2026,7,1),SoD_Check!$C$5:$C$854,"<"&DATE(2026,8,1)) -> 0 | G23: =COUNTIFS(Risk_Scoring!$M$5:$M$756,"High",Risk_Scoring!$F$5:$F$756,">="&DATE(2026,7,1),Risk_Scoring!$F$5:$F$756,"<"&DATE(2026,8,1)) -> 0 | H23: =COUNTIFS(Purchase_Orders!$C$2:$C$851,">="&DATE(2026,7,1),Purchase_Orders!$C$2:$C$851,"<"&DATE(2026,8,1)) -> 0
A25: Note: Duplicate Payment Flags is a running total (not period-bound) since a duplicate is identified by invoice, not by date.

Sheet Report_Quarterly
A1: Recurring Report — Quarterly
A2: Recurring management report, grouped by period. Built from the reconciliation / AP / AR / risk modules — the VBA macro refreshes and exports this tab.
A4: Period | B4: AP Payments ($) | C4: AR Receipts ($) | D4: 3-Way Match Exceptions | E4: Duplicate Payment Flags | F4: SoD Violations | G4: High-Risk Transactions | H4: New POs Raised
A5: Q1-2025 | B5: =SUMIFS(Payment_Log_AP!$E$2:$E$753,Payment_Log_AP!$D$2:$D$753,">="&DATE(2025,1,1),Payment_Log_AP!$D$2:$D$753,"<"&DATE(2025,4,1)) -> 286731.61 | C5: =SUMIFS(Cash_Receipts_AR!$E$2:$E$503,Cash_Receipts_AR!$D$2:$D$503,">="&DATE(2025,1,1),Cash_Receipts_AR!$D$2:$D$503,"<"&DATE(2025,4,1)) -> 247286.76 | D5: =COUNTIFS(3Way_Match!$L$5:$L$854,"EXCEPTION",3Way_Match!$D$5:$D$854,">="&DATE(2025,1,1),3Way_Match!$D$5:$D$854,"<"&DATE(2025,4,1)) -> 30 | E5: =COUNTIFS(Duplicate_Payments!$H$5:$H$885,"DUPLICATE*") -> 16 | F5: =COUNTIFS(SoD_Check!$G$5:$G$854,"VIOLATION*",SoD_Check!$C$5:$C$854,">="&DATE(2025,1,1),SoD_Check!$C$5:$C$854,"<"&DATE(2025,4,1)) -> 6 | G5: =COUNTIFS(Risk_Scoring!$M$5:$M$756,"High",Risk_Scoring!$F$5:$F$756,">="&DATE(2025,1,1),Risk_Scoring!$F$5:$F$756,"<"&DATE(2025,4,1)) -> 4 | H5: =COUNTIFS(Purchase_Orders!$C$2:$C$851,">="&DATE(2025,1,1),Purchase_Orders!$C$2:$C$851,"<"&DATE(2025,4,1)) -> 134
A6: Q2-2025 | B6: =SUMIFS(Payment_Log_AP!$E$2:$E$753,Payment_Log_AP!$D$2:$D$753,">="&DATE(2025,4,1),Payment_Log_AP!$D$2:$D$753,"<"&DATE(2025,7,1)) -> 394992.74 | C6: =SUMIFS(Cash_Receipts_AR!$E$2:$E$503,Cash_Receipts_AR!$D$2:$D$503,">="&DATE(2025,4,1),Cash_Receipts_AR!$D$2:$D$503,"<"&DATE(2025,7,1)) -> 332039.16 | D6: =COUNTIFS(3Way_Match!$L$5:$L$854,"EXCEPTION",3Way_Match!$D$5:$D$854,">="&DATE(2025,4,1),3Way_Match!$D$5:$D$854,"<"&DATE(2025,7,1)) -> 26 | E6: =COUNTIFS(Duplicate_Payments!$H$5:$H$885,"DUPLICATE*") -> 16 | F6: =COUNTIFS(SoD_Check!$G$5:$G$854,"VIOLATION*",SoD_Check!$C$5:$C$854,">="&DATE(2025,4,1),SoD_Check!$C$5:$C$854,"<"&DATE(2025,7,1)) -> 1 | G6: =COUNTIFS(Risk_Scoring!$M$5:$M$756,"High",Risk_Scoring!$F$5:$F$756,">="&DATE(2025,4,1),Risk_Scoring!$F$5:$F$756,"<"&DATE(2025,7,1)) -> 8 | H6: =COUNTIFS(Purchase_Orders!$C$2:$C$851,">="&DATE(2025,4,1),Purchase_Orders!$C$2:$C$851,"<"&DATE(2025,7,1)) -> 140
A7: Q3-2025 | B7: =SUMIFS(Payment_Log_AP!$E$2:$E$753,Payment_Log_AP!$D$2:$D$753,">="&DATE(2025,7,1),Payment_Log_AP!$D$2:$D$753,"<"&DATE(2025,10,1)) -> 465079.87 | C7: =SUMIFS(Cash_Receipts_AR!$E$2:$E$503,Cash_Receipts_AR!$D$2:$D$503,">="&DATE(2025,7,1),Cash_Receipts_AR!$D$2:$D$503,"<"&DATE(2025,10,1)) -> 325735.09 | D7: =COUNTIFS(3Way_Match!$L$5:$L$854,"EXCEPTION",3Way_Match!$D$5:$D$854,">="&DATE(2025,7,1),3Way_Match!$D$5:$D$854,"<"&DATE(2025,10,1)) -> 29 | E7: =COUNTIFS(Duplicate_Payments!$H$5:$H$885,"DUPLICATE*") -> 16 | F7: =COUNTIFS(SoD_Check!$G$5:$G$854,"VIOLATION*",SoD_Check!$C$5:$C$854,">="&DATE(2025,7,1),SoD_Check!$C$5:$C$854,"<"&DATE(2025,10,1)) -> 4 | G7: =COUNTIFS(Risk_Scoring!$M$5:$M$756,"High",Risk_Scoring!$F$5:$F$756,">="&DATE(2025,7,1),Risk_Scoring!$F$5:$F$756,"<"&DATE(2025,10,1)) -> 3 | H7: =COUNTIFS(Purchase_Orders!$C$2:$C$851,">="&DATE(2025,7,1),Purchase_Orders!$C$2:$C$851,"<"&DATE(2025,10,1)) -> 141
A8: Q4-2025 | B8: =SUMIFS(Payment_Log_AP!$E$2:$E$753,Payment_Log_AP!$D$2:$D$753,">="&DATE(2025,10,1),Payment_Log_AP!$D$2:$D$753,"<"&DATE(2026,1,1)) -> 434279.83 | C8: =SUMIFS(Cash_Receipts_AR!$E$2:$E$503,Cash_Receipts_AR!$D$2:$D$503,">="&DATE(2025,10,1),Cash_Receipts_AR!$D$2:$D$503,"<"&DATE(2026,1,1)) -> 324137.08 | D8: =COUNTIFS(3Way_Match!$L$5:$L$854,"EXCEPTION",3Way_Match!$D$5:$D$854,">="&DATE(2025,10,1),3Way_Match!$D$5:$D$854,"<"&DATE(2026,1,1)) -> 22 | E8: =COUNTIFS(Duplicate_Payments!$H$5:$H$885,"DUPLICATE*") -> 16 | F8: =COUNTIFS(SoD_Check!$G$5:$G$854,"VIOLATION*",SoD_Check!$C$5:$C$854,">="&DATE(2025,10,1),SoD_Check!$C$5:$C$854,"<"&DATE(2026,1,1)) -> 7 | G8: =COUNTIFS(Risk_Scoring!$M$5:$M$756,"High",Risk_Scoring!$F$5:$F$756,">="&DATE(2025,10,1),Risk_Scoring!$F$5:$F$756,"<"&DATE(2026,1,1)) -> 1 | H8: =COUNTIFS(Purchase_Orders!$C$2:$C$851,">="&DATE(2025,10,1),Purchase_Orders!$C$2:$C$851,"<"&DATE(2026,1,1)) -> 153
A9: Q1-2026 | B9: =SUMIFS(Payment_Log_AP!$E$2:$E$753,Payment_Log_AP!$D$2:$D$753,">="&DATE(2026,1,1),Payment_Log_AP!$D$2:$D$753,"<"&DATE(2026,4,1)) -> 504327.19 | C9: =SUMIFS(Cash_Receipts_AR!$E$2:$E$503,Cash_Receipts_AR!$D$2:$D$503,">="&DATE(2026,1,1),Cash_Receipts_AR!$D$2:$D$503,"<"&DATE(2026,4,1)) -> 343713.6 | D9: =COUNTIFS(3Way_Match!$L$5:$L$854,"EXCEPTION",3Way_Match!$D$5:$D$854,">="&DATE(2026,1,1),3Way_Match!$D$5:$D$854,"<"&DATE(2026,4,1)) -> 31 | E9: =COUNTIFS(Duplicate_Payments!$H$5:$H$885,"DUPLICATE*") -> 16 | F9: =COUNTIFS(SoD_Check!$G$5:$G$854,"VIOLATION*",SoD_Check!$C$5:$C$854,">="&DATE(2026,1,1),SoD_Check!$C$5:$C$854,"<"&DATE(2026,4,1)) -> 2 | G9: =COUNTIFS(Risk_Scoring!$M$5:$M$756,"High",Risk_Scoring!$F$5:$F$756,">="&DATE(2026,1,1),Risk_Scoring!$F$5:$F$756,"<"&DATE(2026,4,1)) -> 3 | H9: =COUNTIFS(Purchase_Orders!$C$2:$C$851,">="&DATE(2026,1,1),Purchase_Orders!$C$2:$C$851,"<"&DATE(2026,4,1)) -> 154
A10: Q2-2026 | B10: =SUMIFS(Payment_Log_AP!$E$2:$E$753,Payment_Log_AP!$D$2:$D$753,">="&DATE(2026,4,1),Payment_Log_AP!$D$2:$D$753,"<"&DATE(2026,7,1)) -> 442674.33 | C10: =SUMIFS(Cash_Receipts_AR!$E$2:$E$503,Cash_Receipts_AR!$D$2:$D$503,">="&DATE(2026,4,1),Cash_Receipts_AR!$D$2:$D$503,"<"&DATE(2026,7,1)) -> 316735.75 | D10: =COUNTIFS(3Way_Match!$L$5:$L$854,"EXCEPTION",3Way_Match!$D$5:$D$854,">="&DATE(2026,4,1),3Way_Match!$D$5:$D$854,"<"&DATE(2026,7,1)) -> 22 | E10: =COUNTIFS(Duplicate_Payments!$H$5:$H$885,"DUPLICATE*") -> 16 | F10: =COUNTIFS(SoD_Check!$G$5:$G$854,"VIOLATION*",SoD_Check!$C$5:$C$854,">="&DATE(2026,4,1),SoD_Check!$C$5:$C$854,"<"&DATE(2026,7,1)) -> 1 | G10: =COUNTIFS(Risk_Scoring!$M$5:$M$756,"High",Risk_Scoring!$F$5:$F$756,">="&DATE(2026,4,1),Risk_Scoring!$F$5:$F$756,"<"&DATE(2026,7,1)) -> 2 | H10: =COUNTIFS(Purchase_Orders!$C$2:$C$851,">="&DATE(2026,4,1),Purchase_Orders!$C$2:$C$851,"<"&DATE(2026,7,1)) -> 128
A11: Q3-2026 | B11: =SUMIFS(Payment_Log_AP!$E$2:$E$753,Payment_Log_AP!$D$2:$D$753,">="&DATE(2026,7,1),Payment_Log_AP!$D$2:$D$753,"<"&DATE(2026,10,1)) -> 13225.35 | C11: =SUMIFS(Cash_Receipts_AR!$E$2:$E$503,Cash_Receipts_AR!$D$2:$D$503,">="&DATE(2026,7,1),Cash_Receipts_AR!$D$2:$D$503,"<"&DATE(2026,10,1)) -> 0 | D11: =COUNTIFS(3Way_Match!$L$5:$L$854,"EXCEPTION",3Way_Match!$D$5:$D$854,">="&DATE(2026,7,1),3Way_Match!$D$5:$D$854,"<"&DATE(2026,10,1)) -> 0 | E11: =COUNTIFS(Duplicate_Payments!$H$5:$H$885,"DUPLICATE*") -> 16 | F11: =COUNTIFS(SoD_Check!$G$5:$G$854,"VIOLATION*",SoD_Check!$C$5:$C$854,">="&DATE(2026,7,1),SoD_Check!$C$5:$C$854,"<"&DATE(2026,10,1)) -> 0 | G11: =COUNTIFS(Risk_Scoring!$M$5:$M$756,"High",Risk_Scoring!$F$5:$F$756,">="&DATE(2026,7,1),Risk_Scoring!$F$5:$F$756,"<"&DATE(2026,10,1)) -> 0 | H11: =COUNTIFS(Purchase_Orders!$C$2:$C$851,">="&DATE(2026,7,1),Purchase_Orders!$C$2:$C$851,"<"&DATE(2026,10,1)) -> 0
A13: Note: Duplicate Payment Flags is a running total (not period-bound) since a duplicate is identified by invoice, not by date.

Sheet Report_Yearly
A1: Recurring Report — Yearly
A2: Recurring management report, grouped by period. Built from the reconciliation / AP / AR / risk modules — the VBA macro refreshes and exports this tab.
A4: Period | B4: AP Payments ($) | C4: AR Receipts ($) | D4: 3-Way Match Exceptions | E4: Duplicate Payment Flags | F4: SoD Violations | G4: High-Risk Transactions | H4: New POs Raised
A5: FY2025 | B5: =SUMIFS(Payment_Log_AP!$E$2:$E$753,Payment_Log_AP!$D$2:$D$753,">="&DATE(2025,1,1),Payment_Log_AP!$D$2:$D$753,"<"&DATE(2026,1,1)) -> 1581084.1 | C5: =SUMIFS(Cash_Receipts_AR!$E$2:$E$503,Cash_Receipts_AR!$D$2:$D$503,">="&DATE(2025,1,1),Cash_Receipts_AR!$D$2:$D$503,"<"&DATE(2026,1,1)) -> 1229198.1 | D5: =COUNTIFS(3Way_Match!$L$5:$L$854,"EXCEPTION",3Way_Match!$D$5:$D$854,">="&DATE(2025,1,1),3Way_Match!$D$5:$D$854,"<"&DATE(2026,1,1)) -> 107 | E5: =COUNTIFS(Duplicate_Payments!$H$5:$H$885,"DUPLICATE*") -> 16 | F5: =COUNTIFS(SoD_Check!$G$5:$G$854,"VIOLATION*",SoD_Check!$C$5:$C$854,">="&DATE(2025,1,1),SoD_Check!$C$5:$C$854,"<"&DATE(2026,1,1)) -> 18 | G5: =COUNTIFS(Risk_Scoring!$M$5:$M$756,"High",Risk_Scoring!$F$5:$F$756,">="&DATE(2025,1,1),Risk_Scoring!$F$5:$F$756,"<"&DATE(2026,1,1)) -> 16 | H5: =COUNTIFS(Purchase_Orders!$C$2:$C$851,">="&DATE(2025,1,1),Purchase_Orders!$C$2:$C$851,"<"&DATE(2026,1,1)) -> 568
A6: FY2026 (partial, through data end) | B6: =SUMIFS(Payment_Log_AP!$E$2:$E$753,Payment_Log_AP!$D$2:$D$753,">="&DATE(2026,1,1),Payment_Log_AP!$D$2:$D$753,"<"&DATE(2027,1,1)) -> 960226.87 | C6: =SUMIFS(Cash_Receipts_AR!$E$2:$E$503,Cash_Receipts_AR!$D$2:$D$503,">="&DATE(2026,1,1),Cash_Receipts_AR!$D$2:$D$503,"<"&DATE(2027,1,1)) -> 660449.35 | D6: =COUNTIFS(3Way_Match!$L$5:$L$854,"EXCEPTION",3Way_Match!$D$5:$D$854,">="&DATE(2026,1,1),3Way_Match!$D$5:$D$854,"<"&DATE(2027,1,1)) -> 53 | E6: =COUNTIFS(Duplicate_Payments!$H$5:$H$885,"DUPLICATE*") -> 16 | F6: =COUNTIFS(SoD_Check!$G$5:$G$854,"VIOLATION*",SoD_Check!$C$5:$C$854,">="&DATE(2026,1,1),SoD_Check!$C$5:$C$854,"<"&DATE(2027,1,1)) -> 3 | G6: =COUNTIFS(Risk_Scoring!$M$5:$M$756,"High",Risk_Scoring!$F$5:$F$756,">="&DATE(2026,1,1),Risk_Scoring!$F$5:$F$756,"<"&DATE(2027,1,1)) -> 5 | H6: =COUNTIFS(Purchase_Orders!$C$2:$C$851,">="&DATE(2026,1,1),Purchase_Orders!$C$2:$C$851,"<"&DATE(2027,1,1)) -> 282
A8: Note: Duplicate Payment Flags is a running total (not period-bound) since a duplicate is identified by invoice, not by date.

Sheet Report_Weekly
A1: Recurring Report — Weekly (most recent 12 weeks; pattern extends the same way for any week)
A2: Recurring management report, grouped by period. Built from the reconciliation / AP / AR / risk modules — the VBA macro refreshes and exports this tab.
A4: Period | B4: AP Payments ($) | C4: AR Receipts ($) | D4: 3-Way Match Exceptions | E4: Duplicate Payment Flags | F4: SoD Violations | G4: High-Risk Transactions | H4: New POs Raised
A5: Wk of 13-Apr-2026 | B5: =SUMIFS(Payment_Log_AP!$E$2:$E$753,Payment_Log_AP!$D$2:$D$753,">="&DATE(2026,4,13),Payment_Log_AP!$D$2:$D$753,"<"&DATE(2026,4,20)) -> 17210.23 | C5: =SUMIFS(Cash_Receipts_AR!$E$2:$E$503,Cash_Receipts_AR!$D$2:$D$503,">="&DATE(2026,4,13),Cash_Receipts_AR!$D$2:$D$503,"<"&DATE(2026,4,20)) -> 30576.59 | D5: =COUNTIFS(3Way_Match!$L$5:$L$854,"EXCEPTION",3Way_Match!$D$5:$D$854,">="&DATE(2026,4,13),3Way_Match!$D$5:$D$854,"<"&DATE(2026,4,20)) -> 1 | E5: =COUNTIFS(Duplicate_Payments!$H$5:$H$885,"DUPLICATE*") -> 16 | F5: =COUNTIFS(SoD_Check!$G$5:$G$854,"VIOLATION*",SoD_Check!$C$5:$C$854,">="&DATE(2026,4,13),SoD_Check!$C$5:$C$854,"<"&DATE(2026,4,20)) -> 0 | G5: =COUNTIFS(Risk_Scoring!$M$5:$M$756,"High",Risk_Scoring!$F$5:$F$756,">="&DATE(2026,4,13),Risk_Scoring!$F$5:$F$756,"<"&DATE(2026,4,20)) -> 0 | H5: =COUNTIFS(Purchase_Orders!$C$2:$C$851,">="&DATE(2026,4,13),Purchase_Orders!$C$2:$C$851,"<"&DATE(2026,4,20)) -> 14
A6: Wk of 20-Apr-2026 | B6: =SUMIFS(Payment_Log_AP!$E$2:$E$753,Payment_Log_AP!$D$2:$D$753,">="&DATE(2026,4,20),Payment_Log_AP!$D$2:$D$753,"<"&DATE(2026,4,27)) -> 31624.9 | C6: =SUMIFS(Cash_Receipts_AR!$E$2:$E$503,Cash_Receipts_AR!$D$2:$D$503,">="&DATE(2026,4,20),Cash_Receipts_AR!$D$2:$D$503,"<"&DATE(2026,4,27)) -> 8759.06 | D6: =COUNTIFS(3Way_Match!$L$5:$L$854,"EXCEPTION",3Way_Match!$D$5:$D$854,">="&DATE(2026,4,20),3Way_Match!$D$5:$D$854,"<"&DATE(2026,4,27)) -> 3 | E6: =COUNTIFS(Duplicate_Payments!$H$5:$H$885,"DUPLICATE*") -> 16 | F6: =COUNTIFS(SoD_Check!$G$5:$G$854,"VIOLATION*",SoD_Check!$C$5:$C$854,">="&DATE(2026,4,20),SoD_Check!$C$5:$C$854,"<"&DATE(2026,4,27)) -> 0 | G6: =COUNTIFS(Risk_Scoring!$M$5:$M$756,"High",Risk_Scoring!$F$5:$F$756,">="&DATE(2026,4,20),Risk_Scoring!$F$5:$F$756,"<"&DATE(2026,4,27)) -> 0 | H6: =COUNTIFS(Purchase_Orders!$C$2:$C$851,">="&DATE(2026,4,20),Purchase_Orders!$C$2:$C$851,"<"&DATE(2026,4,27)) -> 9
A7: Wk of 27-Apr-2026 | B7: =SUMIFS(Payment_Log_AP!$E$2:$E$753,Payment_Log_AP!$D$2:$D$753,">="&DATE(2026,4,27),Payment_Log_AP!$D$2:$D$753,"<"&DATE(2026,5,4)) -> 13689.02 | C7: =SUMIFS(Cash_Receipts_AR!$E$2:$E$503,Cash_Receipts_AR!$D$2:$D$503,">="&DATE(2026,4,27),Cash_Receipts_AR!$D$2:$D$503,"<"&DATE(2026,5,4)) -> 19786.3 | D7: =COUNTIFS(3Way_Match!$L$5:$L$854,"EXCEPTION",3Way_Match!$D$5:$D$854,">="&DATE(2026,4,27),3Way_Match!$D$5:$D$854,"<"&DATE(2026,5,4)) -> 1 | E7: =COUNTIFS(Duplicate_Payments!$H$5:$H$885,"DUPLICATE*") -> 16 | F7: =COUNTIFS(SoD_Check!$G$5:$G$854,"VIOLATION*",SoD_Check!$C$5:$C$854,">="&DATE(2026,4,27),SoD_Check!$C$5:$C$854,"<"&DATE(2026,5,4)) -> 0 | G7: =COUNTIFS(Risk_Scoring!$M$5:$M$756,"High",Risk_Scoring!$F$5:$F$756,">="&DATE(2026,4,27),Risk_Scoring!$F$5:$F$756,"<"&DATE(2026,5,4)) -> 0 | H7: =COUNTIFS(Purchase_Orders!$C$2:$C$851,">="&DATE(2026,4,27),Purchase_Orders!$C$2:$C$851,"<"&DATE(2026,5,4)) -> 3
A8: Wk of 04-May-2026 | B8: =SUMIFS(Payment_Log_AP!$E$2:$E$753,Payment_Log_AP!$D$2:$D$753,">="&DATE(2026,5,4),Payment_Log_AP!$D$2:$D$753,"<"&DATE(2026,5,11)) -> 53070.05 | C8: =SUMIFS(Cash_Receipts_AR!$E$2:$E$503,Cash_Receipts_AR!$D$2:$D$503,">="&DATE(2026,5,4),Cash_Receipts_AR!$D$2:$D$503,"<"&DATE(2026,5,11)) -> 25770.78 | D8: =COUNTIFS(3Way_Match!$L$5:$L$854,"EXCEPTION",3Way_Match!$D$5:$D$854,">="&DATE(2026,5,4),3Way_Match!$D$5:$D$854,"<"&DATE(2026,5,11)) -> 1 | E8: =COUNTIFS(Duplicate_Payments!$H$5:$H$885,"DUPLICATE*") -> 16 | F8: =COUNTIFS(SoD_Check!$G$5:$G$854,"VIOLATION*",SoD_Check!$C$5:$C$854,">="&DATE(2026,5,4),SoD_Check!$C$5:$C$854,"<"&DATE(2026,5,11)) -> 0 | G8: =COUNTIFS(Risk_Scoring!$M$5:$M$756,"High",Risk_Scoring!$F$5:$F$756,">="&DATE(2026,5,4),Risk_Scoring!$F$5:$F$756,"<"&DATE(2026,5,11)) -> 0 | H8: =COUNTIFS(Purchase_Orders!$C$2:$C$851,">="&DATE(2026,5,4),Purchase_Orders!$C$2:$C$851,"<"&DATE(2026,5,11)) -> 9
A9: Wk of 11-May-2026 | B9: =SUMIFS(Payment_Log_AP!$E$2:$E$753,Payment_Log_AP!$D$2:$D$753,">="&DATE(2026,5,11),Payment_Log_AP!$D$2:$D$753,"<"&DATE(2026,5,18)) -> 16055.43 | C9: =SUMIFS(Cash_Receipts_AR!$E$2:$E$503,Cash_Receipts_AR!$D$2:$D$503,">="&DATE(2026,5,11),Cash_Receipts_AR!$D$2:$D$503,"<"&DATE(2026,5,18)) -> 22657.33 | D9: =COUNTIFS(3Way_Match!$L$5:$L$854,"EXCEPTION",3Way_Match!$D$5:$D$854,">="&DATE(2026,5,11),3Way_Match!$D$5:$D$854,"<"&DATE(2026,5,18)) -> 3 | E9: =COUNTIFS(Duplicate_Payments!$H$5:$H$885,"DUPLICATE*") -> 16 | F9: =COUNTIFS(SoD_Check!$G$5:$G$854,"VIOLATION*",SoD_Check!$C$5:$C$854,">="&DATE(2026,5,11),SoD_Check!$C$5:$C$854,"<"&DATE(2026,5,18)) -> 0 | G9: =COUNTIFS(Risk_Scoring!$M$5:$M$756,"High",Risk_Scoring!$F$5:$F$756,">="&DATE(2026,5,11),Risk_Scoring!$F$5:$F$756,"<"&DATE(2026,5,18)) -> 0 | H9: =COUNTIFS(Purchase_Orders!$C$2:$C$851,">="&DATE(2026,5,11),Purchase_Orders!$C$2:$C$851,"<"&DATE(2026,5,18)) -> 9
A10: Wk of 18-May-2026 | B10: =SUMIFS(Payment_Log_AP!$E$2:$E$753,Payment_Log_AP!$D$2:$D$753,">="&DATE(2026,5,18),Payment_Log_AP!$D$2:$D$753,"<"&DATE(2026,5,25)) -> 32196.77 | C10: =SUMIFS(Cash_Receipts_AR!$E$2:$E$503,Cash_Receipts_AR!$D$2:$D$503,">="&DATE(2026,5,18),Cash_Receipts_AR!$D$2:$D$503,"<"&DATE(2026,5,25)) -> 10101.72 | D10: =COUNTIFS(3Way_Match!$L$5:$L$854,"EXCEPTION",3Way_Match!$D$5:$D$854,">="&DATE(2026,5,18),3Way_Match!$D$5:$D$854,"<"&DATE(2026,5,25)) -> 2 | E10: =COUNTIFS(Duplicate_Payments!$H$5:$H$885,"DUPLICATE*") -> 16 | F10: =COUNTIFS(SoD_Check!$G$5:$G$854,"VIOLATION*",SoD_Check!$C$5:$C$854,">="&DATE(2026,5,18),SoD_Check!$C$5:$C$854,"<"&DATE(2026,5,25)) -> 0 | G10: =COUNTIFS(Risk_Scoring!$M$5:$M$756,"High",Risk_Scoring!$F$5:$F$756,">="&DATE(2026,5,18),Risk_Scoring!$F$5:$F$756,"<"&DATE(2026,5,25)) -> 0 | H10: =COUNTIFS(Purchase_Orders!$C$2:$C$851,">="&DATE(2026,5,18),Purchase_Orders!$C$2:$C$851,"<"&DATE(2026,5,25)) -> 8
A11: Wk of 25-May-2026 | B11: =SUMIFS(Payment_Log_AP!$E$2:$E$753,Payment_Log_AP!$D$2:$D$753,">="&DATE(2026,5,25),Payment_Log_AP!$D$2:$D$753,"<"&DATE(2026,6,1)) -> 22291.28 | C11: =SUMIFS(Cash_Receipts_AR!$E$2:$E$503,Cash_Receipts_AR!$D$2:$D$503,">="&DATE(2026,5,25),Cash_Receipts_AR!$D$2:$D$503,"<"&DATE(2026,6,1)) -> 18319.62 | D11: =COUNTIFS(3Way_Match!$L$5:$L$854,"EXCEPTION",3Way_Match!$D$5:$D$854,">="&DATE(2026,5,25),3Way_Match!$D$5:$D$854,"<"&DATE(2026,6,1)) -> 1 | E11: =COUNTIFS(Duplicate_Payments!$H$5:$H$885,"DUPLICATE*") -> 16 | F11: =COUNTIFS(SoD_Check!$G$5:$G$854,"VIOLATION*",SoD_Check!$C$5:$C$854,">="&DATE(2026,5,25),SoD_Check!$C$5:$C$854,"<"&DATE(2026,6,1)) -> 1 | G11: =COUNTIFS(Risk_Scoring!$M$5:$M$756,"High",Risk_Scoring!$F$5:$F$756,">="&DATE(2026,5,25),Risk_Scoring!$F$5:$F$756,"<"&DATE(2026,6,1)) -> 0 | H11: =COUNTIFS(Purchase_Orders!$C$2:$C$851,">="&DATE(2026,5,25),Purchase_Orders!$C$2:$C$851,"<"&DATE(2026,6,1)) -> 10
A12: Wk of 01-Jun-2026 | B12: =SUMIFS(Payment_Log_AP!$E$2:$E$753,Payment_Log_AP!$D$2:$D$753,">="&DATE(2026,6,1),Payment_Log_AP!$D$2:$D$753,"<"&DATE(2026,6,8)) -> 52557.1 | C12: =SUMIFS(Cash_Receipts_AR!$E$2:$E$503,Cash_Receipts_AR!$D$2:$D$503,">="&DATE(2026,6,1),Cash_Receipts_AR!$D$2:$D$503,"<"&DATE(2026,6,8)) -> 23406.23 | D12: =COUNTIFS(3Way_Match!$L$5:$L$854,"EXCEPTION",3Way_Match!$D$5:$D$854,">="&DATE(2026,6,1),3Way_Match!$D$5:$D$854,"<"&DATE(2026,6,8)) -> 1 | E12: =COUNTIFS(Duplicate_Payments!$H$5:$H$885,"DUPLICATE*") -> 16 | F12: =COUNTIFS(SoD_Check!$G$5:$G$854,"VIOLATION*",SoD_Check!$C$5:$C$854,">="&DATE(2026,6,1),SoD_Check!$C$5:$C$854,"<"&DATE(2026,6,8)) -> 0 | G12: =COUNTIFS(Risk_Scoring!$M$5:$M$756,"High",Risk_Scoring!$F$5:$F$756,">="&DATE(2026,6,1),Risk_Scoring!$F$5:$F$756,"<"&DATE(2026,6,8)) -> 1 | H12: =COUNTIFS(Purchase_Orders!$C$2:$C$851,">="&DATE(2026,6,1),Purchase_Orders!$C$2:$C$851,"<"&DATE(2026,6,8)) -> 10
A13: Wk of 08-Jun-2026 | B13: =SUMIFS(Payment_Log_AP!$E$2:$E$753,Payment_Log_AP!$D$2:$D$753,">="&DATE(2026,6,8),Payment_Log_AP!$D$2:$D$753,"<"&DATE(2026,6,15)) -> 17913.22 | C13: =SUMIFS(Cash_Receipts_AR!$E$2:$E$503,Cash_Receipts_AR!$D$2:$D$503,">="&DATE(2026,6,8),Cash_Receipts_AR!$D$2:$D$503,"<"&DATE(2026,6,15)) -> 14694.82 | D13: =COUNTIFS(3Way_Match!$L$5:$L$854,"EXCEPTION",3Way_Match!$D$5:$D$854,">="&DATE(2026,6,8),3Way_Match!$D$5:$D$854,"<"&DATE(2026,6,15)) -> 1 | E13: =COUNTIFS(Duplicate_Payments!$H$5:$H$885,"DUPLICATE*") -> 16 | F13: =COUNTIFS(SoD_Check!$G$5:$G$854,"VIOLATION*",SoD_Check!$C$5:$C$854,">="&DATE(2026,6,8),SoD_Check!$C$5:$C$854,"<"&DATE(2026,6,15)) -> 0 | G13: =COUNTIFS(Risk_Scoring!$M$5:$M$756,"High",Risk_Scoring!$F$5:$F$756,">="&DATE(2026,6,8),Risk_Scoring!$F$5:$F$756,"<"&DATE(2026,6,15)) -> 1 | H13: =COUNTIFS(Purchase_Orders!$C$2:$C$851,">="&DATE(2026,6,8),Purchase_Orders!$C$2:$C$851,"<"&DATE(2026,6,15)) -> 15
A14: Wk of 15-Jun-2026 | B14: =SUMIFS(Payment_Log_AP!$E$2:$E$753,Payment_Log_AP!$D$2:$D$753,">="&DATE(2026,6,15),Payment_Log_AP!$D$2:$D$753,"<"&DATE(2026,6,22)) -> 13767.43 | C14: =SUMIFS(Cash_Receipts_AR!$E$2:$E$503,Cash_Receipts_AR!$D$2:$D$503,">="&DATE(2026,6,15),Cash_Receipts_AR!$D$2:$D$503,"<"&DATE(2026,6,22)) -> 29971.4 | D14: =COUNTIFS(3Way_Match!$L$5:$L$854,"EXCEPTION",3Way_Match!$D$5:$D$854,">="&DATE(2026,6,15),3Way_Match!$D$5:$D$854,"<"&DATE(2026,6,22)) -> 2 | E14: =COUNTIFS(Duplicate_Payments!$H$5:$H$885,"DUPLICATE*") -> 16 | F14: =COUNTIFS(SoD_Check!$G$5:$G$854,"VIOLATION*",SoD_Check!$C$5:$C$854,">="&DATE(2026,6,15),SoD_Check!$C$5:$C$854,"<"&DATE(2026,6,22)) -> 0 | G14: =COUNTIFS(Risk_Scoring!$M$5:$M$756,"High",Risk_Scoring!$F$5:$F$756,">="&DATE(2026,6,15),Risk_Scoring!$F$5:$F$756,"<"&DATE(2026,6,22)) -> 0 | H14: =COUNTIFS(Purchase_Orders!$C$2:$C$851,">="&DATE(2026,6,15),Purchase_Orders!$C$2:$C$851,"<"&DATE(2026,6,22)) -> 11
A15: Wk of 22-Jun-2026 | B15: =SUMIFS(Payment_Log_AP!$E$2:$E$753,Payment_Log_AP!$D$2:$D$753,">="&DATE(2026,6,22),Payment_Log_AP!$D$2:$D$753,"<"&DATE(2026,6,29)) -> 20831.37 | C15: =SUMIFS(Cash_Receipts_AR!$E$2:$E$503,Cash_Receipts_AR!$D$2:$D$503,">="&DATE(2026,6,22),Cash_Receipts_AR!$D$2:$D$503,"<"&DATE(2026,6,29)) -> 38213.23 | D15: =COUNTIFS(3Way_Match!$L$5:$L$854,"EXCEPTION",3Way_Match!$D$5:$D$854,">="&DATE(2026,6,22),3Way_Match!$D$5:$D$854,"<"&DATE(2026,6,29)) -> 2 | E15: =COUNTIFS(Duplicate_Payments!$H$5:$H$885,"DUPLICATE*") -> 16 | F15: =COUNTIFS(SoD_Check!$G$5:$G$854,"VIOLATION*",SoD_Check!$C$5:$C$854,">="&DATE(2026,6,22),SoD_Check!$C$5:$C$854,"<"&DATE(2026,6,29)) -> 0 | G15: =COUNTIFS(Risk_Scoring!$M$5:$M$756,"High",Risk_Scoring!$F$5:$F$756,">="&DATE(2026,6,22),Risk_Scoring!$F$5:$F$756,"<"&DATE(2026,6,29)) -> 0 | H15: =COUNTIFS(Purchase_Orders!$C$2:$C$851,">="&DATE(2026,6,22),Purchase_Orders!$C$2:$C$851,"<"&DATE(2026,6,29)) -> 8
A16: Wk of 29-Jun-2026 | B16: =SUMIFS(Payment_Log_AP!$E$2:$E$753,Payment_Log_AP!$D$2:$D$753,">="&DATE(2026,6,29),Payment_Log_AP!$D$2:$D$753,"<"&DATE(2026,7,6)) -> 51718.39 | C16: =SUMIFS(Cash_Receipts_AR!$E$2:$E$503,Cash_Receipts_AR!$D$2:$D$503,">="&DATE(2026,6,29),Cash_Receipts_AR!$D$2:$D$503,"<"&DATE(2026,7,6)) -> 4069.65 | D16: =COUNTIFS(3Way_Match!$L$5:$L$854,"EXCEPTION",3Way_Match!$D$5:$D$854,">="&DATE(2026,6,29),3Way_Match!$D$5:$D$854,"<"&DATE(2026,7,6)) -> 0 | E16: =COUNTIFS(Duplicate_Payments!$H$5:$H$885,"DUPLICATE*") -> 16 | F16: =COUNTIFS(SoD_Check!$G$5:$G$854,"VIOLATION*",SoD_Check!$C$5:$C$854,">="&DATE(2026,6,29),SoD_Check!$C$5:$C$854,"<"&DATE(2026,7,6)) -> 0 | G16: =COUNTIFS(Risk_Scoring!$M$5:$M$756,"High",Risk_Scoring!$F$5:$F$756,">="&DATE(2026,6,29),Risk_Scoring!$F$5:$F$756,"<"&DATE(2026,7,6)) -> 0 | H16: =COUNTIFS(Purchase_Orders!$C$2:$C$851,">="&DATE(2026,6,29),Purchase_Orders!$C$2:$C$851,"<"&DATE(2026,7,6)) -> 3
A18: Note: Duplicate Payment Flags is a running total (not period-bound) since a duplicate is identified by invoice, not by date.

Sheet KPI_Dashboard
A1: Finance Operations — KPI Dashboard
A2: One-page snapshot as of Assumptions!B5. This is the tab the VBA macro exports to PDF and emails out.
B4: AP Outstanding (Total) | E4: AR Outstanding (Total) | H4: DPO (days)
B5: =SUM(AP_Aging!$B$890:$B$893) -> 569517.22 | E5: =SUM(AR_Aging!$B$609:$B$612) -> 430247.17 | H5: =DPO_Summary!$B$8 -> 103.58317
B8: DSO (days) | E8: 3-Way Match Exceptions | H8: Duplicate Payment Flags
B9: =DSO_Summary!$B$8 -> 100.51921 | E9: =COUNTIF(3Way_Match!$L$5:$L$854,"EXCEPTION") -> 160 | H9: =COUNTIF(Duplicate_Payments!$H$5:$H$885,"DUPLICATE*") -> 16
B12: SoD Violations | E12: High-Risk Transactions | H12: New-Vendor Risk Flags
B13: =SoD_Check!$B$857 -> 21 | E13: =Risk_Scoring!$B$760 -> 21 | H13: =New_Vendor_Risk!$B$47 -> 0
B16: Bank Recon Unmatched/Unexplained Items | E16: AR 90+ Days Overdue ($) | H16: Overall Audit Status
B17: =COUNTIF(Bank_Reconciliation!$H$6:$H$757,"Unmatched*")+COUNTIF(Bank_Reconciliation!$G$762:$G$1543,"Unexplained*") -> 30 | E17: =AR_Aging!$B$612 -> 323070.04 | H17: =RCM!$B$14 -> REVIEW REQUIRED - One or more controls FAILED
B23: AP Aging Mix | E23: AR Aging Mix
B24: Bucket | C24: $ | E24: Bucket | F24: $
B25: 0-30 | C25: =AP_Aging!B890 -> 248495.64 | E25: 0-30 | F25: =AR_Aging!B609 -> 36608.27
B26: 31-60 | C26: =AP_Aging!B891 -> 15605.37 | E26: 31-60 | F26: =AR_Aging!B610 -> 46667.73
B27: 61-90 | C27: =AP_Aging!B892 -> 24163.94 | E27: 61-90 | F27: =AR_Aging!B611 -> 23901.13
B28: 90+ | C28: =AP_Aging!B893 -> 281252.27 | E28: 90+ | F28: =AR_Aging!B612 -> 323070.04
